Workbook
Name S: #REF!
Name S: #REF!
Name S: #REF!
Name S: #REF!
Name S: #REF!
Name S: #REF!
Name S: #REF!
Name S: #REF!
Name S: #REF!
Name S: #REF!
Name S: #REF!

Sheet Piamonte HVCDP
A1: District | C1: Barangay | D1: Farmers Served (No.) | E1: Existing Area (ha) | N1: Farmers Served (No.) | O1: Expansion Area (ha) | X1: REMARKS
E2: Area Planted (ha) | H2: Area Harvested (ha) | K2: Production (MT) | O2: Area Planted (ha) | R2: Area Harvested (ha) | U2: Production (MT)
E4: Previous | F4: This Mo. | G4: To Date | H4: Previous | I4: This Mo. | J4: To Date | K4: Previous | L4: This Mo. | M4: To Date | O4: Previous | P4: This Mo. | Q4: To Date | R4: Previous | S4: This Mo. | T4: To Date | U4: Previous | V4: This Mo. | W4: To Date
A5: III | B5: FRUIT VEGETABLES
B6: Eggplant | C6: Altura Matanda
C7: Altura South
C8: Banadero | D8: 3 | E8: 1.4 | G8: 1.4 | H8: 1.4 | J8: 1.4 | K8: 15.4 | M8: 15.4
C9: Bilog Bilog | D9: 3 | E9: 1.3 | G9: 1.3 | I9: 0.4 | J9: 0.4 | L9: 0.44 | M9: 0.44
C10: Luyos
C11: Malaking Pulo
C12: Montana | D12: 7 | E12: 3.2 | F12: 1.2 | G12: 4.4 | H12: 2.7 | J12: 2.7 | K12: 28.9 | M12: 28.9
C13: Sala
C14: Santol | D14: 4 | E14: 2.55 | G14: 2.55 | H14: 3.05 | J14: 3.05 | K14: 27.6 | M14: 27.6
C15: Sulpoc | D15: 1 | F15: 0.9 | G15: 0.9
C16: TOTAL | D16: =SUM(D6:D15) -> 18 | E16: =SUM(E6:E15) -> 8.45 | F16: =SUM(F6:F15) -> 2.1 | G16: =SUM(G6:G15) -> 10.55 | H16: =SUM(H6:H15) -> 7.15 | I16: =SUM(I6:I15) -> 0.4 | J16: =SUM(J6:J15) -> 7.55 | K16: =SUM(K6:K15) -> 71.9 | ... W16: =SUM(W6:W15) -> 0
B17: Sitao | C17: Altura Matanda
C18: Altura South
C19: Banadero | D19: 1 | E19: 0.35 | G19: 0.35
C20: Bilog Bilog | D20: 36 | E20: 16.35 | F20: 0.25 | G20: 16.6 | H20: 8.15 | J20: 8.15 | K20: 33.7 | M20: 33.7
C21: Luyos
C22: Malaking Pulo
C23: Montana | D23: 7 | E23: 2.52 | G23: 2.52 | H23: 1.57 | J23: 1.57 | K23: 16.62 | M23: 16.62
C24: Sala | D24: 5 | E24: 0.85 | G24: 0.85 | H24: 0.35 | J24: 0.35 | K24: 4.2 | M24: 4.2
C25: Santol | D25: 3 | E25: 0.8 | G25: 0.8 | H25: 1.35 | J25: 1.35 | K25: 11.2 | M25: 11.2
C26: Sulpoc | D26: 8 | E26: 2.95 | F26: 1 | G26: 3.95 | H26: 2.55 | J26: 2.55 | K26: 25.6 | M26: 25.6
C27: TOTAL | D27: =SUM(D17:D26) -> 60 | E27: =SUM(E17:E26) -> 23.82 | F27: =SUM(F17:F26) -> 1.25 | G27: =SUM(G17:G26) -> 25.07 | H27: =SUM(H17:H26) -> 13.97 | I27: =SUM(I17:I26) -> 0 | J27: =SUM(J17:J26) -> 13.97 | K27: =SUM(K17:K26) -> 91.32 | ... W27: =SUM(W17:W26) -> 0
B28: Squash | C28: Altura Matanda | D28: 3 | E28: 1.4 | G28: 1.4 | H28: 1.4 | J28: 1.4 | K28: 14 | M28: 14
C29: Altura South
C30: Banadero
C31: Bilog Bilog | D31: 17 | E31: 7.25 | F31: 0.5 | G31: 7.75 | H31: 2.25 | J31: 2.25 | K31: 15.3 | M31: 15.3
C32: Luyos | D32: 3 | E32: 0.4 | F32: 0.7 | G32: 1.1 | H32: 0.4 | J32: 0.4 | K32: 4 | M32: 4
C33: Malaking Pulo
C34: Montana | D34: 2 | E34: 1.25 | G34: 1.25 | H34: 0.25 | J34: 0.25 | K34: 2.5 | M34: 2.5
C35: Sala | D35: 2 | E35: 0.5 | G35: 0.5 | H35: 0.6 | J35: 0.6 | K35: 6 | M35: 6
C36: Santol
C37: Sulpoc | D37: 2 | E37: 0.8 | G37: 0.8 | H37: 0.8 | J37: 0.8 | K37: 8 | M37: 8
C38: TOTAL | D38: =SUM(D28:D37) -> 29 | E38: =SUM(E28:E37) -> 11.6 | F38: =SUM(F28:F37) -> 1.2 | G38: =SUM(G28:G37) -> 12.8 | H38: =SUM(H28:H37) -> 5.7 | I38: =SUM(I28:I37) -> 0 | J38: =SUM(J28:J37) -> 5.7 | K38: =SUM(K28:K37) -> 49.8 | ... W38: =SUM(W28:W37) -> 0
B39: Okra | C39: Altura Matanda
C40: Altura South
C41: Banadero
C42: Bilog Bilog | D42: 1 | E42: 0.4 | G42: 0.4
C43: Luyos | D43: 2 | E43: 0.6 | G43: 0.6 | H43: 0.35 | J43: 0.35 | K43: 0.18 | M43: 0.18
C44: Malaking Pulo
C45: Montana
C46: Sala
C47: Santol | D47: 6 | E47: 2.05 | G47: 2.05 | H47: 2.9 | J47: 2.9 | K47: 21.3 | M47: 21.3
C48: Sulpoc | D48: 2 | E48: 1 | G48: 1 | I48: 0.5 | J48: 0.5 | L48: 0.5 | M48: 0.5
C49: TOTAL | D49: =SUM(D39:D48) -> 11 | E49: =SUM(E39:E48) -> 4.05 | F49: =SUM(F39:F48) -> 0 | G49: =SUM(G39:G48) -> 4.05 | H49: =SUM(H39:H48) -> 3.25 | I49: =SUM(I39:I48) -> 0.5 | J49: =SUM(J39:J48) -> 3.75 | K49: =SUM(K39:K48) -> 21.48 | ... W49: =SUM(W39:W48) -> 0
A50: III | B50: Patola | C50: Altura Matanda
C51: Altura South | D51: 4 | E51: 0.9 | G51: 0.9
C52: Banadero
C53: Bilog Bilog | D53: 10 | E53: 3.35 | G53: 3.35 | H53: 0.9 | J53: 0.9 | K53: 7.6 | M53: 7.6
C54: Luyos
C55: Malaking Pulo
C56: Montana | D56: 2 | E56: 0.2 | G56: 0.2 | H56: 0.1 | J56: 0.1 | K56: 0.8 | M56: 0.8
C57: Sala | D57: 1 | E57: 0.05 | G57: 0.05
C58: Santol
C59: Sulpoc | D59: 9 | E59: 3.68 | F59: 0.5 | G59: 4.18 | H59: 2.85 | J59: 2.85 | K59: 22.8 | M59: 22.8
C60: TOTAL | D60: =SUM(D50:D59) -> 26 | E60: =SUM(E50:E59) -> 8.18 | F60: =SUM(F50:F59) -> 0.5 | G60: =SUM(G50:G59) -> 8.68 | H60: =SUM(H50:H59) -> 3.85 | I60: =SUM(I50:I59) -> 0 | J60: =SUM(J50:J59) -> 3.85 | K60: =SUM(K50:K59) -> 31.2 | ... W60: =SUM(W50:W59) -> 0
B61: Sigarilyas | C61: Altura Matanda
C62: Altura South | D62: 2 | E62: 0.5 | G62: 0.5
C63: Banadero
C64: Bilog Bilog | D64: 7 | E64: 1.95 | G64: 1.95 | H64: 0.95 | J64: 0.95 | K64: 0.9 | M64: 0.9
C65: Luyos | D65: 3 | E65: 1.4 | G65: 1.4 | H65: 1.7 | J65: 1.7 | K65: 1.7 | M65: 1.7
C66: Malaking Pulo
C67: Montana | D67: 6 | E67: 4.65 | G67: 4.65 | H67: 2.5 | J67: 2.5 | K67: 4.7 | M67: 4.7
C68: Sala | D68: 2 | E68: 0.75 | G68: 0.75 | H68: 0.75 | J68: 0.75 | K68: 7.5 | M68: 7.5
C69: Santol
C70: Sulpoc | D70: 14 | E70: 7.85 | G70: 7.85 | H70: 10.4 | J70: 10.4 | K70: 50.6 | M70: 50.6
C71: TOTAL | D71: =SUM(D61:D70) -> 34 | E71: =SUM(E61:E70) -> 17.1 | F71: =SUM(F61:F70) -> 0 | G71: =SUM(G61:G70) -> 17.1 | H71: =SUM(H61:H70) -> 16.3 | I71: =SUM(I61:I70) -> 0 | J71: =SUM(J61:J70) -> 16.3 | K71: =SUM(K61:K70) -> 65.4 | ... W71: =SUM(W61:W70) -> 0
B72: Upo | C72: Altura Matanda
C73: Altura South
C74: Banadero
C75: Bilog Bilog | D75: 8 | E75: 2.6 | F75: 0.3 | G75: 2.9 | H75: 1.75 | J75: 1.75 | K75: 10.8 | M75: 10.8
C76: Luyos | D76: 4 | E76: 1.2 | G76: 1.2 | H76: 0.4 | J76: 0.4 | K76: 4.8 | M76: 4.8
C77: Malaking Pulo
C78: Montana | D78: 5 | E78: 1.75 | F78: 1 | G78: 2.75 | H78: 0.95 | J78: 0.95 | K78: 11.4 | M78: 11.4
C79: Sala
C80: Santol
C81: Sulpoc
C82: TOTAL | D82: =SUM(D72:D81) -> 17 | E82: =SUM(E72:E81) -> 5.55 | F82: =SUM(F72:F81) -> 1.3 | G82: =SUM(G72:G81) -> 6.85 | H82: =SUM(H72:H81) -> 3.1 | I82: =SUM(I72:I81) -> 0 | J82: =SUM(J72:J81) -> 3.1 | K82: =SUM(K72:K81) -> 27 | ... W82: =SUM(W72:W81) -> 0
B83: Ampalaya | C83: Altura Matanda | D83: 1 | E83: 0.7 | G83: 0.7 | H83: 0.7 | J83: 0.7 | K83: 0.7 | M83: 0.7
C84: Altura South
C85: Banadero
C86: Bilog Bilog | D86: 7 | E86: 4.3 | G86: 4.3 | H86: 2.4 | J86: 2.4 | K86: 2.3 | M86: 2.3
C87: Luyos | D87: 1 | E87: 0.05 | G87: 0.05 | H87: 0.05 | J87: 0.05 | K87: 0.5 | M87: 0.5
C88: Malaking Pulo
C89: Montana | D89: 2 | E89: 0.4 | G89: 0.4 | H89: 0.4 | J89: 0.4 | K89: 4 | M89: 4
C90: Sala | D90: 1 | E90: 0.25 | G90: 0.25
C91: Santol | D91: 3 | E91: 1.35 | G91: 1.35 | H91: 1.35 | J91: 1.35 | K91: 13 | M91: 13
C92: Sulpoc | D92: 3 | E92: 0.95 | F92: 0.5 | G92: 1.45 | H92: 0.45 | J92: 0.45 | K92: 2.7 | M92: 2.7
C93: TOTAL | D93: =SUM(D83:D92) -> 18 | E93: =SUM(E83:E92) -> 8 | F93: =SUM(F83:F92) -> 0.5 | G93: =SUM(G83:G92) -> 8.5 | H93: =SUM(H83:H92) -> 5.35 | I93: =SUM(I83:I92) -> 0 | J93: =SUM(J83:J92) -> 5.35 | K93: =SUM(K83:K92) -> 23.2 | ... W93: =SUM(W83:W92) -> 0
A94: III | B94: Pipino | C94: Altura Matanda
C95: Altura South
C96: Banadero
C97: Bilog Bilog | D97: 6 | E97: 1.9 | G97: 1.9 | H97: 0.3 | J97: 0.3 | K97: 0.45 | M97: 0.45
C98: Luyos
C99: Malaking Pulo
C100: Montana
C101: Sala
...

Sheet Requizo HVCDP
A1: District | B1: Commodity | C1: Barangay | D1: Farmers Served (No.) | E1: Existing Area (ha) | N1: Farmers Served (No.) | O1: Expansion Area (ha) | X1: REMARKS
E2: Area Planted (ha) | H2: Area Harvested (ha) | K2: Production (MT) | O2: Area Planted (ha) | R2: Area Harvested (ha) | U2: Production (MT)
E4: Previous | F4: This Mo. | G4: To Date | H4: Previous | I4: This Mo. | J4: To Date | K4: Previous | L4: This Mo. | O4: Previous | P4: This Mo. | Q4: To Date | R4: Previous | S4: This Mo. | T4: To Date | U4: Previous | V4: This Mo. | W4: To Date
B5: FRUIT VEGETABLES
B6: Eggplant | C6: Altura Bata | D6: 2 | E6: 0.3 | G6: 0.3 | H6: 0.3 | J6: 0.3 | K6: 3.3 | M6: 3.3
C7: Ambulong | D7: 1 | E7: 1 | G7: 1
C8: Gonzales | D8: 1 | E8: 0.33 | G8: 0.33 | H8: 0.33 | J8: 0.33 | K8: 3.43 | M8: 3.43
C9: Janopol Occ
C10: Janopol Or
C11: Pantay Matanda
C12: San Jose | D12: 13 | E12: 4.35 | G12: 4.35 | H12: 0.95 | J12: 0.95 | K12: 10.45 | M12: 10.45 | X12: 1.7 Damaged by Kristine
C13: Santor
C14: Talaga | D14: 1 | E14: 0.25 | G14: 0.25 | H14: 0.25 | J14: 0.25 | K14: 2.75 | M14: 2.75
C15: Trapiche | D15: 1 | E15: 0.2 | G15: 0.2 | H15: 0.2 | J15: 0.2 | K15: 2.2 | M15: 2.2
C16: TOTAL | D16: =SUM(D6:D15) -> 19 | E16: =SUM(E6:E15) -> 6.43 | F16: =SUM(F6:F15) -> 0 | G16: =SUM(G6:G15) -> 6.43 | H16: =SUM(H6:H15) -> 2.03 | I16: =SUM(I6:I15) -> 0 | J16: =SUM(J6:J15) -> 2.03 | K16: =SUM(K6:K15) -> 22.13 | ... W16: =SUM(W6:W15) -> 0
B17: Sitao | C17: Altura Bata | D17: 1 | E17: 0.4 | G17: 0.4 | H17: 0.4 | J17: 0.4 | K17: 4 | M17: 4
C18: Ambulong | D18: 4 | E18: 1.25 | G18: 1.25 | H18: 1.25 | J18: 1.25 | K18: 8.5 | M18: 8.5
C19: Gonzales | D19: 1 | E19: 0.1 | G19: 0.1 | H19: 0.1 | J19: 0.1 | K19: 1 | M19: 1
C20: Janopol Occ | D20: 2 | E20: 0.5 | G20: 0.5 | X20: 0.5 Ha Damaged by Krisitne
C21: Janopol Or | D21: 0
C22: Pantay Matanda | D22: 0
C23: San Jose | D23: 13 | E23: 3.75 | G23: 3.75 | H23: 2.85 | J23: 2.85 | K23: 32.6 | M23: 32.6 | X23: 0.9 Damaged by Kristine
C24: Santor | D24: 2 | E24: 0.55 | G24: 0.55 | H24: 0.55 | J24: 0.55 | K24: 5.5 | M24: 5.5
C25: Talaga | D25: 0
C26: Trapiche | D26: 1 | E26: 0.1 | G26: 0.1
C27: TOTAL | D27: =SUM(D17:D26) -> 24 | E27: =SUM(E17:E26) -> 6.65 | F27: =SUM(F17:F26) -> 0 | G27: =SUM(G17:G26) -> 6.65 | H27: =SUM(H17:H26) -> 5.15 | I27: =SUM(I17:I26) -> 0 | J27: =SUM(J17:J26) -> 5.15 | K27: =SUM(K17:K26) -> 51.6 | ... W27: =SUM(W17:W26) -> 0
B28: Squash | C28: Altura Bata | D28: 1 | E28: 0.4 | G28: 0.4 | H28: 0.4 | J28: 0.4 | K28: 10 | M28: 10
C29: Ambulong | D29: 4 | E29: 4.85 | G29: 4.85 | H29: 4.45 | J29: 4.45 | K29: 45 | M29: 45
C30: Gonzales | D30: 1 | E30: 0.5 | G30: 0.5 | H30: 0.5 | J30: 0.5 | K30: 5 | M30: 5
C31: Janopol Occ | D31: 1 | E31: 0.25 | G31: 0.25 | X31: 0.25 Ha Damaged by Kristine
C32: Janopol Or | D32: 1 | E32: 0.1 | G32: 0.1 | H32: 0.1 | J32: 0.1 | K32: 1 | M32: 1
C33: Pantay Matanda | D33: 3 | E33: 0.85 | G33: 0.85 | H33: 0.25 | J33: 0.25 | K33: 2.5 | M33: 2.5
C34: San Jose | D34: 4 | E34: 1.2 | G34: 1.2 | H34: 0.7 | J34: 0.7 | K34: 7 | M34: 7 | X34: 0.5 Ha Damaged by Kristine
C35: Santor | D35: 1 | E35: 0.25 | G35: 0.25 | X35: 0.25 Ha Damaged by Kristine
C36: Talaga | D36: 3 | E36: 1 | G36: 1 | H36: 1 | J36: 1 | K36: 8 | M36: 8
C37: Trapiche | D37: 3 | E37: 0.65 | G37: 0.65 | H37: 0.45 | J37: 0.45 | K37: 4.5 | M37: 4.5
C38: TOTAL | D38: =SUM(D28:D37) -> 22 | E38: =SUM(E28:E37) -> 10.05 | F38: =SUM(F28:F37) -> 0 | G38: =SUM(G28:G37) -> 10.05 | H38: =SUM(H28:H37) -> 7.85 | I38: =SUM(I28:I37) -> 0 | J38: =SUM(J28:J37) -> 7.85 | K38: =SUM(K28:K37) -> 83 | ... W38: =SUM(W28:W37) -> 0
B39: Okra | C39: Altura Bata
C40: Ambulong
C41: Gonzales | D41: 1 | E41: 0.05 | G41: 0.05 | H41: 0.05 | J41: 0.05 | K41: 0.5 | M41: 0.5
C42: Janopol Occ | D42: 1 | E42: 0.35 | G42: 0.35 | H42: 0.35 | J42: 0.35 | K42: 3.5 | M42: 3.5
C43: Janopol Or
C44: Pantay Matanda
C45: San Jose | D45: 9 | E45: 2.85 | G45: 2.85 | H45: 2.3 | J45: 2.3 | K45: 11 | M45: 11 | X45: 0.55 Ha Damaged by Kristine
C46: Santor
C47: Talaga
C48: Trapiche
C49: TOTAL | D49: =SUM(D39:D48) -> 11 | E49: =SUM(E39:E48) -> 3.25 | F49: =SUM(F39:F48) -> 0 | G49: =SUM(G39:G48) -> 3.25 | H49: =SUM(H39:H48) -> 2.7 | I49: =SUM(I39:I48) -> 0 | J49: =SUM(J39:J48) -> 2.7 | K49: =SUM(K39:K48) -> 15 | ... W49: =SUM(W39:W48) -> 0
B50: Patola | C50: Altura Bata | D50: 3 | E50: 1.05 | G50: 1.05 | H50: 0.25 | J50: 0.25 | K50: 3.8 | M50: 3.8
C51: Ambulong | D51: 1 | E51: 0.25 | G51: 0.25 | H51: 0.25 | J51: 0.25 | K51: 2 | M51: 2
C52: Gonzales
C53: Janopol Occ
C54: Janopol Or
C55: Pantay Matanda
C56: San Jose
C57: Santor
C58: Talaga
C59: Trapiche | D59: 1 | E59: 0.1 | G59: 0.1 | H59: 0.1 | J59: 0.1 | K59: 0.8 | M59: 0.8
C60: TOTAL | D60: =SUM(D50:D59) -> 5 | E60: =SUM(E50:E59) -> 1.4 | F60: =SUM(F50:F59) -> 0 | G60: =SUM(G50:G59) -> 1.4 | H60: =SUM(H50:H59) -> 0.6 | I60: =SUM(I50:I59) -> 0 | J60: =SUM(J50:J59) -> 0.6 | K60: =SUM(K50:K59) -> 6.6 | ... W60: =SUM(W50:W59) -> 0
B61: Sigarilyas | C61: Altura Bata | D61: 2 | E61: 0.65 | G61: 0.65 | X61: 0.65 Ha Damaged by Kristine
C62: Ambulong
C63: Gonzales
C64: Janopol Occ
C65: Janopol Or
C66: Pantay Matanda
C67: San Jose | D67: 2 | E67: 0.5 | G67: 0.5 | H67: 0.5 | J67: 0.5 | K67: 4 | M67: 4
C68: Santor | D68: 1 | E68: 0.7 | G68: 0.7
C69: Talaga | D69: 1 | E69: 1 | G69: 1 | X69: 1.0 Ha Damaged by Kristine
C70: Trapiche
C71: TOTAL | D71: =SUM(D61:D70) -> 6 | E71: =SUM(E61:E70) -> 2.85 | F71: =SUM(F61:F70) -> 0 | G71: =SUM(G61:G70) -> 2.85 | H71: =SUM(H61:H70) -> 0.5 | I71: =SUM(I61:I70) -> 0 | J71: =SUM(J61:J70) -> 0.5 | K71: =SUM(K61:K70) -> 4 | ... W71: =SUM(W61:W70) -> 0
B72: Upo | C72: Altura Bata
C73: Ambulong | D73: 1 | E73: 0.25 | G73: 0.25 | H73: 0.25 | J73: 0.25 | K73: 3 | M73: 3
C74: Gonzales
C75: Janopol Occ
C76: Janopol Or
C77: Pantay Matanda
C78: San Jose | D78: 2 | E78: 0.3 | F78: 0.4 | G78: 0.7 | H78: 0.3 | J78: 0.3 | K78: 3.6 | M78: 3.6
C79: Santor
C80: Talaga
C81: Trapiche
C82: TOTAL | D82: =SUM(D72:D81) -> 3 | E82: =SUM(E72:E81) -> 0.55 | F82: =SUM(F72:F81) -> 0.4 | G82: =SUM(G72:G81) -> 0.95 | H82: =SUM(H72:H81) -> 0.55 | I82: =SUM(I72:I81) -> 0 | J82: =SUM(J72:J81) -> 0.55 | K82: =SUM(K72:K81) -> 6.6 | ... W82: =SUM(W72:W81) -> 0
B83: Ampalaya | C83: Altura Bata | D83: 3 | E83: 2.45 | G83: 2.45 | H83: 1.2 | J83: 1.2 | K83: 10 | M83: 10 | X83: 1.25 Ha Damaged by Kristine
C84: Ambulong
C85: Gonzales
C86: Janopol Occ
C87: Janopol Or
C88: Pantay Matanda
C89: San Jose | D89: 5 | E89: 1.15 | G89: 1.15 | H89: 0.68 | J89: 0.68 | K89: 6.8 | M89: 6.8 | X89: 0.22 Ha Damaged by Kristine
C90: Santor
C91: Talaga
C92: Trapiche
C93: TOTAL | D93: =SUM(D83:D92) -> 8 | E93: =SUM(E83:E92) -> 3.6 | F93: =SUM(F83:F92) -> 0 | G93: =SUM(G83:G92) -> 3.6 | H93: =SUM(H83:H92) -> 1.88 | I93: =SUM(I83:I92) -> 0 | J93: =SUM(J83:J92) -> 1.88 | K93: =SUM(K83:K92) -> 16.8 | ... W93: =SUM(W83:W92) -> 0
B94: Pipino | C94: Altura Bata
C95: Ambulong
C96: Gonzales
C97: Janopol Occ
C98: Janopol Or
C99: Pantay Matanda
C100: San Jose
C101: Santor
...

Sheet Lucido HVCDP
A1: District | B1: Commodity | C1: Barangay | D1: Farmers Served (No.) | E1: Existing Area (ha) | N1: Farmers Served (No.) | O1: Expansion Area (ha) | X1: REMARKS
E2: Area Planted (ha) | H2: Area Harvested (ha) | K2: Production (MT) | O2: Area Planted (ha) | R2: Area Harvested (ha) | U2: Production (MT)
E4: Previous | F4: This Mo. | G4: To Date | H4: Previous | I4: This Mo. | J4: To Date | K4: Previous | L4: This Mo. | M4: To Date | O4: Previous | P4: This Mo. | Q4: To Date | R4: Previous | S4: This Mo. | T4: To Date | U4: Previous | V4: This Mo. | W4: To Date
B5: FRUIT VEGETABLES
B6: Eggplant | C6: Banjo East
C7: Banjo West
C8: Boot
C9: Cale | D9: 3 | E9: 1.15 | G9: =+E9+F9 -> 1.15 | X9: 0.25 ha Damaged by STS Kristine
C10: Darasa
C11: Hidalgo
C12: Maugat | D12: 5 | E12: 4 | G12: =+E12+F12 -> 4 | H12: 0.5 | I12: 0.25 | J12: =SUM(H12+I12) -> 0.75 | K12: 5 | L12: 1.25 | M12: =SUM(K12+L12) -> 6.25 | X12: 1.25 ha- Damaged by STS Kristine
C13: Natatas | D13: 1 | E13: 0.1 | G13: =+E13+F13 -> 0.1
C14: Pantay Bata
C15: Suplang | D15: 2 | E15: 1.3 | G15: =+E15+F15 -> 1.3 | H15: 1.3 | J15: =SUM(H15+I15) -> 1.3 | K15: 13 | M15: =SUM(K15+L15) -> 13
C16: TOTAL | D16: =SUM(D6:D15) -> 11 | E16: =SUM(E6:E15) -> 6.55 | F16: =SUM(F6:F15) -> 0 | G16: =SUM(G6:G15) -> 6.55 | H16: =SUM(H6:H15) -> 1.8 | I16: =SUM(I6:I15) -> 0.25 | J16: =SUM(J6:J15) -> 2.05 | K16: =SUM(K6:K15) -> 18 | ... W16: =SUM(W6:W15) -> 0
B17: Sitao | C17: Banjo East
C18: Banjo West
C19: Boot | D19: 1 | F19: 0.5 | G19: =+E19+F19 -> 0.5
C20: Cale | D20: 10 | E20: 2.35 | F20: 0.55 | G20: =+E20+F20 -> 2.9 | H20: 2.1 | J20: =+H20+I20 -> 2.1 | K20: 20.5 | M20: =+K20+L20 -> 20.5 | X20: 0.25 ha- Damaged by STS Kristine
C21: Darasa | D21: 2 | E21: 0.35 | G21: =+E21+F21 -> 0.35 | H21: 0.35 | J21: =+H21+I21 -> 0.35 | K21: 3.5 | M21: =+K21+L21 -> 3.5
C22: Hidalgo
C23: Maugat | D23: 1 | E23: 0.4 | G23: =+E23+F23 -> 0.4 | H23: 0.4 | J23: =+H23+I23 -> 0.4 | K23: 4 | M23: =+K23+L23 -> 4
C24: Natatas | D24: 6 | E24: 1.7 | G24: =+E24+F24 -> 1.7 | H24: 1.7 | J24: =+H24+I24 -> 1.7 | K24: 17 | M24: =+K24+L24 -> 17
C25: Pantay Bata
C26: Suplang | D26: 5 | E26: 2.15 | G26: =+E26+F26 -> 2.15 | H26: 2.15 | J26: =SUM(H26+I26) -> 2.15 | K26: 21.5 | M26: =SUM(K26+L26) -> 21.5
C27: TOTAL | D27: =SUM(D17:D26) -> 25 | E27: =SUM(E17:E26) -> 6.95 | F27: =SUM(F17:F26) -> 1.05 | G27: =SUM(G17:G26) -> 8 | H27: =SUM(H17:H26) -> 6.7 | I27: =SUM(I17:I26) -> 0 | J27: =SUM(J17:J26) -> 6.7 | K27: =SUM(K17:K26) -> 66.5 | ... W27: =SUM(W17:W26) -> 0
B28: Squash | C28: Banjo East
C29: Banjo West
C30: Boot | D30: 1 | E30: 0.25 | G30: =+E30+F30 -> 0.25
C31: Cale | D31: 9 | E31: 1.1 | G31: =+E31+F31 -> 1.1 | X31: 0.50 ha Damaged by STS Kristine
C32: Darasa | D32: 1 | E32: 0.1 | G32: =+E32+F32 -> 0.1 | H32: 0.1 | J32: =+H32+I32 -> 0.1 | K32: 1 | M32: =+K32+L32 -> 1
C33: Hidalgo
C34: Maugat
C35: Natatas | D35: 3 | E35: 0.57 | G35: =+E35+F35 -> 0.57 | H35: 0.57 | J35: =+H35+I35 -> 0.57 | K35: 4.6 | M35: =+K35+L35 -> 4.6
C36: Pantay Bata | D36: 1 | E36: 0.15 | G36: 0.15 | H36: 0.15 | J36: =+H36+I36 -> 0.15 | K36: 1.5 | M36: =+K36+L36 -> 1.5
C37: Suplang | D37: 1 | E37: 0.15 | G37: =+E37+F37 -> 0.15 | H37: 0.15 | J37: =+H37+I37 -> 0.15 | K37: 1.5 | M37: =+K37+L37 -> 1.5
C38: TOTAL | D38: =SUM(D28:D37) -> 16 | E38: =SUM(E28:E37) -> 2.32 | F38: =SUM(F28:F37) -> 0 | G38: =SUM(G28:G37) -> 2.32 | H38: =SUM(H28:H37) -> 0.97 | I38: =SUM(I28:I37) -> 0 | J38: =SUM(J28:J37) -> 0.97 | K38: =SUM(K28:K37) -> 8.6 | ... W38: =SUM(W28:W37) -> 0
B39: Okra | C39: Banjo East
C40: Banjo West
C41: Boot
C42: Cale | D42: 24 | E42: 7.12 | G42: =+E42+F42 -> 7.12 | H42: 5.67 | J42: =(H42+I42) -> 5.67 | K42: 56.7 | M42: =K42+L42 -> 56.7 | X42: 1.45 ha- Damaged by STS Kristine
C43: Darasa
C44: Hidalgo
C45: Maugat | D45: 1 | E45: 0.3 | G45: =+E45+F45 -> 0.3 | H45: 0.3 | J45: =(H45+I45) -> 0.3 | K45: 3 | M45: =K45+L45 -> 3
C46: Natatas | D46: 1 | E46: 0.8 | G46: =+E46+F46 -> 0.8 | H46: 0.8 | J46: =+H46+I46 -> 0.8 | K46: 4 | M46: =+K46+L46 -> 4
C47: Pantay Bata
C48: Suplang | D48: 2 | E48: 0.65 | G48: =+E48+F48 -> 0.65 | H48: 0.2 | J48: =+H48+I48 -> 0.2 | K48: 1.6 | M48: 1.6 | X48: 0.45 ha- Damaged by STS Kristine
C49: TOTAL | D49: =SUM(D39:D48) -> 28 | E49: =SUM(E39:E48) -> 8.87 | F49: =SUM(F39:F48) -> 0 | G49: =SUM(G39:G48) -> 8.87 | H49: =SUM(H39:H48) -> 6.97 | I49: =SUM(I39:I48) -> 0 | J49: =SUM(J39:J48) -> 6.97 | K49: =SUM(K39:K48) -> 65.3 | ... W49: =SUM(W39:W48) -> 0
B50: Patola | C50: Banjo East
C51: Banjo West
C52: Boot
C53: Cale
C54: Darasa
C55: Hidalgo
C56: Maugat | D56: 1 | E56: 0.3 | G56: =+E56+F56 -> 0.3
C57: Natatas
C58: Pantay Bata
C59: Suplang
C60: TOTAL | D60: =SUM(D50:D59) -> 1 | E60: =SUM(E50:E59) -> 0.3 | F60: =SUM(F50:F59) -> 0 | G60: =SUM(G50:G59) -> 0.3 | H60: =SUM(H50:H59) -> 0 | I60: =SUM(I50:I59) -> 0 | J60: =SUM(J50:J59) -> 0 | K60: =SUM(K50:K59) -> 0 | ... W60: =SUM(W50:W59) -> 0
B61: Sigarilyas | C61: Banjo East
C62: Banjo West
C63: Boot
C64: Cale | D64: 10 | E64: 2.68 | G64: =+E64+F64 -> 2.68 | H64: 0.91 | J64: =+H64+I64 -> 0.91 | K64: 7.08 | M64: =+K64+L64 -> 7.08 | X64: 1.77 ha- Damage by STS Kristine
C65: Darasa
C66: Hidalgo
C67: Maugat
C68: Natatas
C69: Pantay Bata
C70: Suplang | D70: 1 | E70: 0.25 | G70: =+E70+F70 -> 0.25 | H70: 0.25 | J70: =+H70+I70 -> 0.25 | K70: 2.5 | M70: =+K70+L70 -> 2.5
C71: TOTAL | D71: =SUM(D61:D70) -> 11 | E71: =SUM(E61:E70) -> 2.93 | F71: =SUM(F61:F70) -> 0 | G71: =SUM(G61:G70) -> 2.93 | H71: =SUM(H61:H70) -> 1.16 | I71: =SUM(I61:I70) -> 0 | J71: =SUM(J61:J70) -> 1.16 | K71: =SUM(K61:K70) -> 9.58 | ... W71: =SUM(W61:W70) -> 0
B72: Upo | C72: Banjo East
C73: Banjo West
C74: Boot
C75: Cale | D75: 3 | E75: 0.4 | F75: 0.5 | G75: =+E75+F75 -> 0.9
C76: Darasa
C77: Hidalgo
C78: Maugat | D78: 1 | E78: 0.3 | G78: =+E78+F78 -> 0.3 | I78: 0.24 | J78: =+H78+I78 -> 0.24 | L78: 1.2 | M78: =+K78+L78 -> 1.2 | X78: 0.06 was damaged by STS Kristine
C79: Natatas | D79: 1 | E79: 0.25 | G79: =+E79+F79 -> 0.25 | I79: 0.2 | J79: =+H79+I79 -> 0.2 | L79: 1 | M79: =+K79+L79 -> 1 | X79: 0.05 was damaged by STS Kristine
C80: Pantay Bata
C81: Suplang | D81: 1 | E81: 0.25 | G81: =+E81+F81 -> 0.25 | H81: 0.25 | J81: 0.25 | K81: 2.5 | M81: =+K81+L81 -> 2.5
C82: TOTAL | D82: =SUM(D72:D81) -> 6 | E82: =SUM(E72:E81) -> 1.2 | F82: =SUM(F72:F81) -> 0.5 | G82: =SUM(G72:G81) -> 1.7 | H82: =SUM(H72:H81) -> 0.25 | I82: =SUM(I72:I81) -> 0.44 | J82: =SUM(J72:J81) -> 0.69 | K82: =SUM(K72:K81) -> 2.5 | ... W82: =SUM(W72:W81) -> 0
B83: Ampalaya | C83: Banjo East
C84: Banjo West
C85: Boot | D85: 1 | E85: 0.25 | G85: =+E85+F85 -> 0.25 | X85: 0.25 ha damged by STS Kristine
C86: Cale | D86: 4 | E86: 0.3 | F86: 1.7 | G86: =+E86+F86 -> 2 | H86: 0.3 | J86: =+H86+I86 -> 0.3 | K86: 3 | M86: =+K86+L86 -> 3
C87: Darasa | D87: 1 | E87: 0.3 | G87: =+E87+F87 -> 0.3 | H87: 0.3 | J87: =+H87+I87 -> 0.3 | K87: 3 | M87: =+K87+L87 -> 3
C88: Hidalgo
C89: Maugat | D89: 1 | F89: 0.5 | G89: =+E89+F89 -> 0.5
C90: Natatas | D90: 1 | E90: 0.8 | G90: =+E90+F90 -> 0.8 | H90: 0.8 | J90: =+H90+I90 -> 0.8 | K90: 8 | M90: =+K90+L90 -> 8
C91: Pantay Bata
C92: Suplang | D92: 1 | E92: 1 | G92: =+E92+F92 -> 1
C93: TOTAL | D93: =SUM(D83:D92) -> 9 | E93: =SUM(E83:E92) -> 2.65 | F93: =SUM(F83:F92) -> 2.2 | G93: =SUM(G83:G92) -> 4.85 | H93: =SUM(H83:H92) -> 1.4 | I93: =SUM(I83:I92) -> 0 | J93: =SUM(J83:J92) -> 1.4 | K93: =SUM(K83:K92) -> 14 | ... W93: =SUM(W83:W92) -> 0
B94: Pipino | C94: Banjo East
C95: Banjo West
C96: Boot
C97: Cale
C98: Darasa
C99: Hidalgo
C100: Maugat
C101: Natatas
...

Sheet Rimas HVCDP
A1: District | B1: Commodity | C1: Barangay | D1: Farmers Served (No.) | E1: Existing Area (ha) | N1: Farmers Served (No.) | O1: Expansion Area (ha) | X1: REMARKS
E2: Area Planted (ha) | H2: Area Harvested (ha) | K2: Production (MT) | O2: Area Planted (ha) | R2: Area Harvested (ha) | U2: Production (MT)
E4: Previous | F4: This Mo. | G4: To Date | H4: Previous | I4: This Mo. | J4: To Date | K4: Previous | L4: This Mo. | M4: To Date | O4: Previous | P4: This Mo. | Q4: To Date | R4: Previous | S4: This Mo. | T4: To Date | U4: Previous | V4: This Mo. | W4: To Date
B5: FRUIT VEGETABLES | X5: Affected by STS Kristine
B6: Eggplant | C6: Bagbag
C7: Bagumbayan
C8: Balele
C9: Laurel
C10: Mabini | D10: 3 | E10: 2.1 | G10: 2.1 | H10: 0.3 | J10: 0.3 | K10: 1.2 | M10: 1.2
C11: Maria Paz
C12: Pagaspas
C13: Tinurik
C14: Ulango | D14: 1 | E14: 0.5 | G14: 0.5
C15: Wawa
C16: TOTAL | D16: =SUM(D6:D15) -> 4 | E16: =SUM(E6:E15) -> 2.6 | F16: =SUM(F6:F15) -> 0 | G16: =SUM(G6:G15) -> 2.6 | H16: =SUM(H6:H15) -> 0.3 | I16: =SUM(I6:I15) -> 0 | J16: =SUM(J6:J15) -> 0.3 | K16: =SUM(K6:K15) -> 1.2 | ... W16: =SUM(W6:W15) -> 0
B17: Sitao | C17: Bagbag | D17: 4 | E17: 1.8 | G17: 1.8 | H17: 0.5 | J17: 0.5 | K17: 2 | M17: 2
C18: Bagumbayan | D18: 1 | E18: 0.05 | G18: 0.05 | H18: 0.05 | J18: 0.05 | K18: 0.2 | M18: 0.2
C19: Balele | D19: 4 | E19: 1.25 | G19: 1.25 | H19: 1 | J19: 1 | K19: 5 | M19: 5
C20: Laurel
C21: Mabini | D21: 2 | E21: 0.75 | G21: 0.75 | H21: 0.75 | J21: 0.75 | K21: 3 | M21: 3
C22: Maria Paz | D22: 6 | E22: 2.35 | G22: 2.35 | H22: 2.35 | J22: 2.35 | K22: 11.75 | M22: 11.75
C23: Pagaspas
C24: Tinurik
C25: Ulango | D25: 2 | E25: 0.75 | G25: 0.75 | H25: 0.25 | J25: 0.25 | K25: 1 | M25: 1
C26: Wawa | D26: 1 | E26: 0.25 | G26: 0.25
C27: TOTAL | D27: =SUM(D17:D26) -> 20 | E27: =SUM(E17:E26) -> 7.2 | F27: =SUM(F17:F26) -> 0 | G27: =SUM(G17:G26) -> 7.2 | H27: =SUM(H17:H26) -> 4.9 | I27: =SUM(I17:I26) -> 0 | J27: =SUM(J17:J26) -> 4.9 | K27: =SUM(K17:K26) -> 22.95 | ... W27: =SUM(W17:W26) -> 0
B28: Squash | C28: Bagbag
C29: Bagumbayan | D29: 2 | E29: 0.55 | G29: 0.55 | H29: 0.55 | J29: 0.55 | K29: 2.75 | M29: 2.75
C30: Balele | D30: 2 | E30: 0.8 | G30: 0.8 | H30: 0.8 | J30: 0.8 | K30: 4.8 | M30: 4.8
C31: Laurel | D31: 2 | E31: 0.5 | G31: 0.5 | H31: 0.5 | J31: 0.5 | K31: 3 | M31: 3
C32: Mabini
C33: Maria Paz | D33: 21 | E33: 0.5 | G33: 0.5 | H33: 0.5 | J33: 0.5 | K33: 3 | M33: 3
C34: Pagaspas
C35: Tinurik
C36: Ulango
C37: Wawa | D37: 1 | E37: 0.25 | G37: 0.25 | H37: 0.25 | J37: 0.25 | K37: 1.5 | M37: 1.5
C38: TOTAL | D38: =SUM(D28:D37) -> 28 | E38: =SUM(E28:E37) -> 2.6 | F38: =SUM(F28:F37) -> 0 | G38: =SUM(G28:G37) -> 2.6 | H38: =SUM(H28:H37) -> 2.6 | I38: =SUM(I28:I37) -> 0 | J38: =SUM(J28:J37) -> 2.6 | K38: =SUM(K28:K37) -> 15.05 | ... W38: =SUM(W28:W37) -> 0
B39: Okra | C39: Bagbag
C40: Bagumbayan
C41: Balele | D41: 2 | E41: 1 | G41: 1 | H41: 1 | J41: 1 | K41: 5 | M41: 5
C42: Laurel
C43: Mabini
C44: Maria Paz
C45: Pagaspas
C46: Tinurik
C47: Ulango
C48: Wawa
C49: TOTAL | D49: =SUM(D39:D48) -> 2 | E49: =SUM(E39:E48) -> 1 | F49: =SUM(F39:F48) -> 0 | G49: =SUM(G39:G48) -> 1 | H49: =SUM(H39:H48) -> 1 | I49: =SUM(I39:I48) -> 0 | J49: =SUM(J39:J48) -> 1 | K49: =SUM(K39:K48) -> 5 | ... W49: =SUM(W39:W48) -> 0 | X49: Affected by STS Kristine
B50: Patola | C50: Bagbag
C51: Bagumbayan
C52: Balele | D52: 3 | E52: 1.25 | G52: 1.25 | H52: 1.25 | J52: 1.25 | K52: 5 | M52: 5
C53: Laurel
C54: Mabini
C55: Maria Paz
C56: Pagaspas
C57: Tinurik
C58: Ulango
C59: Wawa
C60: TOTAL | D60: =SUM(D50:D59) -> 3 | E60: =SUM(E50:E59) -> 1.25 | F60: =SUM(F50:F59) -> 0 | G60: =SUM(G50:G59) -> 1.25 | H60: =SUM(H50:H59) -> 1.25 | I60: =SUM(I50:I59) -> 0 | J60: =SUM(J50:J59) -> 1.25 | K60: =SUM(K50:K59) -> 5 | ... W60: =SUM(W50:W59) -> 0
B61: Sigarilyas | C61: Bagbag | D61: 2 | E61: 1.25 | G61: 1.25
C62: Bagumbayan
C63: Balele | D63: 1 | E63: 0.25 | G63: 0.25 | H63: 0.25 | J63: 0.25 | K63: 1.25 | M63: 1.25
C64: Laurel
C65: Mabini
C66: Maria Paz
C67: Pagaspas
C68: Tinurik
C69: Ulango
C70: Wawa
C71: TOTAL | D71: =SUM(D61:D70) -> 3 | E71: =SUM(E61:E70) -> 1.5 | F71: =SUM(F61:F70) -> 0 | G71: =SUM(G61:G70) -> 1.5 | H71: =SUM(H61:H70) -> 0.25 | I71: =SUM(I61:I70) -> 0 | J71: =SUM(J61:J70) -> 0.25 | K71: =SUM(K61:K70) -> 1.25 | ... W71: =SUM(W61:W70) -> 0
B72: Upo | C72: Bagbag
C73: Bagumbayan
C74: Balele | D74: 2 | E74: 1.2 | G74: 1.2 | H74: 1.2 | J74: 1.2 | K74: 5.6 | M74: 5.6
C75: Laurel | D75: 1 | E75: 0.25 | G75: 0.25 | H75: 0.25 | J75: 0.25 | K75: 1.25 | M75: 1.25
C76: Mabini
C77: Maria Paz
C78: Pagaspas
C79: Tinurik
C80: Ulango | D80: 1 | E80: 0.25 | G80: 0.25 | H80: 0.25 | J80: 0.25 | K80: 1.25 | M80: 1.25
C81: Wawa
C82: TOTAL | D82: =SUM(D72:D81) -> 4 | E82: =SUM(E72:E81) -> 1.7 | F82: =SUM(F72:F81) -> 0 | G82: =SUM(G72:G81) -> 1.7 | H82: =SUM(H72:H81) -> 1.7 | I82: =SUM(I72:I81) -> 0 | J82: =SUM(J72:J81) -> 1.7 | K82: =SUM(K72:K81) -> 8.1 | ... W82: =SUM(W72:W81) -> 0
B83: Ampalaya | C83: Bagbag | D83: 2 | E83: 1.75 | G83: 1.75 | H83: 1 | J83: 1 | K83: 6 | M83: 6
C84: Bagumbayan
C85: Balele | D85: 6 | E85: 2.1 | G85: 2.1 | H85: 2.1 | J85: 2.1 | K85: 12.6 | M85: 12.6
C86: Laurel
C87: Mabini
C88: Maria Paz | D88: 10 | E88: 5.15 | G88: 5.15 | H88: 5.15 | J88: 5.15 | K88: 26.75 | M88: 26.75
C89: Pagaspas
C90: Tinurik
C91: Ulango
C92: Wawa
C93: TOTAL | D93: =SUM(D83:D92) -> 18 | E93: =SUM(E83:E92) -> 9 | F93: =SUM(F83:F92) -> 0 | G93: =SUM(G83:G92) -> 9 | H93: =SUM(H83:H92) -> 8.25 | I93: =SUM(I83:I92) -> 0 | J93: =SUM(J83:J92) -> 8.25 | K93: =SUM(K83:K92) -> 45.35 | ... W93: =SUM(W83:W92) -> 0
B94: Pipino | C94: Bagbag
C95: Bagumbayan
C96: Balele
C97: Laurel
C98: Mabini | X98: Affected by STS Kristine
C99: Maria Paz
C100: Pagaspas
C101: Tinurik
...

Sheet Consolidation HVCDP
A1: District | B1: Commodity | C1: Barangay | D1: Farmers Served (No.) | E1: Existing Area (ha) | N1: Farmers Served (No.) | O1: Expansion Area (ha) | X1: REMARKS
E2: Area Planted (ha) | H2: Area Harvested (ha) | K2: Production (MT) | O2: Area Planted (ha) | R2: Area Harvested (ha) | U2: Production (MT)
E4: Previous | F4: This Mo. | G4: To Date | H4: Previous | I4: This Mo. | J4: To Date | K4: Previous | L4: This Mo. | M4: To Date | O4: Previous | P4: This Mo. | Q4: To Date | R4: Previous | S4: This Mo. | T4: To Date | U4: Previous | V4: This Mo. | W4: To Date
A5: III | B5: FRUIT VEGETABLES
B6: Eggplant | C6: =COUNTA('Piamonte HVCDP'!D6:D15)+COUNTA('Requizo HVCDP'!D6:D15)+COUNTA('Lucido HVCDP'!D6:D15)+COUNTA('Rimas HVCDP'!D6:D15) -> 17 | D6: =SUM('Piamonte HVCDP'!D16+'Requizo HVCDP'!D16+'Lucido HVCDP'!D16+'Rimas HVCDP'!D16) -> 52 | E6: =SUM('Piamonte HVCDP'!E16+'Requizo HVCDP'!E16+'Lucido HVCDP'!E16+'Rimas HVCDP'!E16) -> 24.03 | F6: =SUM('Piamonte HVCDP'!F16+'Requizo HVCDP'!F16+'Lucido HVCDP'!F16+'Rimas HVCDP'!F16) -> 2.1 | G6: =SUM('Piamonte HVCDP'!G16+'Requizo HVCDP'!G16+'Lucido HVCDP'!G16+'Rimas HVCDP'!G16) -> 26.13 | H6: =SUM('Piamonte HVCDP'!H16+'Requizo HVCDP'!H16+'Lucido HVCDP'!H16+'Rimas HVCDP'!H16) -> 11.28 | I6: =SUM('Piamonte HVCDP'!I16+'Requizo HVCDP'!I16+'Lucido HVCDP'!I16+'Rimas HVCDP'!I16) -> 0.65 | J6: =SUM('Piamonte HVCDP'!J16+'Requizo HVCDP'!J16+'Lucido HVCDP'!J16+'Rimas HVCDP'!J16) -> 11.93 | K6: =SUM('Piamonte HVCDP'!K16+'Requizo HVCDP'!K16+'Lucido HVCDP'!K16+'Rimas HVCDP'!K16) -> 113.23 | ... W6: =SUM('Piamonte HVCDP'!W16+'Requizo HVCDP'!W16+'Lucido HVCDP'!W16+'Rimas HVCDP'!W16) -> 0
B7: Sitao | C7: =COUNTA('Piamonte HVCDP'!D17:D26)+COUNTA('Requizo HVCDP'!D17:D26)+COUNTA('Lucido HVCDP'!D17:D26)+COUNTA('Rimas HVCDP'!D17:D26) -> 29 | D7: =SUM('Piamonte HVCDP'!D27+'Requizo HVCDP'!D27+'Lucido HVCDP'!D27+'Rimas HVCDP'!D27) -> 129 | E7: =SUM('Piamonte HVCDP'!E27+'Requizo HVCDP'!E27+'Lucido HVCDP'!E27+'Rimas HVCDP'!E27) -> 44.62 | F7: =SUM('Piamonte HVCDP'!F27+'Requizo HVCDP'!F27+'Lucido HVCDP'!F27+'Rimas HVCDP'!F27) -> 2.3 | G7: =SUM('Piamonte HVCDP'!G27+'Requizo HVCDP'!G27+'Lucido HVCDP'!G27+'Rimas HVCDP'!G27) -> 46.92 | H7: =SUM('Piamonte HVCDP'!H27+'Requizo HVCDP'!H27+'Lucido HVCDP'!H27+'Rimas HVCDP'!H27) -> 30.72 | I7: =SUM('Piamonte HVCDP'!I27+'Requizo HVCDP'!I27+'Lucido HVCDP'!I27+'Rimas HVCDP'!I27) -> 0 | J7: =SUM('Piamonte HVCDP'!J27+'Requizo HVCDP'!J27+'Lucido HVCDP'!J27+'Rimas HVCDP'!J27) -> 30.72 | K7: =SUM('Piamonte HVCDP'!K27+'Requizo HVCDP'!K27+'Lucido HVCDP'!K27+'Rimas HVCDP'!K27) -> 232.37 | ... W7: =SUM('Piamonte HVCDP'!W27+'Requizo HVCDP'!W27+'Lucido HVCDP'!W27+'Rimas HVCDP'!W27) -> 0
B8: Squash | C8: =COUNTA('Piamonte HVCDP'!D28:D37,'Requizo HVCDP'!D28:D37,'Lucido HVCDP'!D28:D37,'Rimas HVCDP'!D28:D37) -> 27 | D8: =SUM('Piamonte HVCDP'!D38+'Requizo HVCDP'!D38+'Lucido HVCDP'!D38+'Rimas HVCDP'!D38) -> 95 | E8: =SUM('Piamonte HVCDP'!E38+'Requizo HVCDP'!E38+'Lucido HVCDP'!E38+'Rimas HVCDP'!E38) -> 26.57 | F8: =SUM('Piamonte HVCDP'!F38+'Requizo HVCDP'!F38+'Lucido HVCDP'!F38+'Rimas HVCDP'!F38) -> 1.2 | G8: =SUM('Piamonte HVCDP'!G38+'Requizo HVCDP'!G38+'Lucido HVCDP'!G38+'Rimas HVCDP'!G38) -> 27.77 | H8: =SUM('Piamonte HVCDP'!H38+'Requizo HVCDP'!H38+'Lucido HVCDP'!H38+'Rimas HVCDP'!H38) -> 17.12 | I8: =SUM('Piamonte HVCDP'!I38+'Requizo HVCDP'!I38+'Lucido HVCDP'!I38+'Rimas HVCDP'!I38) -> 0 | J8: =SUM('Piamonte HVCDP'!J38+'Requizo HVCDP'!J38+'Lucido HVCDP'!J38+'Rimas HVCDP'!J38) -> 17.12 | K8: =SUM('Piamonte HVCDP'!K38+'Requizo HVCDP'!K38+'Lucido HVCDP'!K38+'Rimas HVCDP'!K38) -> 156.45 | ... W8: =SUM('Piamonte HVCDP'!W38+'Requizo HVCDP'!W38+'Lucido HVCDP'!W38+'Rimas HVCDP'!W38) -> 0
B9: Okra | C9: =COUNTA('Piamonte HVCDP'!D39:D48,'Requizo HVCDP'!D39:D48,'Lucido HVCDP'!D39:D48,'Rimas HVCDP'!D39:D48) -> 12 | D9: =SUM('Piamonte HVCDP'!D49+'Requizo HVCDP'!D49+'Lucido HVCDP'!D49+'Rimas HVCDP'!D49) -> 52 | E9: =SUM('Piamonte HVCDP'!E49+'Requizo HVCDP'!E49+'Lucido HVCDP'!E49+'Rimas HVCDP'!E49) -> 17.17 | F9: =SUM('Piamonte HVCDP'!F49+'Requizo HVCDP'!F49+'Lucido HVCDP'!F49+'Rimas HVCDP'!F49) -> 0 | G9: =SUM('Piamonte HVCDP'!G49+'Requizo HVCDP'!G49+'Lucido HVCDP'!G49+'Rimas HVCDP'!G49) -> 17.17 | H9: =SUM('Piamonte HVCDP'!H49+'Requizo HVCDP'!H49+'Lucido HVCDP'!H49+'Rimas HVCDP'!H49) -> 13.92 | I9: =SUM('Piamonte HVCDP'!I49+'Requizo HVCDP'!I49+'Lucido HVCDP'!I49+'Rimas HVCDP'!I49) -> 0.5 | J9: =SUM('Piamonte HVCDP'!J49+'Requizo HVCDP'!J49+'Lucido HVCDP'!J49+'Rimas HVCDP'!J49) -> 14.42 | K9: =SUM('Piamonte HVCDP'!K49+'Requizo HVCDP'!K49+'Lucido HVCDP'!K49+'Rimas HVCDP'!K49) -> 106.78 | ... W9: =SUM('Piamonte HVCDP'!W49+'Requizo HVCDP'!W49+'Lucido HVCDP'!W49+'Rimas HVCDP'!W49) -> 0
B10: Patola | C10: =COUNTA('Piamonte HVCDP'!D50:D59,'Requizo HVCDP'!D50:D59,'Lucido HVCDP'!D50:D59,'Rimas HVCDP'!D50:D59) -> 11 | D10: =SUM('Piamonte HVCDP'!D60+'Requizo HVCDP'!D60+'Lucido HVCDP'!D60+'Rimas HVCDP'!D60) -> 35 | E10: =SUM('Piamonte HVCDP'!E60+'Requizo HVCDP'!E60+'Lucido HVCDP'!E60+'Rimas HVCDP'!E60) -> 11.13 | F10: =SUM('Piamonte HVCDP'!F60+'Requizo HVCDP'!F60+'Lucido HVCDP'!F60+'Rimas HVCDP'!F60) -> 0.5 | G10: =SUM('Piamonte HVCDP'!G60+'Requizo HVCDP'!G60+'Lucido HVCDP'!G60+'Rimas HVCDP'!G60) -> 11.63 | H10: =SUM('Piamonte HVCDP'!H60+'Requizo HVCDP'!H60+'Lucido HVCDP'!H60+'Rimas HVCDP'!H60) -> 5.7 | I10: =SUM('Piamonte HVCDP'!I60+'Requizo HVCDP'!I60+'Lucido HVCDP'!I60+'Rimas HVCDP'!I60) -> 0 | J10: =SUM('Piamonte HVCDP'!J60+'Requizo HVCDP'!J60+'Lucido HVCDP'!J60+'Rimas HVCDP'!J60) -> 5.7 | K10: =SUM('Piamonte HVCDP'!K60+'Requizo HVCDP'!K60+'Lucido HVCDP'!K60+'Rimas HVCDP'!K60) -> 42.8 | ... W10: =SUM('Piamonte HVCDP'!W60+'Requizo HVCDP'!W60+'Lucido HVCDP'!W60+'Rimas HVCDP'!W60) -> 0
B11: Sigarilyas | C11: =COUNTA('Piamonte HVCDP'!D61:D70,'Requizo HVCDP'!D61:D70,'Lucido HVCDP'!D61:D70,'Rimas HVCDP'!D61:D70) -> 14 | D11: =SUM('Piamonte HVCDP'!D71+'Requizo HVCDP'!D71+'Lucido HVCDP'!D71+'Rimas HVCDP'!D71) -> 54 | E11: =SUM('Piamonte HVCDP'!E71+'Requizo HVCDP'!E71+'Lucido HVCDP'!E71+'Rimas HVCDP'!E71) -> 24.38 | F11: =SUM('Piamonte HVCDP'!F71+'Requizo HVCDP'!F71+'Lucido HVCDP'!F71+'Rimas HVCDP'!F71) -> 0 | G11: =SUM('Piamonte HVCDP'!G71+'Requizo HVCDP'!G71+'Lucido HVCDP'!G71+'Rimas HVCDP'!G71) -> 24.38 | H11: =SUM('Piamonte HVCDP'!H71+'Requizo HVCDP'!H71+'Lucido HVCDP'!H71+'Rimas HVCDP'!H71) -> 18.21 | I11: =SUM('Piamonte HVCDP'!I71+'Requizo HVCDP'!I71+'Lucido HVCDP'!I71+'Rimas HVCDP'!I71) -> 0 | J11: =SUM('Piamonte HVCDP'!J71+'Requizo HVCDP'!J71+'Lucido HVCDP'!J71+'Rimas HVCDP'!J71) -> 18.21 | K11: =SUM('Piamonte HVCDP'!K71+'Requizo HVCDP'!K71+'Lucido HVCDP'!K71+'Rimas HVCDP'!K71) -> 80.23 | ... W11: =SUM('Piamonte HVCDP'!W71+'Requizo HVCDP'!W71+'Lucido HVCDP'!W71+'Rimas HVCDP'!W71) -> 0
B12: Upo | C12: =COUNTA('Piamonte HVCDP'!D72:D81,'Requizo HVCDP'!D72:D81,'Lucido HVCDP'!D72:D81,'Rimas HVCDP'!D72:D81) -> 12 | D12: =SUM('Piamonte HVCDP'!D82+'Requizo HVCDP'!D82+'Lucido HVCDP'!D82+'Rimas HVCDP'!D82) -> 30 | E12: =SUM('Piamonte HVCDP'!E82+'Requizo HVCDP'!E82+'Lucido HVCDP'!E82+'Rimas HVCDP'!E82) -> 9 | F12: =SUM('Piamonte HVCDP'!F82+'Requizo HVCDP'!F82+'Lucido HVCDP'!F82+'Rimas HVCDP'!F82) -> 2.2 | G12: =SUM('Piamonte HVCDP'!G82+'Requizo HVCDP'!G82+'Lucido HVCDP'!G82+'Rimas HVCDP'!G82) -> 11.2 | H12: =SUM('Piamonte HVCDP'!H82+'Requizo HVCDP'!H82+'Lucido HVCDP'!H82+'Rimas HVCDP'!H82) -> 5.6 | I12: =SUM('Piamonte HVCDP'!I82+'Requizo HVCDP'!I82+'Lucido HVCDP'!I82+'Rimas HVCDP'!I82) -> 0.44 | J12: =SUM('Piamonte HVCDP'!J82+'Requizo HVCDP'!J82+'Lucido HVCDP'!J82+'Rimas HVCDP'!J82) -> 6.04 | K12: =SUM('Piamonte HVCDP'!K82+'Requizo HVCDP'!K82+'Lucido HVCDP'!K82+'Rimas HVCDP'!K82) -> 44.2 | ... W12: =SUM('Piamonte HVCDP'!W82+'Requizo HVCDP'!W82+'Lucido HVCDP'!W82+'Rimas HVCDP'!W82) -> 0
B13: Ampalaya | C13: =COUNTA('Piamonte HVCDP'!D83:D92,'Requizo HVCDP'!D83:D92,'Lucido HVCDP'!D83:D92,'Rimas HVCDP'!D83:D92) -> 18 | D13: =SUM('Piamonte HVCDP'!D93+'Requizo HVCDP'!D93+'Lucido HVCDP'!D93+'Rimas HVCDP'!D93) -> 53 | E13: =SUM('Piamonte HVCDP'!E93+'Requizo HVCDP'!E93+'Lucido HVCDP'!E93+'Rimas HVCDP'!E93) -> 23.25 | F13: =SUM('Piamonte HVCDP'!F93+'Requizo HVCDP'!F93+'Lucido HVCDP'!F93+'Rimas HVCDP'!F93) -> 2.7 | G13: =SUM('Piamonte HVCDP'!G93+'Requizo HVCDP'!G93+'Lucido HVCDP'!G93+'Rimas HVCDP'!G93) -> 25.95 | H13: =SUM('Piamonte HVCDP'!H93+'Requizo HVCDP'!H93+'Lucido HVCDP'!H93+'Rimas HVCDP'!H93) -> 16.88 | I13: =SUM('Piamonte HVCDP'!I93+'Requizo HVCDP'!I93+'Lucido HVCDP'!I93+'Rimas HVCDP'!I93) -> 0 | J13: =SUM('Piamonte HVCDP'!J93+'Requizo HVCDP'!J93+'Lucido HVCDP'!J93+'Rimas HVCDP'!J93) -> 16.88 | K13: =SUM('Piamonte HVCDP'!K93+'Requizo HVCDP'!K93+'Lucido HVCDP'!K93+'Rimas HVCDP'!K93) -> 99.35 | ... W13: =SUM('Piamonte HVCDP'!W93+'Requizo HVCDP'!W93+'Lucido HVCDP'!W93+'Rimas HVCDP'!W93) -> 0
B14: Pipino | C14: =COUNTA('Piamonte HVCDP'!D94:D103,'Requizo HVCDP'!D94:D103,'Lucido HVCDP'!D94:D103,'Rimas HVCDP'!D94:D103) -> 1 | D14: =SUM('Piamonte HVCDP'!D104+'Requizo HVCDP'!D104+'Lucido HVCDP'!D104+'Rimas HVCDP'!D104) -> 6 | E14: =SUM('Piamonte HVCDP'!E104+'Requizo HVCDP'!E104+'Lucido HVCDP'!E104+'Rimas HVCDP'!E104) -> 1.9 | F14: =SUM('Piamonte HVCDP'!F104+'Requizo HVCDP'!F104+'Lucido HVCDP'!F104+'Rimas HVCDP'!F104) -> 0 | G14: =SUM('Piamonte HVCDP'!G104+'Requizo HVCDP'!G104+'Lucido HVCDP'!G104+'Rimas HVCDP'!G104) -> 1.9 | H14: =SUM('Piamonte HVCDP'!H104+'Requizo HVCDP'!H104+'Lucido HVCDP'!H104+'Rimas HVCDP'!H104) -> 0.3 | I14: =SUM('Piamonte HVCDP'!I104+'Requizo HVCDP'!I104+'Lucido HVCDP'!I104+'Rimas HVCDP'!I104) -> 0 | J14: =SUM('Piamonte HVCDP'!J104+'Requizo HVCDP'!J104+'Lucido HVCDP'!J104+'Rimas HVCDP'!J104) -> 0.3 | K14: =SUM('Piamonte HVCDP'!K104+'Requizo HVCDP'!K104+'Lucido HVCDP'!K104+'Rimas HVCDP'!K104) -> 0.45 | ... W14: =SUM('Piamonte HVCDP'!W104+'Requizo HVCDP'!W104+'Lucido HVCDP'!W104+'Rimas HVCDP'!W104) -> 0
B15: Sili | C15: =COUNTA('Piamonte HVCDP'!D105:D114,'Requizo HVCDP'!D105:D114,'Lucido HVCDP'!D105:D114,'Rimas HVCDP'!D105:D114) -> 9 | D15: =SUM('Piamonte HVCDP'!D115+'Requizo HVCDP'!D115+'Lucido HVCDP'!D115+'Rimas HVCDP'!D115) -> 15 | E15: =SUM('Piamonte HVCDP'!E115+'Requizo HVCDP'!E115+'Lucido HVCDP'!E115+'Rimas HVCDP'!E115) -> 6.05 | F15: =SUM('Piamonte HVCDP'!F115+'Requizo HVCDP'!F115+'Lucido HVCDP'!F115+'Rimas HVCDP'!F115) -> 0 | G15: =SUM('Piamonte HVCDP'!G115+'Requizo HVCDP'!G115+'Lucido HVCDP'!G115+'Rimas HVCDP'!G115) -> 6.05 | H15: =SUM('Piamonte HVCDP'!H115+'Requizo HVCDP'!H115+'Lucido HVCDP'!H115+'Rimas HVCDP'!H115) -> 1.25 | I15: =SUM('Piamonte HVCDP'!I115+'Requizo HVCDP'!I115+'Lucido HVCDP'!I115+'Rimas HVCDP'!I115) -> 0.19 | J15: =SUM('Piamonte HVCDP'!J115+'Requizo HVCDP'!J115+'Lucido HVCDP'!J115+'Rimas HVCDP'!J115) -> 1.44 | K15: =SUM('Piamonte HVCDP'!K115+'Requizo HVCDP'!K115+'Lucido HVCDP'!K115+'Rimas HVCDP'!K115) -> 9.9 | ... W15: =SUM('Piamonte HVCDP'!W115+'Requizo HVCDP'!W115+'Lucido HVCDP'!W115+'Rimas HVCDP'!W115) -> 0
B16: Beans | C16: =COUNTA('Piamonte HVCDP'!D116:D125,'Requizo HVCDP'!D116:D125,'Lucido HVCDP'!D127:D136,'Rimas HVCDP'!D116:D125) -> 8 | D16: =SUM('Piamonte HVCDP'!D126+'Requizo HVCDP'!D126+'Lucido HVCDP'!D137+'Rimas HVCDP'!D126) -> 14 | E16: =SUM('Piamonte HVCDP'!E126+'Requizo HVCDP'!E126+'Lucido HVCDP'!E137+'Rimas HVCDP'!E126) -> 5.53 | F16: =SUM('Piamonte HVCDP'!F126+'Requizo HVCDP'!F126+'Lucido HVCDP'!F137+'Rimas HVCDP'!F126) -> 0.25 | G16: =SUM('Piamonte HVCDP'!G126+'Requizo HVCDP'!G126+'Lucido HVCDP'!G137+'Rimas HVCDP'!G126) -> 5.78 | H16: =SUM('Piamonte HVCDP'!H126+'Requizo HVCDP'!H126+'Lucido HVCDP'!H137+'Rimas HVCDP'!H126) -> 2.53 | I16: =SUM('Piamonte HVCDP'!I126+'Requizo HVCDP'!I126+'Lucido HVCDP'!I137+'Rimas HVCDP'!I126) -> 0 | J16: =SUM('Piamonte HVCDP'!J126+'Requizo HVCDP'!J126+'Lucido HVCDP'!J137+'Rimas HVCDP'!J126) -> 2.53 | K16: =SUM('Piamonte HVCDP'!K126+'Requizo HVCDP'!K126+'Lucido HVCDP'!K137+'Rimas HVCDP'!K126) -> 16.7 | ... W16: =SUM('Piamonte HVCDP'!W126+'Requizo HVCDP'!W126+'Lucido HVCDP'!W137+'Rimas HVCDP'!W126) -> 0
B17: Paayap | C17: =COUNTA('Piamonte HVCDP'!D127:D136,'Requizo HVCDP'!D127:D136,'Lucido HVCDP'!D160:D169,'Rimas HVCDP'!D127:D136) -> 7 | D17: =SUM('Piamonte HVCDP'!D137+'Requizo HVCDP'!D137+'Lucido HVCDP'!D170+'Rimas HVCDP'!D137) -> 11 | E17: =SUM('Piamonte HVCDP'!E137+'Requizo HVCDP'!E137+'Lucido HVCDP'!E170+'Rimas HVCDP'!E137) -> 2.75 | F17: =SUM('Piamonte HVCDP'!F137+'Requizo HVCDP'!F137+'Lucido HVCDP'!F170+'Rimas HVCDP'!F137) -> 0.7 | G17: =SUM('Piamonte HVCDP'!G137+'Requizo HVCDP'!G137+'Lucido HVCDP'!G170+'Rimas HVCDP'!G137) -> 3.45 | H17: =SUM('Piamonte HVCDP'!H137+'Requizo HVCDP'!H137+'Lucido HVCDP'!H170+'Rimas HVCDP'!H137) -> 1.6 | I17: =SUM('Piamonte HVCDP'!I137+'Requizo HVCDP'!I137+'Lucido HVCDP'!I170+'Rimas HVCDP'!I137) -> 0 | J17: =SUM('Piamonte HVCDP'!J137+'Requizo HVCDP'!J137+'Lucido HVCDP'!J170+'Rimas HVCDP'!J137) -> 1.6 | K17: =SUM('Piamonte HVCDP'!K137+'Requizo HVCDP'!K137+'Lucido HVCDP'!K170+'Rimas HVCDP'!K137) -> 16 | ... W17: =SUM('Piamonte HVCDP'!W137+'Requizo HVCDP'!W137+'Lucido HVCDP'!W170+'Rimas HVCDP'!W137) -> 0
B18: Tomato | C18: =COUNTA('Piamonte HVCDP'!D138:D147,'Requizo HVCDP'!D138:D147,'Lucido HVCDP'!D171:D180,'Rimas HVCDP'!D138:D147) -> 10 | D18: =SUM('Piamonte HVCDP'!D148+'Requizo HVCDP'!D148+'Lucido HVCDP'!D181+'Rimas HVCDP'!D148) -> 23 | E18: =SUM('Piamonte HVCDP'!E148+'Requizo HVCDP'!E148+'Lucido HVCDP'!E181+'Rimas HVCDP'!E148) -> 7.9 | F18: =SUM('Piamonte HVCDP'!F148+'Requizo HVCDP'!F148+'Lucido HVCDP'!F181+'Rimas HVCDP'!F148) -> 3.4 | G18: =SUM('Piamonte HVCDP'!G148+'Requizo HVCDP'!G148+'Lucido HVCDP'!G181+'Rimas HVCDP'!G148) -> 11.3 | H18: =SUM('Piamonte HVCDP'!H148+'Requizo HVCDP'!H148+'Lucido HVCDP'!H181+'Rimas HVCDP'!H148) -> 4.57 | I18: =SUM('Piamonte HVCDP'!I148+'Requizo HVCDP'!I148+'Lucido HVCDP'!I181+'Rimas HVCDP'!I148) -> 0.19 | J18: =SUM('Piamonte HVCDP'!J148+'Requizo HVCDP'!J148+'Lucido HVCDP'!J181+'Rimas HVCDP'!J148) -> 4.76 | K18: =SUM('Piamonte HVCDP'!K148+'Requizo HVCDP'!K148+'Lucido HVCDP'!K181+'Rimas HVCDP'!K148) -> 52 | ... W18: =SUM('Piamonte HVCDP'!W148+'Requizo HVCDP'!W148+'Lucido HVCDP'!W181+'Rimas HVCDP'!W148) -> 0
B19: Patani | C19: =COUNTA('Requizo HVCDP'!D149,'Lucido HVCDP'!D138:D147,'Rimas HVCDP'!D149) -> 3 | D19: =SUM('Requizo HVCDP'!D159+'Lucido HVCDP'!D148+'Rimas HVCDP'!D150) -> 5 | E19: =SUM('Requizo HVCDP'!E159+'Lucido HVCDP'!E148+'Rimas HVCDP'!E150) -> 1.05 | F19: =SUM('Requizo HVCDP'!F159+'Lucido HVCDP'!F148+'Rimas HVCDP'!F150) -> 0 | G19: =SUM('Requizo HVCDP'!G159+'Lucido HVCDP'!G148+'Rimas HVCDP'!G150) -> 1.05 | H19: =SUM('Requizo HVCDP'!H159+'Lucido HVCDP'!H148+'Rimas HVCDP'!H150) -> 0.65 | I19: =SUM('Requizo HVCDP'!I159+'Lucido HVCDP'!I148+'Rimas HVCDP'!I150) -> 0 | J19: =SUM('Requizo HVCDP'!J159+'Lucido HVCDP'!J148+'Rimas HVCDP'!J150) -> 0.65 | K19: =SUM('Requizo HVCDP'!K159+'Lucido HVCDP'!K148+'Rimas HVCDP'!K150) -> 6.5 | ... W19: =SUM('Requizo HVCDP'!W159+'Lucido HVCDP'!W148+'Rimas HVCDP'!W150) -> 0
B20: Mungbean | C20: =COUNTA('Lucido HVCDP'!D116:D125) -> 0 | D20: =SUM('Lucido HVCDP'!D126) -> 0 | E20: =SUM('Lucido HVCDP'!E126) -> 0 | F20: =SUM('Lucido HVCDP'!F126) -> 0 | G20: =SUM('Lucido HVCDP'!G126) -> 0 | H20: =SUM('Lucido HVCDP'!H126) -> 0 | I20: =SUM('Lucido HVCDP'!I126) -> 0 | J20: =SUM('Lucido HVCDP'!J126) -> 0 | K20: =SUM('Lucido HVCDP'!K126) -> 0 | ... W20: =SUM('Lucido HVCDP'!W126) -> 0
B21: INDUSTRIAL CROPS
B22: Banana | C22: =COUNTA('Piamonte HVCDP'!D150:D159,'Requizo HVCDP'!D162:D171,'Lucido HVCDP'!D183:D192,'Rimas HVCDP'!D153:D162) -> 40 | D22: =SUM('Piamonte HVCDP'!D160+'Requizo HVCDP'!D172+'Lucido HVCDP'!D193+'Rimas HVCDP'!D163) -> 917 | E22: =SUM('Piamonte HVCDP'!E160+'Requizo HVCDP'!E172+'Lucido HVCDP'!E193+'Rimas HVCDP'!E163) -> 336.7747 | F22: =SUM('Piamonte HVCDP'!F160+'Requizo HVCDP'!F172+'Lucido HVCDP'!F193+'Rimas HVCDP'!F163) -> 0 | G22: =SUM('Piamonte HVCDP'!G160+'Requizo HVCDP'!G172+'Lucido HVCDP'!G193+'Rimas HVCDP'!G163) -> 336.7747 | H22: =SUM('Piamonte HVCDP'!H160+'Requizo HVCDP'!H172+'Lucido HVCDP'!H193+'Rimas HVCDP'!H163) -> 8.4 | I22: =SUM('Piamonte HVCDP'!I160+'Requizo HVCDP'!I172+'Lucido HVCDP'!I193+'Rimas HVCDP'!I163) -> 0 | J22: =SUM('Piamonte HVCDP'!J160+'Requizo HVCDP'!J172+'Lucido HVCDP'!J193+'Rimas HVCDP'!J163) -> 8.4 | K22: =SUM('Piamonte HVCDP'!K160+'Requizo HVCDP'!K172+'Lucido HVCDP'!K193+'Rimas HVCDP'!K163) -> 93.65 | ... W22: =SUM('Piamonte HVCDP'!W160+'Requizo HVCDP'!W172+'Lucido HVCDP'!W193+'Rimas HVCDP'!W163) -> 0
B23: Cacao | C23: =COUNTA('Piamonte HVCDP'!D161:D170,'Requizo HVCDP'!D173:D182,'Lucido HVCDP'!D194:D203,'Rimas HVCDP'!D164:D173) -> 40 | D23: =SUM('Piamonte HVCDP'!D171+'Requizo HVCDP'!D183+'Lucido HVCDP'!D204+'Rimas HVCDP'!D174) -> 41 | E23: =SUM('Piamonte HVCDP'!E171+'Requizo HVCDP'!E183+'Lucido HVCDP'!E204+'Rimas HVCDP'!E174) -> 16.414 | F23: =SUM('Piamonte HVCDP'!F171+'Requizo HVCDP'!F183+'Lucido HVCDP'!F204+'Rimas HVCDP'!F174) -> 0 | G23: =SUM('Piamonte HVCDP'!G171+'Requizo HVCDP'!G183+'Lucido HVCDP'!G204+'Rimas HVCDP'!G174) -> 16.414 | H23: =SUM('Piamonte HVCDP'!H171+'Requizo HVCDP'!H183+'Lucido HVCDP'!H204+'Rimas HVCDP'!H174) -> 0 | I23: =SUM('Piamonte HVCDP'!I171+'Requizo HVCDP'!I183+'Lucido HVCDP'!I204+'Rimas HVCDP'!I174) -> 0 | J23: =SUM('Piamonte HVCDP'!J171+'Requizo HVCDP'!J183+'Lucido HVCDP'!J204+'Rimas HVCDP'!J174) -> 0 | K23: =SUM('Piamonte HVCDP'!K171+'Requizo HVCDP'!K183+'Lucido HVCDP'!K204+'Rimas HVCDP'!K174) -> 0 | ... W23: =SUM('Piamonte HVCDP'!W171+'Requizo HVCDP'!W183+'Lucido HVCDP'!W204+'Rimas HVCDP'!W174) -> 0
B24: Coffee | C24: =COUNTA('Piamonte HVCDP'!D172,'Requizo HVCDP'!D184:D187,'Lucido HVCDP'!D205,'Rimas HVCDP'!D175:D177) -> 6 | D24: =SUM('Piamonte HVCDP'!D173+'Requizo HVCDP'!D188+'Lucido HVCDP'!D206+'Rimas HVCDP'!D178) -> 3 | E24: =SUM('Piamonte HVCDP'!E173+'Requizo HVCDP'!E188+'Lucido HVCDP'!E206+'Rimas HVCDP'!E178) -> 3.7 | F24: =SUM('Piamonte HVCDP'!F173+'Requizo HVCDP'!F188+'Lucido HVCDP'!F206+'Rimas HVCDP'!F178) -> 0 | G24: =SUM('Piamonte HVCDP'!G173+'Requizo HVCDP'!G188+'Lucido HVCDP'!G206+'Rimas HVCDP'!G178) -> 3.7 | H24: =SUM('Piamonte HVCDP'!H173+'Requizo HVCDP'!H188+'Lucido HVCDP'!H206+'Rimas HVCDP'!H178) -> 0 | I24: =SUM('Piamonte HVCDP'!I173+'Requizo HVCDP'!I188+'Lucido HVCDP'!I206+'Rimas HVCDP'!I178) -> 0 | J24: =SUM('Piamonte HVCDP'!J173+'Requizo HVCDP'!J188+'Lucido HVCDP'!J206+'Rimas HVCDP'!J178) -> 0 | K24: =SUM('Piamonte HVCDP'!K173+'Requizo HVCDP'!K188+'Lucido HVCDP'!K206+'Rimas HVCDP'!K178) -> 0 | ... W24: =SUM('Piamonte HVCDP'!W173+'Requizo HVCDP'!W188+'Lucido HVCDP'!W206+'Rimas HVCDP'!W178) -> 0
B25: FRUIT TREES
B26: Calamansi | C26: =COUNTA('Piamonte HVCDP'!D175:D184,'Requizo HVCDP'!D190:D199,'Lucido HVCDP'!D208:D217,'Rimas HVCDP'!D180:D189) -> 40 | D26: =SUM('Piamonte HVCDP'!D185+'Requizo HVCDP'!D200+'Lucido HVCDP'!D218+'Rimas HVCDP'!D190) -> 106 | E26: =SUM('Piamonte HVCDP'!E185+'Requizo HVCDP'!E200+'Lucido HVCDP'!E218+'Rimas HVCDP'!E190) -> 23.499 | F26: =SUM('Piamonte HVCDP'!F185+'Requizo HVCDP'!F200+'Lucido HVCDP'!F218+'Rimas HVCDP'!F190) -> 0 | G26: =SUM('Piamonte HVCDP'!G185+'Requizo HVCDP'!G200+'Lucido HVCDP'!G218+'Rimas HVCDP'!G190) -> 23.499 | H26: =SUM('Piamonte HVCDP'!H185+'Requizo HVCDP'!H200+'Lucido HVCDP'!H218+'Rimas HVCDP'!H190) -> 0.4 | I26: =SUM('Piamonte HVCDP'!I185+'Requizo HVCDP'!I200+'Lucido HVCDP'!I218+'Rimas HVCDP'!I190) -> 0 | J26: =SUM('Piamonte HVCDP'!J185+'Requizo HVCDP'!J200+'Lucido HVCDP'!J218+'Rimas HVCDP'!J190) -> 0.4 | K26: =SUM('Piamonte HVCDP'!K185+'Requizo HVCDP'!K200+'Lucido HVCDP'!K218+'Rimas HVCDP'!K190) -> 1.6 | ... W26: =SUM('Piamonte HVCDP'!W185+'Requizo HVCDP'!W200+'Lucido HVCDP'!W218+'Rimas HVCDP'!W190) -> 0
B27: Avocado | C27: =COUNTA('Piamonte HVCDP'!D186:D195,'Requizo HVCDP'!D201:D210,'Lucido HVCDP'!D219:D228,'Rimas HVCDP'!D191:D200) -> 40 | D27: =SUM('Piamonte HVCDP'!D196+'Requizo HVCDP'!D211+'Lucido HVCDP'!D229+'Rimas HVCDP'!D201) -> 97 | E27: =SUM('Piamonte HVCDP'!E196+'Requizo HVCDP'!E211+'Lucido HVCDP'!E229+'Rimas HVCDP'!E201) -> 22.1845 | F27: =SUM('Piamonte HVCDP'!F196+'Requizo HVCDP'!F211+'Lucido HVCDP'!F229+'Rimas HVCDP'!F201) -> 0 | G27: =SUM('Piamonte HVCDP'!G196+'Requizo HVCDP'!G211+'Lucido HVCDP'!G229+'Rimas HVCDP'!G201) -> 22.1845 | H27: =SUM('Piamonte HVCDP'!H196+'Requizo HVCDP'!H211+'Lucido HVCDP'!H229+'Rimas HVCDP'!H201) -> 0.5 | I27: =SUM('Piamonte HVCDP'!I196+'Requizo HVCDP'!I211+'Lucido HVCDP'!I229+'Rimas HVCDP'!I201) -> 0 | J27: =SUM('Piamonte HVCDP'!J196+'Requizo HVCDP'!J211+'Lucido HVCDP'!J229+'Rimas HVCDP'!J201) -> 0.5 | K27: =SUM('Piamonte HVCDP'!K196+'Requizo HVCDP'!K211+'Lucido HVCDP'!K229+'Rimas HVCDP'!K201) -> 2.5 | ... W27: =SUM('Piamonte HVCDP'!W196+'Requizo HVCDP'!W211+'Lucido HVCDP'!W229+'Rimas HVCDP'!W201) -> 0
B28: Papaya | C28: =COUNTA('Piamonte HVCDP'!D197:D206,'Requizo HVCDP'!D212:D221,'Lucido HVCDP'!D230:D239,'Rimas HVCDP'!D202:D211) -> 40 | D28: =SUM('Piamonte HVCDP'!D207+'Requizo HVCDP'!D222+'Lucido HVCDP'!D240+'Rimas HVCDP'!D212) -> 92 | E28: =SUM('Piamonte HVCDP'!E207+'Requizo HVCDP'!E222+'Lucido HVCDP'!E240+'Rimas HVCDP'!E212) -> 17.934 | F28: =SUM('Piamonte HVCDP'!F207+'Requizo HVCDP'!F222+'Lucido HVCDP'!F240+'Rimas HVCDP'!F212) -> 0 | G28: =SUM('Piamonte HVCDP'!G207+'Requizo HVCDP'!G222+'Lucido HVCDP'!G240+'Rimas HVCDP'!G212) -> 17.934 | H28: =SUM('Piamonte HVCDP'!H207+'Requizo HVCDP'!H222+'Lucido HVCDP'!H240+'Rimas HVCDP'!H212) -> 0.6 | I28: =SUM('Piamonte HVCDP'!I207+'Requizo HVCDP'!I222+'Lucido HVCDP'!I240+'Rimas HVCDP'!I212) -> 0 | J28: =SUM('Piamonte HVCDP'!J207+'Requizo HVCDP'!J222+'Lucido HVCDP'!J240+'Rimas HVCDP'!J212) -> 0.6 | K28: =SUM('Piamonte HVCDP'!K207+'Requizo HVCDP'!K222+'Lucido HVCDP'!K240+'Rimas HVCDP'!K212) -> 1.75 | ... W28: =SUM('Piamonte HVCDP'!W207+'Requizo HVCDP'!W222+'Lucido HVCDP'!W240+'Rimas HVCDP'!W212) -> 0
B29: Chico | C29: =COUNTA('Piamonte HVCDP'!D208:D217,'Requizo HVCDP'!D223:D232,'Lucido HVCDP'!D241:D250,'Rimas HVCDP'!D213:D222) -> 40 | D29: =SUM('Piamonte HVCDP'!D218+'Requizo HVCDP'!D233+'Lucido HVCDP'!D251+'Rimas HVCDP'!D223) -> 79 | E29: =SUM('Piamonte HVCDP'!E218+'Requizo HVCDP'!E233+'Lucido HVCDP'!E251+'Rimas HVCDP'!E223) -> 15.622 | F29: =SUM('Piamonte HVCDP'!F218+'Requizo HVCDP'!F233+'Lucido HVCDP'!F251+'Rimas HVCDP'!F223) -> 0 | G29: =SUM('Piamonte HVCDP'!G218+'Requizo HVCDP'!G233+'Lucido HVCDP'!G251+'Rimas HVCDP'!G223) -> 15.622 | H29: =SUM('Piamonte HVCDP'!H218+'Requizo HVCDP'!H233+'Lucido HVCDP'!H251+'Rimas HVCDP'!H223) -> 0.35 | I29: =SUM('Piamonte HVCDP'!I218+'Requizo HVCDP'!I233+'Lucido HVCDP'!I251+'Rimas HVCDP'!I223) -> 0 | J29: =SUM('Piamonte HVCDP'!J218+'Requizo HVCDP'!J233+'Lucido HVCDP'!J251+'Rimas HVCDP'!J223) -> 0.35 | K29: =SUM('Piamonte HVCDP'!K218+'Requizo HVCDP'!K233+'Lucido HVCDP'!K251+'Rimas HVCDP'!K223) -> 0.75 | ... W29: =SUM('Piamonte HVCDP'!W218+'Requizo HVCDP'!W233+'Lucido HVCDP'!W251+'Rimas HVCDP'!W223) -> 0
B30: Rambutan | C30: =COUNTA('Piamonte HVCDP'!D219:D228,'Requizo HVCDP'!D234:D243,'Lucido HVCDP'!D252:D261,'Rimas HVCDP'!D224:D233) -> 40 | D30: =SUM('Piamonte HVCDP'!D229+'Requizo HVCDP'!D244+'Lucido HVCDP'!D262+'Rimas HVCDP'!D234) -> 253 | E30: =SUM('Piamonte HVCDP'!E229+'Requizo HVCDP'!E244+'Lucido HVCDP'!E262+'Rimas HVCDP'!E234) -> 67.1125 | F30: =SUM('Piamonte HVCDP'!F229+'Requizo HVCDP'!F244+'Lucido HVCDP'!F262+'Rimas HVCDP'!F234) -> 0 | G30: =SUM('Piamonte HVCDP'!G229+'Requizo HVCDP'!G244+'Lucido HVCDP'!G262+'Rimas HVCDP'!G234) -> 67.1125 | H30: =SUM('Piamonte HVCDP'!H229+'Requizo HVCDP'!H244+'Lucido HVCDP'!H262+'Rimas HVCDP'!H234) -> 0.09 | I30: =SUM('Piamonte HVCDP'!I229+'Requizo HVCDP'!I244+'Lucido HVCDP'!I262+'Rimas HVCDP'!I234) -> 0 | J30: =SUM('Piamonte HVCDP'!J229+'Requizo HVCDP'!J244+'Lucido HVCDP'!J262+'Rimas HVCDP'!J234) -> 0.09 | K30: =SUM('Piamonte HVCDP'!K229+'Requizo HVCDP'!K244+'Lucido HVCDP'!K262+'Rimas HVCDP'!K234) -> 1.62 | ... W30: =SUM('Piamonte HVCDP'!W229+'Requizo HVCDP'!W244+'Lucido HVCDP'!W262+'Rimas HVCDP'!W234) -> 0
B31: Mango | C31: =COUNTA('Piamonte HVCDP'!D230:D239,'Requizo HVCDP'!D234:D243,'Lucido HVCDP'!D252:D261,'Rimas HVCDP'!D224:D233) -> 40 | D31: =SUM('Piamonte HVCDP'!D240+'Requizo HVCDP'!D255+'Lucido HVCDP'!D273+'Rimas HVCDP'!D245) -> 62 | E31: =SUM('Piamonte HVCDP'!E240+'Requizo HVCDP'!E255+'Lucido HVCDP'!E273+'Rimas HVCDP'!E245) -> 18.606 | F31: =SUM('Piamonte HVCDP'!F240+'Requizo HVCDP'!F255+'Lucido HVCDP'!F273+'Rimas HVCDP'!F245) -> 0 | G31: =SUM('Piamonte HVCDP'!G240+'Requizo HVCDP'!G255+'Lucido HVCDP'!G273+'Rimas HVCDP'!G245) -> 18.606 | H31: =SUM('Piamonte HVCDP'!H240+'Requizo HVCDP'!H255+'Lucido HVCDP'!H273+'Rimas HVCDP'!H245) -> 3.3 | I31: =SUM('Piamonte HVCDP'!I240+'Requizo HVCDP'!I255+'Lucido HVCDP'!I273+'Rimas HVCDP'!I245) -> 0 | J31: =SUM('Piamonte HVCDP'!J240+'Requizo HVCDP'!J255+'Lucido HVCDP'!J273+'Rimas HVCDP'!J245) -> 3.3 | K31: =SUM('Piamonte HVCDP'!K240+'Requizo HVCDP'!K255+'Lucido HVCDP'!K273+'Rimas HVCDP'!K245) -> 39.6 | ... W31: =SUM('Piamonte HVCDP'!W240+'Requizo HVCDP'!W255+'Lucido HVCDP'!W273+'Rimas HVCDP'!W245) -> 0
B32: Lanzones | C32: =COUNTA('Piamonte HVCDP'!D241:D250,'Requizo HVCDP'!D256:D265,'Lucido HVCDP'!D274:D283,'Rimas HVCDP'!D246:D255) -> 40 | D32: =SUM('Piamonte HVCDP'!D251+'Requizo HVCDP'!D266+'Lucido HVCDP'!D284+'Rimas HVCDP'!D256) -> 234 | E32: =SUM('Piamonte HVCDP'!E251+'Requizo HVCDP'!E266+'Lucido HVCDP'!E284+'Rimas HVCDP'!E256) -> 86.7175 | F32: =SUM('Piamonte HVCDP'!F251+'Requizo HVCDP'!F266+'Lucido HVCDP'!F284+'Rimas HVCDP'!F256) -> 0 | G32: =SUM('Piamonte HVCDP'!G251+'Requizo HVCDP'!G266+'Lucido HVCDP'!G284+'Rimas HVCDP'!G256) -> 86.7175 | H32: =SUM('Piamonte HVCDP'!H251+'Requizo HVCDP'!H266+'Lucido HVCDP'!H284+'Rimas HVCDP'!H256) -> 0 | I32: =SUM('Piamonte HVCDP'!I251+'Requizo HVCDP'!I266+'Lucido HVCDP'!I284+'Rimas HVCDP'!I256) -> 0 | J32: =SUM('Piamonte HVCDP'!J251+'Requizo HVCDP'!J266+'Lucido HVCDP'!J284+'Rimas HVCDP'!J256) -> 0 | K32: =SUM('Piamonte HVCDP'!K251+'Requizo HVCDP'!K266+'Lucido HVCDP'!K284+'Rimas HVCDP'!K256) -> 0 | ... W32: =SUM('Piamonte HVCDP'!W251+'Requizo HVCDP'!W266+'Lucido HVCDP'!W284+'Rimas HVCDP'!W256) -> 0
B33: LEAFY VEGETABLES
B34: Malunggay | C34: =COUNTA('Piamonte HVCDP'!D253:D262,'Requizo HVCDP'!D268:D277,'Lucido HVCDP'!D286:D295,'Rimas HVCDP'!D258:D267) -> 21 | D34: =SUM('Piamonte HVCDP'!D263+'Requizo HVCDP'!D278+'Lucido HVCDP'!D296+'Rimas HVCDP'!D268) -> 275 | E34: =SUM('Piamonte HVCDP'!E263+'Requizo HVCDP'!E278+'Lucido HVCDP'!E296+'Rimas HVCDP'!E268) -> 85.5795 | F34: =SUM('Piamonte HVCDP'!F263+'Requizo HVCDP'!F278+'Lucido HVCDP'!F296+'Rimas HVCDP'!F268) -> 0 | G34: =SUM('Piamonte HVCDP'!G263+'Requizo HVCDP'!G278+'Lucido HVCDP'!G296+'Rimas HVCDP'!G268) -> 85.5795 | H34: =SUM('Piamonte HVCDP'!H263+'Requizo HVCDP'!H278+'Lucido HVCDP'!H296+'Rimas HVCDP'!H268) -> 1.5 | I34: =SUM('Piamonte HVCDP'!I263+'Requizo HVCDP'!I278+'Lucido HVCDP'!I296+'Rimas HVCDP'!I268) -> 0 | J34: =SUM('Piamonte HVCDP'!J263+'Requizo HVCDP'!J278+'Lucido HVCDP'!J296+'Rimas HVCDP'!J268) -> 1.5 | K34: =SUM('Piamonte HVCDP'!K263+'Requizo HVCDP'!K278+'Lucido HVCDP'!K296+'Rimas HVCDP'!K268) -> 5 | ... W34: =SUM('Piamonte HVCDP'!W263+'Requizo HVCDP'!W278+'Lucido HVCDP'!W296+'Rimas HVCDP'!W268) -> 0
B35: Mustasa | C35: =COUNTA('Piamonte HVCDP'!D264:D273,'Requizo HVCDP'!D279:D288,'Lucido HVCDP'!D297:D306,'Rimas HVCDP'!D269:D278) -> 5 | D35: =SUM('Piamonte HVCDP'!D274+'Requizo HVCDP'!D289+'Lucido HVCDP'!D307+'Rimas HVCDP'!D279) -> 10 | E35: =SUM('Piamonte HVCDP'!E274+'Requizo HVCDP'!E289+'Lucido HVCDP'!E307+'Rimas HVCDP'!E279) -> 5.25 | F35: =SUM('Piamonte HVCDP'!F274+'Requizo HVCDP'!F289+'Lucido HVCDP'!F307+'Rimas HVCDP'!F279) -> 0 | G35: =SUM('Piamonte HVCDP'!G274+'Requizo HVCDP'!G289+'Lucido HVCDP'!G307+'Rimas HVCDP'!G279) -> 5.25 | H35: =SUM('Piamonte HVCDP'!H274+'Requizo HVCDP'!H289+'Lucido HVCDP'!H307+'Rimas HVCDP'!H279) -> 4.2 | I35: =SUM('Piamonte HVCDP'!I274+'Requizo HVCDP'!I289+'Lucido HVCDP'!I307+'Rimas HVCDP'!I279) -> 0 | J35: =SUM('Piamonte HVCDP'!J274+'Requizo HVCDP'!J289+'Lucido HVCDP'!J307+'Rimas HVCDP'!J279) -> 4.2 | K35: =SUM('Piamonte HVCDP'!K274+'Requizo HVCDP'!K289+'Lucido HVCDP'!K307+'Rimas HVCDP'!K279) -> 27 | ... W35: =SUM('Piamonte HVCDP'!W274+'Requizo HVCDP'!W289+'Lucido HVCDP'!W307+'Rimas HVCDP'!W279) -> 0
B36: Pechay | C36: =COUNTA('Piamonte HVCDP'!D275:D284,'Requizo HVCDP'!D290:D299,'Lucido HVCDP'!D308:D317,'Rimas HVCDP'!D280:D289) -> 17 | D36: =SUM('Piamonte HVCDP'!D285+'Requizo HVCDP'!D300+'Lucido HVCDP'!D318+'Rimas HVCDP'!D290) -> 114 | E36: =SUM('Piamonte HVCDP'!E285+'Requizo HVCDP'!E300+'Lucido HVCDP'!E318+'Rimas HVCDP'!E290) -> 85.69 | F36: =SUM('Piamonte HVCDP'!F285+'Requizo HVCDP'!F300+'Lucido HVCDP'!F318+'Rimas HVCDP'!F290) -> 0 | G36: =SUM('Piamonte HVCDP'!G285+'Requizo HVCDP'!G300+'Lucido HVCDP'!G318+'Rimas HVCDP'!G290) -> 85.69 | H36: =SUM('Piamonte HVCDP'!H285+'Requizo HVCDP'!H300+'Lucido HVCDP'!H318+'Rimas HVCDP'!H290) -> 65.75 | I36: =SUM('Piamonte HVCDP'!I285+'Requizo HVCDP'!I300+'Lucido HVCDP'!I318+'Rimas HVCDP'!I290) -> 0 | J36: =SUM('Piamonte HVCDP'!J285+'Requizo HVCDP'!J300+'Lucido HVCDP'!J318+'Rimas HVCDP'!J290) -> 65.75 | K36: =SUM('Piamonte HVCDP'!K285+'Requizo HVCDP'!K300+'Lucido HVCDP'!K318+'Rimas HVCDP'!K290) -> 530.38 | ... W36: =SUM('Piamonte HVCDP'!W285+'Requizo HVCDP'!W300+'Lucido HVCDP'!W318+'Rimas HVCDP'!W290) -> 0
B37: ROOTCROPS
B38: Radish | C38: =COUNTA('Lucido HVCDP'!D320:D329) -> 0 | D38: =SUM('Lucido HVCDP'!D330) -> 0 | E38: =SUM('Lucido HVCDP'!E330) -> 0 | F38: =SUM('Lucido HVCDP'!F330) -> 0 | G38: =SUM('Lucido HVCDP'!G330) -> 0 | H38: =SUM('Lucido HVCDP'!H330) -> 0 | I38: =SUM('Lucido HVCDP'!I330) -> 0 | J38: =SUM('Lucido HVCDP'!J330) -> 0 | K38: =SUM('Lucido HVCDP'!K330) -> 0 | ... W38: =SUM('Lucido HVCDP'!W330) -> 0
B39: Ginger | C39: =COUNTA('Piamonte HVCDP'!D287:D296,'Requizo HVCDP'!D302:D311,'Lucido HVCDP'!D331:D340,'Rimas HVCDP'!D292:D301) -> 3 | D39: =SUM('Piamonte HVCDP'!D297+'Requizo HVCDP'!D312+'Lucido HVCDP'!D341+'Rimas HVCDP'!D302) -> 2 | E39: =SUM('Piamonte HVCDP'!E297+'Requizo HVCDP'!E312+'Lucido HVCDP'!E341+'Rimas HVCDP'!E302) -> 0.5 | F39: =SUM('Piamonte HVCDP'!F297+'Requizo HVCDP'!F312+'Lucido HVCDP'!F341+'Rimas HVCDP'!F302) -> 0 | G39: =SUM('Piamonte HVCDP'!G297+'Requizo HVCDP'!G312+'Lucido HVCDP'!G341+'Rimas HVCDP'!G302) -> 0.5 | H39: =SUM('Piamonte HVCDP'!H297+'Requizo HVCDP'!H312+'Lucido HVCDP'!H341+'Rimas HVCDP'!H302) -> 0.25 | I39: =SUM('Piamonte HVCDP'!I297+'Requizo HVCDP'!I312+'Lucido HVCDP'!I341+'Rimas HVCDP'!I302) -> 0 | J39: =SUM('Piamonte HVCDP'!J297+'Requizo HVCDP'!J312+'Lucido HVCDP'!J341+'Rimas HVCDP'!J302) -> 0.25 | K39: =SUM('Piamonte HVCDP'!K297+'Requizo HVCDP'!K312+'Lucido HVCDP'!K341+'Rimas HVCDP'!K302) -> 0.12 | ... W39: =SUM('Piamonte HVCDP'!W297+'Requizo HVCDP'!W312+'Lucido HVCDP'!W341+'Rimas HVCDP'!W302) -> 0
B40: Ubi | C40: =COUNTA('Piamonte HVCDP'!D298:D307,'Requizo HVCDP'!D313:D322,'Lucido HVCDP'!D342:D351,'Rimas HVCDP'!D303:D312) -> 2 | D40: =SUM('Piamonte HVCDP'!D308+'Requizo HVCDP'!D323+'Lucido HVCDP'!D352+'Rimas HVCDP'!D313) -> 1 | E40: =SUM('Piamonte HVCDP'!E308+'Requizo HVCDP'!E323+'Lucido HVCDP'!E352+'Rimas HVCDP'!E313) -> 0.05 | F40: =SUM('Piamonte HVCDP'!F308+'Requizo HVCDP'!F323+'Lucido HVCDP'!F352+'Rimas HVCDP'!F313) -> 0 | G40: =SUM('Piamonte HVCDP'!G308+'Requizo HVCDP'!G323+'Lucido HVCDP'!G352+'Rimas HVCDP'!G313) -> 0.05 | H40: =SUM('Piamonte HVCDP'!H308+'Requizo HVCDP'!H323+'Lucido HVCDP'!H352+'Rimas HVCDP'!H313) -> 0 | I40: =SUM('Piamonte HVCDP'!I308+'Requizo HVCDP'!I323+'Lucido HVCDP'!I352+'Rimas HVCDP'!I313) -> 0 | J40: =SUM('Piamonte HVCDP'!J308+'Requizo HVCDP'!J323+'Lucido HVCDP'!J352+'Rimas HVCDP'!J313) -> 0 | K40: =SUM('Piamonte HVCDP'!K308+'Requizo HVCDP'!K323+'Lucido HVCDP'!K352+'Rimas HVCDP'!K313) -> 0 | ... W40: =SUM('Piamonte HVCDP'!W308+'Requizo HVCDP'!W323+'Lucido HVCDP'!W352+'Rimas HVCDP'!W313) -> 0
B41: Peanut | C41: =COUNTA('Piamonte HVCDP'!D309:D318,'Requizo HVCDP'!D324:D333,'Lucido HVCDP'!D353:D362,'Rimas HVCDP'!D314:D323) -> 4 | D41: =SUM('Piamonte HVCDP'!D319+'Requizo HVCDP'!D334+'Lucido HVCDP'!D363+'Rimas HVCDP'!D324) -> 3 | E41: =SUM('Piamonte HVCDP'!E319+'Requizo HVCDP'!E334+'Lucido HVCDP'!E363+'Rimas HVCDP'!E324) -> 0.8 | F41: =SUM('Piamonte HVCDP'!F319+'Requizo HVCDP'!F334+'Lucido HVCDP'!F363+'Rimas HVCDP'!F324) -> 0 | G41: =SUM('Piamonte HVCDP'!G319+'Requizo HVCDP'!G334+'Lucido HVCDP'!G363+'Rimas HVCDP'!G324) -> 0.8 | H41: =SUM('Piamonte HVCDP'!H319+'Requizo HVCDP'!H334+'Lucido HVCDP'!H363+'Rimas HVCDP'!H324) -> 0 | I41: =SUM('Piamonte HVCDP'!I319+'Requizo HVCDP'!I334+'Lucido HVCDP'!I363+'Rimas HVCDP'!I324) -> 0 | J41: =SUM('Piamonte HVCDP'!J319+'Requizo HVCDP'!J334+'Lucido HVCDP'!J363+'Rimas HVCDP'!J324) -> 0 | K41: =SUM('Piamonte HVCDP'!K319+'Requizo HVCDP'!K334+'Lucido HVCDP'!K363+'Rimas HVCDP'!K324) -> 0 | ... W41: =SUM('Piamonte HVCDP'!W319+'Requizo HVCDP'!W334+'Lucido HVCDP'!W363+'Rimas HVCDP'!W324) -> 0
B42: Sweet Potato | C42: =COUNTA('Piamonte HVCDP'!D320:D329,'Requizo HVCDP'!D335:D344,'Lucido HVCDP'!D364:D373,'Rimas HVCDP'!D325:D334) -> 1 | D42: =SUM('Piamonte HVCDP'!D330+'Requizo HVCDP'!D345+'Lucido HVCDP'!D374+'Rimas HVCDP'!D335) -> 0 | E42: =SUM('Piamonte HVCDP'!E330+'Requizo HVCDP'!E345+'Lucido HVCDP'!E374+'Rimas HVCDP'!E335) -> 0 | F42: =SUM('Piamonte HVCDP'!F330+'Requizo HVCDP'!F345+'Lucido HVCDP'!F374+'Rimas HVCDP'!F335) -> 0 | G42: =SUM('Piamonte HVCDP'!G330+'Requizo HVCDP'!G345+'Lucido HVCDP'!G374+'Rimas HVCDP'!G335) -> 0 | H42: =SUM('Piamonte HVCDP'!H330+'Requizo HVCDP'!H345+'Lucido HVCDP'!H374+'Rimas HVCDP'!H335) -> 0 | I42: =SUM('Piamonte HVCDP'!I330+'Requizo HVCDP'!I345+'Lucido HVCDP'!I374+'Rimas HVCDP'!I335) -> 0 | J42: =SUM('Piamonte HVCDP'!J330+'Requizo HVCDP'!J345+'Lucido HVCDP'!J374+'Rimas HVCDP'!J335) -> 0 | K42: =SUM('Piamonte HVCDP'!K330+'Requizo HVCDP'!K345+'Lucido HVCDP'!K374+'Rimas HVCDP'!K335) -> 0 | ... W42: =SUM('Piamonte HVCDP'!W330+'Requizo HVCDP'!W345+'Lucido HVCDP'!W374+'Rimas HVCDP'!W335) -> 0
B43: BULB
B44: Garlic | C44: =COUNTA('Piamonte HVCDP'!D332:D341,'Requizo HVCDP'!D347:D356,'Lucido HVCDP'!D376:D385,'Rimas HVCDP'!D337:D346) -> 1 | D44: =SUM('Piamonte HVCDP'!D342+'Requizo HVCDP'!D357+'Lucido HVCDP'!D386+'Rimas HVCDP'!D347) -> 0 | E44: =SUM('Piamonte HVCDP'!E342+'Requizo HVCDP'!E357+'Lucido HVCDP'!E386+'Rimas HVCDP'!E347) -> 0 | F44: =SUM('Piamonte HVCDP'!F342+'Requizo HVCDP'!F357+'Lucido HVCDP'!F386+'Rimas HVCDP'!F347) -> 0 | G44: =SUM('Piamonte HVCDP'!G342+'Requizo HVCDP'!G357+'Lucido HVCDP'!G386+'Rimas HVCDP'!G347) -> 0 | H44: =SUM('Piamonte HVCDP'!H342+'Requizo HVCDP'!H357+'Lucido HVCDP'!H386+'Rimas HVCDP'!H347) -> 0 | I44: =SUM('Piamonte HVCDP'!I342+'Requizo HVCDP'!I357+'Lucido HVCDP'!I386+'Rimas HVCDP'!I347) -> 0 | J44: =SUM('Piamonte HVCDP'!J342+'Requizo HVCDP'!J357+'Lucido HVCDP'!J386+'Rimas HVCDP'!J347) -> 0 | K44: =SUM('Piamonte HVCDP'!K342+'Requizo HVCDP'!K357+'Lucido HVCDP'!K386+'Rimas HVCDP'!K347) -> 0 | ... W44: =SUM('Piamonte HVCDP'!W342+'Requizo HVCDP'!W357+'Lucido HVCDP'!W386+'Rimas HVCDP'!W347) -> 0
B45: Onion | C45: =COUNTA('Piamonte HVCDP'!D343:D352,'Requizo HVCDP'!D358:D367,'Lucido HVCDP'!D387:D396,'Rimas HVCDP'!D348:D357) -> 1 | D45: =SUM('Piamonte HVCDP'!D353+'Requizo HVCDP'!D368+'Lucido HVCDP'!D397+'Rimas HVCDP'!D358) -> 0 | E45: =SUM('Piamonte HVCDP'!E353+'Requizo HVCDP'!E368+'Lucido HVCDP'!E397+'Rimas HVCDP'!E358) -> 0 | F45: =SUM('Piamonte HVCDP'!F353+'Requizo HVCDP'!F368+'Lucido HVCDP'!F397+'Rimas HVCDP'!F358) -> 0 | G45: =SUM('Piamonte HVCDP'!G353+'Requizo HVCDP'!G368+'Lucido HVCDP'!G397+'Rimas HVCDP'!G358) -> 0 | H45: =SUM('Piamonte HVCDP'!H353+'Requizo HVCDP'!H368+'Lucido HVCDP'!H397+'Rimas HVCDP'!H358) -> 0 | I45: =SUM('Piamonte HVCDP'!I353+'Requizo HVCDP'!I368+'Lucido HVCDP'!I397+'Rimas HVCDP'!I358) -> 0 | J45: =SUM('Piamonte HVCDP'!J353+'Requizo HVCDP'!J368+'Lucido HVCDP'!J397+'Rimas HVCDP'!J358) -> 0 | K45: =SUM('Piamonte HVCDP'!K353+'Requizo HVCDP'!K368+'Lucido HVCDP'!K397+'Rimas HVCDP'!K358) -> 0 | ... W45: =SUM('Piamonte HVCDP'!W353+'Requizo HVCDP'!W368+'Lucido HVCDP'!W397+'Rimas HVCDP'!W358) -> 0
B47: Submitted by: | R47: Noted by:
B50: Sherwin M. Rimas | R50: ATTY. FERDINAND Q. PEREZ
B51: City Agriculturist | R51: Acting City Administrator

Sheet Piamonte Summary
A1: MONTHLY AGRICULTURAL/FISHERY SITUATION REPORT
A2: Barangays Covered: Altura Matanda, Altura South, Banadero, Bilog-Bilog, Luyos, Malaking Pulo, Montana, Sala, Santor, Sulpoc
A4: District | B4: Commodity | C4: No. of Barangays Covered | D4: This Mo. | E4: Stage of Growth | F4: No. of Barangays Covered | G4: Area Harvested | H4: Estimated Production
A5: III | B5: FRUIT VEGETABLES
B6: Eggplant | C6: =COUNTA('[1]Piamonte HVCDP'!F6:F15) -> 0 | D6: ='[1]Piamonte HVCDP'!F16 -> 0 | E6: =IF(D6>0, "Vegetative", "No Planting") -> No Planting | F6: =COUNTA('[1]Piamonte HVCDP'!L5:L15) -> 1 | G6: ='[1]Piamonte HVCDP'!I16 -> 0.6 | H6: =IF(G6=0,"No Production",'[1]Piamonte HVCDP'!L16) -> 6.6
B7: Sitao | C7: =COUNTA('[1]Piamonte HVCDP'!F17:F26) -> 0 | D7: ='[1]Piamonte HVCDP'!F27 -> 0 | E7: =IF(D7>0, "Vegetative", "No Planting") -> No Planting | F7: =COUNTA('[1]Piamonte HVCDP'!L17:L26) -> 0 | G7: ='[1]Piamonte HVCDP'!I27 -> 0 | H7: =IF(G7=0,"No Production",'[1]Piamonte HVCDP'!L27) -> No Production
B8: Squash | C8: =COUNTA('[1]Piamonte HVCDP'!F28:F37) -> 0 | D8: ='[1]Piamonte HVCDP'!F38 -> 0 | E8: =IF(D8>0, "Vegetative", "No Planting") -> No Planting | F8: =COUNTA('[1]Piamonte HVCDP'!I28:I37) -> 0 | G8: ='[1]Piamonte HVCDP'!I38 -> 0 | H8: =IF(G8=0,"No Production",'[1]Piamonte HVCDP'!L38) -> No Production
B9: Okra | C9: =COUNTA('[1]Piamonte HVCDP'!F39:F48) -> 1 | D9: ='[1]Piamonte HVCDP'!F49 -> 0.25 | E9: =IF(D9>0, "Vegetative", "No Planting") -> Vegetative | F9: =COUNTA('[1]Piamonte HVCDP'!I39:I48) -> 0 | G9: ='[1]Piamonte HVCDP'!H49 -> 3.25 | H9: =IF(G9=0,"No Production",'[1]Piamonte HVCDP'!L49) -> 0
B10: Patola | C10: =COUNTA('[1]Piamonte HVCDP'!F50:F59) -> 0 | D10: ='[1]Piamonte HVCDP'!F60 -> 0 | E10: =IF(D10>0, "Vegetative", "No Planting") -> No Planting | F10: =COUNTA('[1]Piamonte HVCDP'!I61:I70) -> 0 | G10: ='[1]Piamonte HVCDP'!H60 -> 3.85 | H10: =IF(G10=0,"No Production",'[1]Piamonte HVCDP'!L60) -> 0
B11: Sigarilyas | C11: =COUNTA('[1]Piamonte HVCDP'!F61:F70) -> 0 | D11: ='[1]Piamonte HVCDP'!F71 -> 0 | E11: =IF(D11>0, "Vegetative", "No Planting") -> No Planting | F11: =COUNTA('[1]Piamonte HVCDP'!I61:I70) -> 0 | G11: ='[1]Piamonte HVCDP'!H71 -> 16.3 | H11: =IF(G11=0,"No Production",'[1]Piamonte HVCDP'!L71) -> 0
B12: Upo | C12: =COUNTA('[1]Piamonte HVCDP'!F72:F81) -> 0 | D12: ='[1]Piamonte HVCDP'!F82 -> 0 | E12: =IF(D12>0, "Vegetative", "No Planting") -> No Planting | F12: =COUNTA('[1]Piamonte HVCDP'!I72:I81) -> 0 | G12: ='[1]Piamonte HVCDP'!I82 -> 0 | H12: =IF(G12=0,"No Production",'[1]Piamonte HVCDP'!L82) -> No Production
B13: Ampalaya | C13: =COUNTA('[1]Piamonte HVCDP'!F83:F92) -> 0 | D13: ='[1]Piamonte HVCDP'!F93 -> 0 | E13: =IF(D13>0, "Vegetative", "No Planting") -> No Planting | F13: =COUNTA('[1]Piamonte HVCDP'!I83:I92) -> 0 | G13: ='[1]Piamonte HVCDP'!I93 -> 0 | H13: =IF(G13=0,"No Production",'[1]Piamonte HVCDP'!L93) -> No Production
B14: Pipino | C14: =COUNTA('[1]Piamonte HVCDP'!F94:F103) -> 0 | D14: ='[1]Piamonte HVCDP'!F104 -> 0 | E14: =IF(D14>0, "Vegetative", "No Planting") -> No Planting | F14: =COUNTA('[1]Piamonte HVCDP'!I94:I103) -> 0 | G14: ='[1]Piamonte HVCDP'!I104 -> 0 | H14: =IF(G14=0,"No Production",'[1]Piamonte HVCDP'!L104) -> No Production
B15: Sili | C15: =COUNTA('[1]Piamonte HVCDP'!F105:F114) -> 0 | D15: ='[1]Piamonte HVCDP'!F115 -> 0 | E15: =IF(D15>0, "Vegetative", "No Planting") -> No Planting | F15: =COUNTA('[1]Piamonte HVCDP'!I105:I114) -> 0 | G15: ='[1]Piamonte HVCDP'!I115 -> 0 | H15: =IF(G15=0,"No Production",'[1]Piamonte HVCDP'!L115) -> No Production
B16: Beans | C16: =COUNTA('[1]Piamonte HVCDP'!F116:F125) -> 0 | D16: ='[1]Piamonte HVCDP'!F126 -> 0 | E16: =IF(D16>0, "Vegetative", "No Planting") -> No Planting | F16: =COUNTA('[1]Piamonte HVCDP'!I116:I125) -> 0 | G16: ='[1]Piamonte HVCDP'!I126 -> 0 | H16: =IF(G16=0,"No Production",'[1]Piamonte HVCDP'!L126) -> No Production
B17: Paayap | C17: =COUNTA('[1]Piamonte HVCDP'!F127:F136) -> 0 | D17: ='[1]Piamonte HVCDP'!F137 -> 0 | E17: =IF(D17>0, "Vegetative", "No Planting") -> No Planting | F17: =COUNTA('[1]Piamonte HVCDP'!I127:I136) -> 0 | G17: ='[1]Piamonte HVCDP'!I137 -> 0 | H17: =IF(G17=0,"No Production",'[1]Piamonte HVCDP'!L137) -> No Production
B18: Tomato | C18: =COUNTA('[1]Piamonte HVCDP'!F138:F147) -> 0 | D18: ='[1]Piamonte HVCDP'!F148 -> 0 | E18: =IF(D18>0, "Vegetative", "No Planting") -> No Planting | F18: =COUNTA('[1]Piamonte HVCDP'!I138:I147) -> 0 | G18: ='[1]Piamonte HVCDP'!I148 -> 0 | H18: =IF(G18=0,"No Production",'[1]Piamonte HVCDP'!L148) -> No Production
B19: INDUSTRIAL CROPS
B20: Banana | C20: =COUNTA('[1]Piamonte HVCDP'!F150:F159) -> 0 | D20: ='[1]Piamonte HVCDP'!F160 -> 0 | E20: =IF(D20>0, "Vegetative", "No Planting") -> No Planting | F20: =COUNTA('[1]Piamonte HVCDP'!I149:I159) -> 0 | G20: ='[1]Piamonte HVCDP'!I160 -> 0 | H20: =IF(G20=0,"No Production",'[1]Piamonte HVCDP'!L160) -> No Production
B21: Cacao | C21: =COUNTA('[1]Piamonte HVCDP'!F161:F170) -> 0 | D21: ='[1]Piamonte HVCDP'!F171 -> 0 | E21: =IF(D21>0, "Vegetative", "No Planting") -> No Planting | F21: =COUNTA('[1]Piamonte HVCDP'!I161:I170) -> 0 | G21: ='[1]Piamonte HVCDP'!I171 -> 0 | H21: =IF(G21=0,"No Production",'[1]Piamonte HVCDP'!L171) -> No Production
B22: Coffee | C22: =COUNTA('[1]Piamonte HVCDP'!F172) -> 0 | D22: ='[1]Piamonte HVCDP'!F173 -> 0 | E22: =IF(D22>0, "Vegetative", "No Planting") -> No Planting | F22: =COUNTA('[1]Piamonte HVCDP'!I172) -> 0 | G22: ='[1]Piamonte HVCDP'!I173 -> 0 | H22: =IF(G22=0,"No Production",'[1]Piamonte HVCDP'!L173) -> No Production
B23: FRUIT TREES
B24: Calamansi | C24: =COUNTA('[1]Piamonte HVCDP'!F175:F184) -> 0 | D24: ='[1]Piamonte HVCDP'!F185 -> 0 | E24: =IF(D24>0, "Vegetative", "No Planting") -> No Planting | F24: =COUNTA('[1]Piamonte HVCDP'!I175:I184) -> 0 | G24: ='[1]Piamonte HVCDP'!I185 -> 0 | H24: =IF(G24=0,"No Production",'[1]Piamonte HVCDP'!L185) -> No Production
B25: Avocado | C25: =COUNTA('[1]Piamonte HVCDP'!F186:F195) -> 0 | D25: ='[1]Piamonte HVCDP'!F196 -> 0 | E25: =IF(D25>0, "Vegetative", "No Planting") -> No Planting | F25: =COUNTA('[1]Piamonte HVCDP'!I186:I195) -> 0 | G25: ='[1]Piamonte HVCDP'!I196 -> 0 | H25: =IF(G25=0,"No Production",'[1]Piamonte HVCDP'!L196) -> No Production
B26: Papaya | C26: =COUNTA('[1]Piamonte HVCDP'!F197:F206) -> 0 | D26: ='[1]Piamonte HVCDP'!F207 -> 0 | E26: =IF(D26>0, "Vegetative", "No Planting") -> No Planting | F26: =COUNTA('[1]Piamonte HVCDP'!I197:I206) -> 0 | G26: ='[1]Piamonte HVCDP'!I207 -> 0 | H26: =IF(G26=0,"No Production",'[1]Piamonte HVCDP'!L207) -> No Production
B27: Chico | C27: =COUNTA('[1]Piamonte HVCDP'!F208:F217) -> 0 | D27: ='[1]Piamonte HVCDP'!F218 -> 0 | E27: =IF(D27>0, "Vegetative", "No Planting") -> No Planting | F27: =COUNTA('[1]Piamonte HVCDP'!H208:H217) -> 0 | G27: ='[1]Piamonte HVCDP'!I218 -> 0 | H27: =IF(G27=0,"No Production",'[1]Piamonte HVCDP'!L218) -> No Production
B28: Rambutan | C28: =COUNTA('[1]Piamonte HVCDP'!F219:F228) -> 0 | D28: ='[1]Piamonte HVCDP'!F229 -> 0 | E28: =IF(D28>0, "Vegetative", "No Planting") -> No Planting | F28: =COUNTA('[1]Piamonte HVCDP'!I219:I228) -> 0 | G28: ='[1]Piamonte HVCDP'!I229 -> 0 | H28: =IF(G28=0,"No Production",'[1]Piamonte HVCDP'!L229) -> No Production
B29: Mango | C29: =COUNTA('[1]Piamonte HVCDP'!F230:F239) -> 0 | D29: ='[1]Piamonte HVCDP'!F240 -> 0 | E29: =IF(D29>0, "Vegetative", "No Planting") -> No Planting | F29: =COUNTA('[1]Piamonte HVCDP'!I230:I239) -> 0 | G29: ='[1]Piamonte HVCDP'!I240 -> 0 | H29: =IF(G29=0,"No Production",'[1]Piamonte HVCDP'!L240) -> No Production
B30: Lanzones | C30: =COUNTA('[1]Piamonte HVCDP'!F241:F250) -> 0 | D30: ='[1]Piamonte HVCDP'!F251 -> 0 | E30: =IF(D30>0, "Vegetative", "No Planting") -> No Planting | F30: =COUNTA('[1]Piamonte HVCDP'!I241:I250) -> 0 | G30: ='[1]Piamonte HVCDP'!I251 -> 0 | H30: =IF(G30=0,"No Production",'[1]Piamonte HVCDP'!L251) -> No Production
B31: LEAFY VEGETABLES
B32: Malunggay | C32: =COUNTA('[1]Piamonte HVCDP'!F253:F262) -> 0 | D32: ='[1]Piamonte HVCDP'!F263 -> 0 | E32: =IF(D32>0, "Vegetative", "No Planting") -> No Planting | F32: =COUNTA('[1]Piamonte HVCDP'!J253:J262) -> 0 | G32: ='[1]Piamonte HVCDP'!I263 -> 0 | H32: =IF(G32=0,"No Production",'[1]Piamonte HVCDP'!L263) -> No Production
B33: Mustasa | C33: =COUNTA('[1]Piamonte HVCDP'!F264:F273) -> 0 | D33: ='[1]Piamonte HVCDP'!F274 -> 0 | E33: =IF(D33>0, "Vegetative", "No Planting") -> No Planting | F33: =COUNTA('[1]Piamonte HVCDP'!I264:I273) -> 0 | G33: ='[1]Piamonte HVCDP'!I274 -> 0 | H33: =IF(G33=0,"No Production",'[1]Piamonte HVCDP'!L274) -> No Production
B34: Pechay | C34: =COUNTA('[1]Piamonte HVCDP'!F275:F284) -> 1 | D34: ='[1]Piamonte HVCDP'!F285 -> 0.3 | E34: =IF(D34>0, "Vegetative", "No Planting") -> Vegetative | F34: =COUNTA('[1]Piamonte HVCDP'!I275:I284) -> 1 | G34: ='[1]Piamonte HVCDP'!I285 -> 3 | H34: =IF(G34=0,"No Production",'[1]Piamonte HVCDP'!L285) -> 0.9
B35: ROOTCROPS
B36: Ginger | C36: =COUNTA('[1]Piamonte HVCDP'!F287:F296) -> 0 | D36: ='[1]Piamonte HVCDP'!F297 -> 0 | E36: =IF(D36>0, "Vegetative", "No Planting") -> No Planting | F36: =COUNTA('[1]Piamonte HVCDP'!I287:I296) -> 0 | G36: ='[1]Piamonte HVCDP'!I297 -> 0 | H36: =IF(G36=0,"No Production",'[1]Piamonte HVCDP'!L297) -> No Production
B37: Ubi | C37: =COUNTA('[1]Piamonte HVCDP'!F298:F307) -> 0 | D37: ='[1]Piamonte HVCDP'!F308 -> 0 | E37: =IF(D37>0, "Vegetative", "No Planting") -> No Planting | F37: =COUNTA('[1]Piamonte HVCDP'!I298:I307) -> 0 | G37: ='[1]Piamonte HVCDP'!I308 -> 0 | H37: =IF(G37=0,"No Production",'[1]Piamonte HVCDP'!L308) -> No Production
B38: Peanut | C38: =COUNTA('[1]Piamonte HVCDP'!F309:F318) -> 0 | D38: ='[1]Piamonte HVCDP'!F319 -> 0 | E38: =IF(D38>0, "Vegetative", "No Planting") -> No Planting | F38: =COUNTA('[1]Piamonte HVCDP'!I309:I318) -> 0 | G38: ='[1]Piamonte HVCDP'!I319 -> 0 | H38: =IF(G38=0,"No Production",'[1]Piamonte HVCDP'!L319) -> No Production
B39: Sweet Potato | C39: =COUNTA('[1]Piamonte HVCDP'!F320:F329) -> 0 | D39: ='[1]Piamonte HVCDP'!F330 -> 0 | E39: =IF(D39>0, "Vegetative", "No Planting") -> No Planting | F39: =COUNTA('[1]Piamonte HVCDP'!I320:I329) -> 0 | G39: ='[1]Piamonte HVCDP'!I330 -> 0 | H39: =IF(G39=0,"No Production",'[1]Piamonte HVCDP'!L330) -> No Production
B40: BULB
B41: Garlic | C41: =COUNTA('[1]Piamonte HVCDP'!F332:F341) -> 0 | D41: ='[1]Piamonte HVCDP'!F342 -> 0 | E41: =IF(D41>0, "Vegetative", "No Planting") -> No Planting | F41: =COUNTA('[1]Piamonte HVCDP'!I332:I341) -> 0 | G41: ='[1]Piamonte HVCDP'!I342 -> 0 | H41: =IF(G41=0,"No Production",'[1]Piamonte HVCDP'!L342) -> No Production
B42: Onion | C42: =COUNTA('[1]Piamonte HVCDP'!F343:F352) -> 0 | D42: ='[1]Piamonte HVCDP'!F353 -> 0 | E42: =IF(D42>0, "Vegetative", "No Planting") -> No Planting | F42: =COUNTA('[1]Piamonte HVCDP'!I343:I352) -> 0 | G42: ='[1]Piamonte HVCDP'!I353 -> 0 | H42: =IF(G42=0,"No Production",'[1]Piamonte HVCDP'!L353) -> No Production
B44: Submitted by: | F44: Noted by:
B47: Adrian V. Piamonte | F47: Sherwin M. Rimas
B48: Agricultural Technologist | F48: City Agriculturist

Sheet Lucido Summary
A1: MONTHLY AGRICULTURAL/FISHERY SITUATION REPORT
A2: Barangays Covered: Banjo East, Banjo West, Boot, Cale, Darasa, Hidalgo, Maugat, Natatas, Pantay Bata, Suplang
A4: District | B4: Commodity | C4: No. of Barangays Covered | D4: This Mo. | E4: Stage of Growth | F4: No. of Barangays Covered | G4: Area Harvested | H4: Estimated Production
A5: III | B5: FRUIT VEGETABLES
B6: Eggplant | C6: =COUNTA('[2]Lucido HVCDP'!F6:F15) -> 0 | D6: ='[2]Lucido HVCDP'!F16 -> 0 | E6: =IF(D6>0, "Vegetative", "No Planting") -> No Planting | F6: =COUNTA('[2]Lucido HVCDP'!I6:I15) -> 1 | G6: ='[2]Lucido HVCDP'!I16 -> 0.25 | H6: =IF(G6=0,"No Production",'[2]Lucido HVCDP'!L16) -> 1.25
B7: Sitao | C7: =COUNTA('[2]Lucido HVCDP'!F17:F26) -> 2 | D7: ='[2]Lucido HVCDP'!F27 -> 1.05 | E7: =IF(D7>0, "Vegetative", "No Planting") -> Vegetative | F7: =COUNTA('[2]Lucido HVCDP'!I17:I26) -> 0 | G7: ='[2]Lucido HVCDP'!I27 -> 0 | H7: =IF(G7=0,"No Production",'[2]Lucido HVCDP'!L27) -> No Production
B8: Squash | C8: =COUNTA('[2]Lucido HVCDP'!F28:F37) -> 0 | D8: ='[2]Lucido HVCDP'!F38 -> 0 | E8: =IF(D8>0, "Vegetative", "No Planting") -> No Planting | F8: =COUNTA('[2]Lucido HVCDP'!I28:I37) -> 0 | G8: ='[2]Lucido HVCDP'!I38 -> 0 | H8: =IF(G8=0,"No Production",'[2]Lucido HVCDP'!L38) -> No Production
B9: Okra | C9: =COUNTA('[2]Lucido HVCDP'!F39:F48) -> 0 | D9: ='[2]Lucido HVCDP'!F49 -> 0 | E9: =IF(D9>0, "Vegetative", "No Planting") -> No Planting | F9: =COUNTA('[2]Lucido HVCDP'!I39:I48) -> 0 | G9: ='[2]Lucido HVCDP'!I49 -> 0 | H9: =IF(G9=0,"No Production",'[2]Lucido HVCDP'!L49) -> No Production
B10: Patola | C10: =COUNTA('[2]Lucido HVCDP'!G50:G59) -> 1 | D10: ='[2]Lucido HVCDP'!F60 -> 0 | E10: =IF(D10>0, "Vegetative", "No Planting") -> No Planting | F10: =COUNTA('[2]Lucido HVCDP'!I50:I59) -> 0 | G10: ='[2]Lucido HVCDP'!I60 -> 0 | H10: =IF(G10=0,"No Production",'[2]Lucido HVCDP'!L60) -> No Production
B11: Sigarilyas | C11: =COUNTA('[2]Lucido HVCDP'!F61:F70) -> 0 | D11: ='[2]Lucido HVCDP'!F71 -> 0 | E11: =IF(D11>0, "Vegetative", "No Planting") -> No Planting | F11: =COUNTA('[2]Lucido HVCDP'!I61:I70) -> 0 | G11: ='[2]Lucido HVCDP'!I71 -> 0 | H11: =IF(G11=0,"No Production",'[2]Lucido HVCDP'!L71) -> No Production
B12: Upo | C12: =COUNTA('[2]Lucido HVCDP'!F72:F81) -> 1 | D12: ='[2]Lucido HVCDP'!F82 -> 0.5 | E12: =IF(D12>0, "Vegetative", "No Planting") -> Vegetative | F12: =COUNTA('[2]Lucido HVCDP'!I72:I81) -> 2 | G12: ='[2]Lucido HVCDP'!I82 -> 0.44 | H12: =IF(G12=0,"No Production",'[2]Lucido HVCDP'!L82) -> 2.2
B13: Ampalaya | C13: =COUNTA('[2]Lucido HVCDP'!F83:F92) -> 2 | D13: ='[2]Lucido HVCDP'!F93 -> 2.2 | E13: =IF(D13>0, "Vegetative", "No Planting") -> Vegetative | F13: =COUNTA('[2]Lucido HVCDP'!I83:I92) -> 0 | G13: ='[2]Lucido HVCDP'!I93 -> 0 | H13: =IF(G13=0,"No Production",'[2]Lucido HVCDP'!L93) -> No Production
B14: Pipino | C14: =COUNTA('[2]Lucido HVCDP'!F94:F103) -> 0 | D14: ='[2]Lucido HVCDP'!F104 -> 0 | E14: =IF(D14>0, "Vegetative", "No Planting") -> No Planting | F14: =COUNTA('[2]Lucido HVCDP'!I94:I103) -> 0 | G14: ='[2]Lucido HVCDP'!I104 -> 0 | H14: =IF(G14=0,"No Production",'[2]Lucido HVCDP'!L104) -> No Production
B15: Sili | C15: =COUNTA('[2]Lucido HVCDP'!F105:F114) -> 0 | D15: ='[2]Lucido HVCDP'!F115 -> 0 | E15: =IF(D15>0, "Vegetative", "No Planting") -> No Planting | F15: =COUNTA('[2]Lucido HVCDP'!I105:I114) -> 1 | G15: ='[2]Lucido HVCDP'!I115 -> 0.19 | H15: =IF(G15=0,"No Production",'[2]Lucido HVCDP'!L115) -> 0.95
B16: Beans | C16: =COUNTA('[2]Lucido HVCDP'!F127:F136) -> 0 | D16: ='[2]Lucido HVCDP'!F137 -> 0 | E16: =IF(D16>0, "Vegetative", "No Planting") -> No Planting | F16: =COUNTA('[2]Lucido HVCDP'!I127:I136) -> 0 | G16: ='[2]Lucido HVCDP'!I137 -> 0 | H16: =IF(G16=0,"No Production",'[2]Lucido HVCDP'!L137) -> No Production
B17: Paayap | C17: =COUNTA('[2]Lucido HVCDP'!F160:F169) -> 1 | D17: ='[2]Lucido HVCDP'!F170 -> 0.4 | E17: =IF(D17>0, "Vegetative", "No Planting") -> Vegetative | F17: =COUNTA('[2]Lucido HVCDP'!I160:I169) -> 0 | G17: ='[2]Lucido HVCDP'!I170 -> 0 | H17: =IF(G17=0,"No Production",'[2]Lucido HVCDP'!L170) -> No Production
B18: Tomato | C18: =COUNTA('[2]Lucido HVCDP'!F171:F180) -> 2 | D18: ='[2]Lucido HVCDP'!F181 -> 1 | E18: =IF(D18>0, "Vegetative", "No Planting") -> Vegetative | F18: =COUNTA('[2]Lucido HVCDP'!I171:I180) -> 1 | G18: ='[2]Lucido HVCDP'!I181 -> 0.19 | H18: =IF(G18=0,"No Production",'[2]Lucido HVCDP'!L181) -> 0.95
B19: Patani | C19: =COUNTA('[2]Lucido HVCDP'!F138:F147) -> 0 | D19: ='[2]Lucido HVCDP'!F148 -> 0 | E19: =IF(D19>0, "Vegetative", "No Planting") -> No Planting | F19: =COUNTA('[2]Lucido HVCDP'!I138:I147) -> 0 | G19: ='[2]Lucido HVCDP'!I148 -> 0 | H19: =IF(G19=0,"No Production",'[2]Lucido HVCDP'!L148) -> No Production
B20: Mungbean | C20: =COUNTA('[2]Lucido HVCDP'!F116:F125) -> 0 | D20: ='[2]Lucido HVCDP'!F126 -> 0 | E20: =IF(D20>0, "Vegetative", "No Planting") -> No Planting | F20: =COUNTA('[2]Lucido HVCDP'!I116:I125) -> 0 | G20: ='[2]Lucido HVCDP'!I126 -> 0 | H20: =IF(G20=0,"No Production",'[2]Lucido HVCDP'!L126) -> No Production
B21: INDUSTRIAL CROPS
B22: Banana | C22: =COUNTA('[2]Lucido HVCDP'!F183:F192) -> 0 | D22: ='[2]Lucido HVCDP'!F193 -> 0 | E22: =IF(D22>0, "Vegetative", "No Planting") -> No Planting | F22: =COUNTA('[2]Lucido HVCDP'!I183:I192) -> 0 | G22: ='[2]Lucido HVCDP'!I193 -> 0 | H22: =IF(G22=0,"No Production",'[2]Lucido HVCDP'!L193) -> No Production
B23: Cacao | C23: =COUNTA('[2]Lucido HVCDP'!F194:F203) -> 0 | D23: ='[2]Lucido HVCDP'!F204 -> 0 | E23: =IF(D23>0, "Vegetative", "No Planting") -> No Planting | F23: =COUNTA('[2]Lucido HVCDP'!I194:I203) -> 0 | G23: ='[2]Lucido HVCDP'!I204 -> 0 | H23: =IF(G23=0,"No Production",'[2]Lucido HVCDP'!L204) -> No Production
B24: Coffee | C24: =COUNTA('[2]Lucido HVCDP'!F205) -> 0 | D24: ='[2]Lucido HVCDP'!F206 -> 0 | E24: =IF(D24>0, "Vegetative", "No Planting") -> No Planting | F24: =COUNTA('[2]Lucido HVCDP'!I205) -> 0 | G24: ='[2]Lucido HVCDP'!I206 -> 0 | H24: =IF(G24=0,"No Production",'[2]Lucido HVCDP'!L206) -> No Production
B25: FRUIT TREES
B26: Calamansi | C26: =COUNTA('[2]Lucido HVCDP'!F208:F217) -> 0 | D26: ='[2]Lucido HVCDP'!F218 -> 0 | E26: =IF(D26>0, "Vegetative", "No Planting") -> No Planting | F26: =COUNTA('[2]Lucido HVCDP'!I208:I217) -> 0 | G26: ='[2]Lucido HVCDP'!I218 -> 0 | H26: =IF(G26=0,"No Production",'[2]Lucido HVCDP'!L218) -> No Production
B27: Avocado | C27: =COUNTA('[2]Lucido HVCDP'!F219:F228) -> 0 | D27: ='[2]Lucido HVCDP'!F229 -> 0 | E27: =IF(D27>0, "Vegetative", "No Planting") -> No Planting | F27: =COUNTA('[2]Lucido HVCDP'!I219:I228) -> 0 | G27: ='[2]Lucido HVCDP'!I229 -> 0 | H27: =IF(G27=0,"No Production",'[2]Lucido HVCDP'!L229) -> No Production
B28: Papaya | C28: =COUNTA('[2]Lucido HVCDP'!F230:F239) -> 0 | D28: ='[2]Lucido HVCDP'!F240 -> 0 | E28: =IF(D28>0, "Vegetative", "No Planting") -> No Planting | F28: =COUNTA('[2]Lucido HVCDP'!I230:I239) -> 0 | G28: ='[2]Lucido HVCDP'!I240 -> 0 | H28: =IF(G28=0,"No Production",'[2]Lucido HVCDP'!L240) -> No Production
B29: Chico | C29: =COUNTA('[2]Lucido HVCDP'!F241:F250) -> 0 | D29: ='[2]Lucido HVCDP'!F251 -> 0 | E29: =IF(D29>0, "Vegetative", "No Planting") -> No Planting | F29: =COUNTA('[2]Lucido HVCDP'!I241:I250) -> 0 | G29: ='[2]Lucido HVCDP'!I251 -> 0 | H29: =IF(G29=0,"No Production",'[2]Lucido HVCDP'!L251) -> No Production
B30: Rambutan | C30: =COUNTA('[2]Lucido HVCDP'!F252:F261) -> 0 | D30: ='[2]Lucido HVCDP'!F262 -> 0 | E30: =IF(D30>0, "Vegetative", "No Planting") -> No Planting | F30: =COUNTA('[2]Lucido HVCDP'!I252:I261) -> 0 | G30: ='[2]Lucido HVCDP'!I262 -> 0 | H30: =IF(G30=0,"No Production",'[2]Lucido HVCDP'!L262) -> No Production
B31: Mango | C31: =COUNTA('[2]Lucido HVCDP'!F263:F272) -> 0 | D31: ='[2]Lucido HVCDP'!F273 -> 0 | E31: =IF(D31>0, "Vegetative", "No Planting") -> No Planting | F31: =COUNTA('[2]Lucido HVCDP'!I263:I272) -> 0 | G31: ='[2]Lucido HVCDP'!I273 -> 0 | H31: =IF(G31=0,"No Production",'[2]Lucido HVCDP'!L273) -> No Production
B32: Lanzones | C32: =COUNTA('[2]Lucido HVCDP'!F274:F283) -> 0 | D32: ='[2]Lucido HVCDP'!F284 -> 0 | E32: =IF(D32>0, "Vegetative", "No Planting") -> No Planting | F32: =COUNTA('[2]Lucido HVCDP'!I274:I283) -> 0 | G32: ='[2]Lucido HVCDP'!I284 -> 0 | H32: =IF(G32=0,"No Production",'[2]Lucido HVCDP'!L284) -> No Production
B33: LEAFY VEGETABLES
B34: Malunggay | C34: =COUNTA('[2]Lucido HVCDP'!F286:F295) -> 0 | D34: ='[2]Lucido HVCDP'!F296 -> 0 | E34: =IF(D34>0, "Vegetative", "No Planting") -> No Planting | F34: =COUNTA('[2]Lucido HVCDP'!I286:I295) -> 0 | G34: ='[2]Lucido HVCDP'!I296 -> 0 | H34: =IF(G34=0,"No Production",'[2]Lucido HVCDP'!L296) -> No Production
B35: Mustasa | C35: =COUNTA('[2]Lucido HVCDP'!F297:F306) -> 0 | D35: ='[2]Lucido HVCDP'!F307 -> 0 | E35: =IF(D35>0, "Vegetative", "No Planting") -> No Planting | F35: =COUNTA('[2]Lucido HVCDP'!I297:I306) -> 0 | G35: ='[2]Lucido HVCDP'!I307 -> 0 | H35: =IF(G35=0,"No Production",'[2]Lucido HVCDP'!L307) -> No Production
B36: Pechay | C36: =COUNTA('[2]Lucido HVCDP'!F308:F317) -> 0 | D36: ='[2]Lucido HVCDP'!F318 -> 0 | E36: =IF(D36>0, "Vegetative", "No Planting") -> No Planting | F36: =COUNTA('[2]Lucido HVCDP'!I308:I317) -> 0 | G36: ='[2]Lucido HVCDP'!I318 -> 0 | H36: =IF(G36=0,"No Production",'[2]Lucido HVCDP'!L318) -> No Production
B37: ROOTCROPS
B38: Radish | C38: =COUNTA('[2]Lucido HVCDP'!F320:F329) -> 0 | D38: ='[2]Lucido HVCDP'!F330 -> 0 | E38: =IF(D38>0, "Vegetative", "No Planting") -> No Planting | F38: =COUNTA('[2]Lucido HVCDP'!I320:I329) -> 0 | G38: ='[2]Lucido HVCDP'!I330 -> 0 | H38: =IF(G38=0,"No Production",'[2]Lucido HVCDP'!L330) -> No Production
B39: Ginger | C39: =COUNTA('[2]Lucido HVCDP'!F331:F340) -> 0 | D39: ='[2]Lucido HVCDP'!F341 -> 0 | E39: =IF(D39>0, "Vegetative", "No Planting") -> No Planting | F39: =COUNTA('[2]Lucido HVCDP'!I331:I340) -> 0 | G39: ='[2]Lucido HVCDP'!I341 -> 0 | H39: =IF(G39=0,"No Production",'[2]Lucido HVCDP'!L341) -> No Production
B40: Ubi | C40: =COUNTA('[2]Lucido HVCDP'!F342:F351) -> 0 | D40: ='[2]Lucido HVCDP'!F352 -> 0 | E40: =IF(D40>0, "Vegetative", "No Planting") -> No Planting | F40: =COUNTA('[2]Lucido HVCDP'!I342:I351) -> 0 | G40: ='[2]Lucido HVCDP'!I352 -> 0 | H40: =IF(G40=0,"No Production",'[2]Lucido HVCDP'!L352) -> No Production
B41: Peanut | C41: =COUNTA('[2]Lucido HVCDP'!F353:F362) -> 0 | D41: ='[2]Lucido HVCDP'!F363 -> 0 | E41: =IF(D41>0, "Vegetative", "No Planting") -> No Planting | F41: =COUNTA('[2]Lucido HVCDP'!I353:I362) -> 0 | G41: ='[2]Lucido HVCDP'!I363 -> 0 | H41: =IF(G41=0,"No Production",'[2]Lucido HVCDP'!L363) -> No Production
B42: Sweet Potato | C42: =COUNTA('[2]Lucido HVCDP'!F364:F373) -> 0 | D42: ='[2]Lucido HVCDP'!F374 -> 0 | E42: =IF(D42>0, "Vegetative", "No Planting") -> No Planting | F42: =COUNTA('[2]Lucido HVCDP'!I364:I373) -> 0 | G42: ='[2]Lucido HVCDP'!I374 -> 0 | H42: =IF(G42=0,"No Production",'[2]Lucido HVCDP'!L374) -> No Production
B43: BULB
B44: Garlic | C44: =COUNTA('[2]Lucido HVCDP'!F376:F385) -> 0 | D44: ='[2]Lucido HVCDP'!F386 -> 0 | E44: =IF(D44>0, "Vegetative", "No Planting") -> No Planting | F44: =COUNTA('[2]Lucido HVCDP'!I376:I385) -> 0 | G44: ='[2]Lucido HVCDP'!I386 -> 0 | H44: =IF(G44=0,"No Production",'[2]Lucido HVCDP'!L386) -> No Production
B45: Onion | C45: =COUNTA('[2]Lucido HVCDP'!F387:F396) -> 0 | D45: ='[2]Lucido HVCDP'!F397 -> 0 | E45: =IF(D45>0, "Vegetative", "No Planting") -> No Planting | F45: =COUNTA('[2]Lucido HVCDP'!I387:I396) -> 0 | G45: ='[2]Lucido HVCDP'!I397 -> 0 | H45: =IF(G45=0,"No Production",'[2]Lucido HVCDP'!L397) -> No Production
B47: Submitted by: | F47: Noted by:
B50: Cynthia N. Lucido | F50: Sherwin M. Rimas
B51: Senior Agriculturist | F51: City Agriculturist

Sheet Requizo Summary
A1: MONTHLY AGRICULTURAL/FISHERY SITUATION REPORT
A2: Barangays Covered: Altura Bata, Ambulong, Gonzales, Janopol Occ, Janopol Oriental, Pantay Matanda, San Jose, Santor, Talaga, Trapiche
A4: District | B4: Commodity | C4: No. of Barangays Covered | D4: This Mo. | E4: Stage of Growth | F4: No. of Barangays Covered | G4: Area Harvested | H4: Estimated Production
A5: III | B5: FRUIT VEGETABLES
B6: Eggplant | C6: =COUNTA('[3]Requizo HVCDP'!F6:F15) -> 0 | D6: ='[3]Requizo HVCDP'!F16 -> 0 | E6: =IF(D6>0, "Vegetative", "No Planting") -> No Planting | F6: =COUNTA('[3]Requizo HVCDP'!I6:I15) -> 0 | G6: ='[3]Requizo HVCDP'!I16 -> 0 | H6: =IF(G6=0,"No Production",'[3]Requizo HVCDP'!L16) -> No Production
B7: Sitao | C7: =COUNTA('[3]Requizo HVCDP'!F17:F26) -> 0 | D7: ='[3]Requizo HVCDP'!G27 -> 6.65 | E7: =IF(D7>0, "Vegetative", "No Planting") -> Vegetative | F7: =COUNTA('[3]Requizo HVCDP'!I17:I26) -> 0 | G7: ='[3]Requizo HVCDP'!I27 -> 0 | H7: =IF(G7=0,"No Production",'[3]Requizo HVCDP'!L27) -> No Production
B8: Squash | C8: =COUNTA('[3]Requizo HVCDP'!F28:F37) -> 0 | D8: ='[3]Requizo HVCDP'!F38 -> 0 | E8: =IF(D8>0, "Vegetative", "No Planting") -> No Planting | F8: =COUNTA('[3]Requizo HVCDP'!I28:I37) -> 0 | G8: ='[3]Requizo HVCDP'!I38 -> 0 | H8: =IF(G8=0,"No Production",'[3]Requizo HVCDP'!L38) -> No Production
B9: Okra | C9: =COUNTA('[3]Requizo HVCDP'!F39:F48) -> 0 | D9: ='[3]Requizo HVCDP'!F49 -> 0 | E9: =IF(D9>0, "Vegetative", "No Planting") -> No Planting | F9: =COUNTA('[3]Requizo HVCDP'!I39:I48) -> 0 | G9: ='[3]Requizo HVCDP'!I49 -> 0 | H9: =IF(G9=0,"No Production",'[3]Requizo HVCDP'!L49) -> No Production
B10: Patola | C10: =COUNTA('[3]Requizo HVCDP'!F50:F59) -> 0 | D10: ='[3]Requizo HVCDP'!F60 -> 0 | E10: =IF(D10>0, "Vegetative", "No Planting") -> No Planting | F10: =COUNTA('[3]Requizo HVCDP'!I50:I59) -> 0 | G10: ='[3]Requizo HVCDP'!I60 -> 0 | H10: =IF(G10=0,"No Production",'[3]Requizo HVCDP'!L60) -> No Production
B11: Sigarilyas | C11: =COUNTA('[3]Requizo HVCDP'!F61:F70) -> 0 | D11: ='[3]Requizo HVCDP'!F71 -> 0 | E11: =IF(D11>0, "Vegetative", "No Planting") -> No Planting | F11: =COUNTA('[3]Requizo HVCDP'!I61:I70) -> 0 | G11: ='[3]Requizo HVCDP'!I71 -> 0 | H11: =IF(G11=0,"No Production",'[3]Requizo HVCDP'!L71) -> No Production
B12: Upo | C12: =COUNTA('[3]Requizo HVCDP'!F72:F81) -> 1 | D12: ='[3]Requizo HVCDP'!F82 -> 0.4 | E12: =IF(D12>0, "Vegetative", "No Planting") -> Vegetative | F12: =COUNTA('[3]Requizo HVCDP'!I72:I81) -> 0 | G12: ='[3]Requizo HVCDP'!I82 -> 0 | H12: =IF(G12=0,"No Production",'[3]Requizo HVCDP'!L82) -> No Production
B13: Ampalaya | C13: =COUNTA('[3]Requizo HVCDP'!F83:F92) -> 0 | D13: ='[3]Requizo HVCDP'!F93 -> 0 | E13: =IF(D13>0, "Vegetative", "No Planting") -> No Planting | F13: =COUNTA('[3]Requizo HVCDP'!I83:I92) -> 0 | G13: ='[3]Requizo HVCDP'!I93 -> 0 | H13: =IF(G13=0,"No Production",'[3]Requizo HVCDP'!L93) -> No Production
B14: Pipino | C14: =COUNTA('[3]Requizo HVCDP'!F94:F103) -> 0 | D14: ='[3]Requizo HVCDP'!F104 -> 0 | E14: =IF(D14>0, "Vegetative", "No Planting") -> No Planting | F14: =COUNTA('[3]Requizo HVCDP'!I94:I103) -> 0 | G14: ='[3]Requizo HVCDP'!I104 -> 0 | H14: =IF(G14=0,"No Production",'[3]Requizo HVCDP'!L104) -> No Production
B15: Sili | C15: =COUNTA('[3]Requizo HVCDP'!F105:F114) -> 0 | D15: ='[3]Requizo HVCDP'!F115 -> 0 | E15: =IF(D15>0, "Vegetative", "No Planting") -> No Planting | F15: =COUNTA('[3]Requizo HVCDP'!I105:I114) -> 0 | G15: ='[3]Requizo HVCDP'!I115 -> 0 | H15: =IF(G15=0,"No Production",'[3]Requizo HVCDP'!L115) -> No Production
B16: Beans | C16: =COUNTA('[3]Requizo HVCDP'!F116:F125) -> 0 | D16: ='[3]Requizo HVCDP'!F126 -> 0 | E16: =IF(D16>0, "Vegetative", "No Planting") -> No Planting | F16: =COUNTA('[3]Requizo HVCDP'!I116:I125) -> 0 | G16: ='[3]Requizo HVCDP'!I126 -> 0 | H16: =IF(G16=0,"No Production",'[3]Requizo HVCDP'!L126) -> No Production
B17: Paayap | C17: =COUNTA('[3]Requizo HVCDP'!F127:F136) -> 1 | D17: ='[3]Requizo HVCDP'!F137 -> 0.3 | E17: =IF(D17>0, "Vegetative", "No Planting") -> Vegetative | F17: =COUNTA('[3]Requizo HVCDP'!I127:I136) -> 0 | G17: ='[3]Requizo HVCDP'!I137 -> 0 | H17: =IF(G17=0,"No Production",'[3]Requizo HVCDP'!L137) -> No Production
B18: Tomato | C18: =COUNTA('[3]Requizo HVCDP'!F138:F147) -> 0 | D18: ='[3]Requizo HVCDP'!F148 -> 0 | E18: =IF(D18>0, "Vegetative", "No Planting") -> No Planting | F18: =COUNTA('[3]Requizo HVCDP'!I138:I147) -> 0 | G18: ='[3]Requizo HVCDP'!I148 -> 0 | H18: =IF(G18=0,"No Production",'[3]Requizo HVCDP'!L148) -> No Production
B19: Patani | C19: =COUNTA('[3]Requizo HVCDP'!F149) -> 0 | D19: ='[3]Requizo HVCDP'!F159 -> 0 | E19: =IF(D19>0, "Vegetative", "No Planting") -> No Planting | F19: =COUNTA('[3]Requizo HVCDP'!I149) -> 0 | G19: ='[3]Requizo HVCDP'!I159 -> 0 | H19: =IF(G19=0,"No Production",'[3]Requizo HVCDP'!L159) -> No Production
B20: INDUSTRIAL CROPS
B21: Banana | C21: =COUNTA('[3]Requizo HVCDP'!F161:F170) -> 0 | D21: ='[3]Requizo HVCDP'!F171 -> 0 | E21: =IF(D21>0, "Vegetative", "No Planting") -> No Planting | F21: =COUNTA('[3]Requizo HVCDP'!I161:I170) -> 0 | G21: ='[3]Requizo HVCDP'!I171 -> 0 | H21: =IF(G21=0,"No Production",'[3]Requizo HVCDP'!L171) -> No Production
B22: Cacao | C22: =COUNTA('[3]Requizo HVCDP'!F172:F181) -> 0 | D22: ='[3]Requizo HVCDP'!F182 -> 0 | E22: =IF(D22>0, "Vegetative", "No Planting") -> No Planting | F22: =COUNTA('[3]Requizo HVCDP'!I172:I181) -> 0 | G22: ='[3]Requizo HVCDP'!I182 -> 0 | H22: =IF(G22=0,"No Production",'[3]Requizo HVCDP'!L182) -> No Production
B23: Coffee | C23: =COUNTA('[3]Requizo HVCDP'!F183:F186) -> 0 | D23: ='[3]Requizo HVCDP'!F187 -> 0 | E23: =IF(D23>0, "Vegetative", "No Planting") -> No Planting | F23: =COUNTA('[3]Requizo HVCDP'!I183:I186) -> 0 | G23: ='[3]Requizo HVCDP'!I187 -> 0 | H23: =IF(G23=0,"No Production",'[3]Requizo HVCDP'!L187) -> No Production
B24: FRUIT TREES
B25: Calamansi | C25: =COUNTA('[3]Requizo HVCDP'!F189:F198) -> 0 | D25: ='[3]Requizo HVCDP'!F199 -> 0 | E25: =IF(D25>0, "Vegetative", "No Planting") -> No Planting | F25: =COUNTA('[3]Requizo HVCDP'!I189:I198) -> 0 | G25: ='[3]Requizo HVCDP'!I199 -> 0 | H25: =IF(G25=0,"No Production",'[3]Requizo HVCDP'!L199) -> No Production
B26: Avocado | C26: =COUNTA('[3]Requizo HVCDP'!F200:F209) -> 0 | D26: ='[3]Requizo HVCDP'!F210 -> 0 | E26: =IF(D26>0, "Vegetative", "No Planting") -> No Planting | F26: =COUNTA('[3]Requizo HVCDP'!I200:I209) -> 0 | G26: ='[3]Requizo HVCDP'!I210 -> 0 | H26: =IF(G26=0,"No Production",'[3]Requizo HVCDP'!L210) -> No Production
B27: Papaya | C27: =COUNTA('[3]Requizo HVCDP'!F211:F220) -> 0 | D27: ='[3]Requizo HVCDP'!F221 -> 0 | E27: =IF(D27>0, "Vegetative", "No Planting") -> No Planting | F27: =COUNTA('[3]Requizo HVCDP'!I211:I220) -> 0 | G27: ='[3]Requizo HVCDP'!I221 -> 0 | H27: =IF(G27=0,"No Production",'[3]Requizo HVCDP'!L221) -> No Production
B28: Chico | C28: =COUNTA('[3]Requizo HVCDP'!F222:F231) -> 0 | D28: ='[3]Requizo HVCDP'!F232 -> 0 | E28: =IF(D28>0, "Vegetative", "No Planting") -> No Planting | F28: =COUNTA('[3]Requizo HVCDP'!I222:I231) -> 0 | G28: ='[3]Requizo HVCDP'!I232 -> 0 | H28: =IF(G28=0,"No Production",'[3]Requizo HVCDP'!L232) -> No Production
B29: Rambutan | C29: =COUNTA('[3]Requizo HVCDP'!F233:F242) -> 0 | D29: ='[3]Requizo HVCDP'!F243 -> 0 | E29: =IF(D29>0, "Vegetative", "No Planting") -> No Planting | F29: =COUNTA('[3]Requizo HVCDP'!I233:I242) -> 0 | G29: ='[3]Requizo HVCDP'!I243 -> 0 | H29: =IF(G29=0,"No Production",'[3]Requizo HVCDP'!L243) -> No Production
B30: Mango | C30: =COUNTA('[3]Requizo HVCDP'!F244:F253) -> 0 | D30: ='[3]Requizo HVCDP'!F254 -> 0 | E30: =IF(D30>0, "Vegetative", "No Planting") -> No Planting | F30: =COUNTA('[3]Requizo HVCDP'!I244:I253) -> 0 | G30: ='[3]Requizo HVCDP'!I254 -> 0 | H30: =IF(G30=0,"No Production",'[3]Requizo HVCDP'!L254) -> No Production
B31: Lanzones | C31: =COUNTA('[3]Requizo HVCDP'!F255:F264) -> 0 | D31: ='[3]Requizo HVCDP'!F265 -> 0 | E31: =IF(D31>0, "Vegetative", "No Planting") -> No Planting | F31: =COUNTA('[3]Requizo HVCDP'!I255:I264) -> 0 | G31: ='[3]Requizo HVCDP'!I265 -> 0 | H31: =IF(G31=0,"No Production",'[3]Requizo HVCDP'!L265) -> No Production
B32: LEAFY VEGETABLES
B33: Malunggay | C33: =COUNTA('[3]Requizo HVCDP'!F267:F276) -> 0 | D33: ='[3]Requizo HVCDP'!F277 -> 0 | E33: =IF(D33>0, "Vegetative", "No Planting") -> No Planting | F33: =COUNTA('[3]Requizo HVCDP'!I267:I276) -> 0 | G33: ='[3]Requizo HVCDP'!I277 -> 0 | H33: =IF(G33=0,"No Production",'[3]Requizo HVCDP'!L277) -> No Production
B34: Mustasa | C34: =COUNTA('[3]Requizo HVCDP'!F278:F287) -> 0 | D34: ='[3]Requizo HVCDP'!F288 -> 0 | E34: =IF(D34>0, "Vegetative", "No Planting") -> No Planting | F34: =COUNTA('[3]Requizo HVCDP'!I278:I287) -> 0 | G34: ='[3]Requizo HVCDP'!I288 -> 0 | H34: =IF(G34=0,"No Production",'[3]Requizo HVCDP'!L288) -> No Production
B35: Pechay | C35: =COUNTA('[3]Requizo HVCDP'!F289:F298) -> 0 | D35: ='[3]Requizo HVCDP'!F299 -> 0 | E35: =IF(D35>0, "Vegetative", "No Planting") -> No Planting | F35: =COUNTA('[3]Requizo HVCDP'!I289:I298) -> 1 | G35: ='[3]Requizo HVCDP'!I299 -> 1 | H35: =IF(G35=0,"No Production",'[3]Requizo HVCDP'!L299) -> 9
B36: ROOTCROPS
B37: Ginger | C37: =COUNTA('[3]Requizo HVCDP'!F300:F310) -> 0 | D37: ='[3]Requizo HVCDP'!F311 -> 0 | E37: =IF(D37>0, "Vegetative", "No Planting") -> No Planting | F37: =COUNTA('[3]Requizo HVCDP'!I301:I310) -> 0 | G37: ='[3]Requizo HVCDP'!I311 -> 0 | H37: =IF(G37=0,"No Production",'[3]Requizo HVCDP'!L311) -> No Production
B38: Ubi | C38: =COUNTA('[3]Requizo HVCDP'!F312:F321) -> 0 | D38: ='[3]Requizo HVCDP'!F322 -> 0 | E38: =IF(D38>0, "Vegetative", "No Planting") -> No Planting | F38: =COUNTA('[3]Requizo HVCDP'!I312:I321) -> 0 | G38: ='[3]Requizo HVCDP'!I322 -> 0 | H38: =IF(G38=0,"No Production",'[3]Requizo HVCDP'!L322) -> No Production
B39: Peanut | C39: =COUNTA('[3]Requizo HVCDP'!F323:F332) -> 0 | D39: ='[3]Requizo HVCDP'!F333 -> 0 | E39: =IF(D39>0, "Vegetative", "No Planting") -> No Planting | F39: =COUNTA('[3]Requizo HVCDP'!I323:I332) -> 0 | G39: ='[3]Requizo HVCDP'!I333 -> 0 | H39: =IF(G39=0,"No Production",'[3]Requizo HVCDP'!L333) -> No Production
B40: Sweet Potato | C40: =COUNTA('[3]Requizo HVCDP'!F334:F343) -> 0 | D40: ='[3]Requizo HVCDP'!F344 -> 0 | E40: =IF(D40>0, "Vegetative", "No Planting") -> No Planting | F40: =COUNTA('[3]Requizo HVCDP'!I334:I343) -> 0 | G40: ='[3]Requizo HVCDP'!I344 -> 0 | H40: =IF(G40=0,"No Production",'[3]Requizo HVCDP'!L344) -> No Production
B41: BULB
B42: Garlic | C42: =COUNTA('[3]Requizo HVCDP'!F346:F355) -> 0 | D42: ='[3]Requizo HVCDP'!F356 -> 0 | E42: =IF(D42>0, "Vegetative", "No Planting") -> No Planting | F42: =COUNTA('[3]Requizo HVCDP'!I346:I355) -> 0 | G42: ='[3]Requizo HVCDP'!I356 -> 0 | H42: =IF(G42=0,"No Production",'[3]Requizo HVCDP'!L356) -> No Production
B43: Onion | C43: =COUNTA('[3]Requizo HVCDP'!F357:F366) -> 0 | D43: ='[3]Requizo HVCDP'!F367 -> 0 | E43: =IF(D43>0, "Vegetative", "No Planting") -> No Planting | F43: =COUNTA('[3]Requizo HVCDP'!I357:I366) -> 0 | G43: ='[3]Requizo HVCDP'!I367 -> 0 | H43: =IF(G43=0,"No Production",'[3]Requizo HVCDP'!L367) -> No Production
B45: Submitted by: | F45: Noted by:
B48: Charo Marie R. Requizo | F48: Sherwin M. Rimas
B49: Agriculturist II | F49: City Agriculturist

Sheet Rimas Summary
A1: MONTHLY AGRICULTURAL/FISHERY SITUATION REPORT
A2: Barangays Covered: Bagbag, Bagumbayan, Balele, Laurel, Mabini, Maria Paz, Pagaspas, Tinurik, Ulango, Wawa
A4: District | B4: Commodity | C4: No. of Barangays Covered | D4: This Mo. | E4: Stage of Growth | F4: No. of Barangays Covered | G4: Area Harvested | H4: Estimated Production
A5: III | B5: FRUIT VEGETABLES
B6: Eggplant | C6: =COUNTA('Rimas HVCDP'!F6:F15) -> 0 | D6: ='Rimas HVCDP'!F16 -> 0 | E6: =IF(D6>0, "vegetative", "No Planting") -> No Planting | F6: =COUNTA('Rimas HVCDP'!I6:I15) -> 0 | G6: ='Rimas HVCDP'!I16 -> 0 | H6: =IF(G6=0,"No Production",'Rimas HVCDP'!L16) -> No Production
B7: Sitao | C7: =COUNTA('Rimas HVCDP'!F17:F26) -> 0 | D7: ='Rimas HVCDP'!F27 -> 0 | E7: =IF(D7>0, "vegetative", "No Planting") -> No Planting | F7: =COUNTA('Rimas HVCDP'!I17:I26) -> 0 | G7: ='Rimas HVCDP'!I27 -> 0 | H7: =IF(G7=0,"No Production",'Rimas HVCDP'!L27) -> No Production
B8: Squash | C8: =COUNTA('Rimas HVCDP'!F28:F37) -> 0 | D8: ='Rimas HVCDP'!F38 -> 0 | E8: =IF(D8>0, "vegetative", "No Planting") -> No Planting | F8: =COUNTA('Rimas HVCDP'!I28:I37) -> 0 | G8: ='Rimas HVCDP'!I38 -> 0 | H8: =IF(G8=0,"No Production",'Rimas HVCDP'!L38) -> No Production
B9: Okra | C9: =COUNTA('Rimas HVCDP'!F39:F48) -> 0 | D9: ='Rimas HVCDP'!F49 -> 0 | E9: =IF(D9>0, "vegetative", "No Planting") -> No Planting | F9: =COUNTA('Rimas HVCDP'!I39:I48) -> 0 | G9: ='Rimas HVCDP'!I49 -> 0 | H9: =IF(G9=0,"No Production",'Rimas HVCDP'!L49) -> No Production
B10: Patola | C10: =COUNTA('Rimas HVCDP'!F50:F59) -> 0 | D10: ='Rimas HVCDP'!F60 -> 0 | E10: =IF(D10>0, "vegetative", "No Planting") -> No Planting | F10: =COUNTA('Rimas HVCDP'!I50:I59) -> 0 | G10: ='Rimas HVCDP'!I60 -> 0 | H10: =IF(G10=0,"No Production",'Rimas HVCDP'!L60) -> No Production
B11: Sigarilyas | C11: =COUNTA('Rimas HVCDP'!F61:F70) -> 0 | D11: ='Rimas HVCDP'!F71 -> 0 | E11: =IF(D11>0, "vegetative", "No Planting") -> No Planting | F11: =COUNTA('Rimas HVCDP'!I61:I70) -> 0 | G11: ='Rimas HVCDP'!I71 -> 0 | H11: =IF(G11=0,"No Production",'Rimas HVCDP'!L71) -> No Production
B12: Upo | C12: =COUNTA('Rimas HVCDP'!F72:F81) -> 0 | D12: ='Rimas HVCDP'!F82 -> 0 | E12: =IF(D12>0, "vegetative", "No Planting") -> No Planting | F12: =COUNTA('Rimas HVCDP'!I72:I81) -> 0 | G12: ='Rimas HVCDP'!I82 -> 0 | H12: =IF(G12=0,"No Production",'Rimas HVCDP'!L82) -> No Production
B13: Ampalaya | C13: =COUNTA('Rimas HVCDP'!F83:F92) -> 0 | D13: ='Rimas HVCDP'!F93 -> 0 | E13: =IF(D13>0, "vegetative", "No Planting") -> No Planting | F13: =COUNTA('Rimas HVCDP'!I83:I92) -> 0 | G13: ='Rimas HVCDP'!I93 -> 0 | H13: =IF(G13=0,"No Production",'Rimas HVCDP'!L93) -> No Production
B14: Pipino | C14: =COUNTA('Rimas HVCDP'!F94:F103) -> 0 | D14: ='Rimas HVCDP'!F104 -> 0 | E14: =IF(D14>0, "vegetative", "No Planting") -> No Planting | F14: =COUNTA('Rimas HVCDP'!I94:I103) -> 0 | G14: ='Rimas HVCDP'!I104 -> 0 | H14: =IF(G14=0,"No Production",'Rimas HVCDP'!L104) -> No Production
B15: Sili | C15: =COUNTA('Rimas HVCDP'!F105:F114) -> 0 | D15: ='Rimas HVCDP'!F115 -> 0 | E15: =IF(D15>0, "vegetative", "No Planting") -> No Planting | F15: =COUNTA('Rimas HVCDP'!I105:I114) -> 0 | G15: ='Rimas HVCDP'!I115 -> 0 | H15: =IF(G15=0,"No Production",'Rimas HVCDP'!L115) -> No Production
B16: Beans | C16: =COUNTA('Rimas HVCDP'!F116:F125) -> 0 | D16: ='Rimas HVCDP'!F126 -> 0 | E16: =IF(D16>0, "vegetative", "No Planting") -> No Planting | F16: =COUNTA('Rimas HVCDP'!I116:I125) -> 0 | G16: ='Rimas HVCDP'!I126 -> 0 | H16: =IF(G16=0,"No Production",'Rimas HVCDP'!L126) -> No Production
B17: Paayap | C17: =COUNTA('Rimas HVCDP'!F127:F136) -> 0 | D17: ='Rimas HVCDP'!F137 -> 0 | E17: =IF(D17>0, "vegetative", "No Planting") -> No Planting | F17: =COUNTA('Rimas HVCDP'!I127:I136) -> 0 | G17: ='Rimas HVCDP'!I137 -> 0 | H17: =IF(G17=0,"No Production",'Rimas HVCDP'!L137) -> No Production
B18: Tomato | C18: =COUNTA('Rimas HVCDP'!F138:F147) -> 0 | D18: ='Rimas HVCDP'!F148 -> 0 | E18: =IF(D18>0, "vegetative", "No Planting") -> No Planting | F18: =COUNTA('Rimas HVCDP'!I138:I147) -> 0 | G18: ='Rimas HVCDP'!I148 -> 0 | H18: =IF(G18=0,"No Production",'Rimas HVCDP'!L148) -> No Production
B19: Patani | C19: =COUNTA('Rimas HVCDP'!F149) -> 0 | D19: ='Rimas HVCDP'!F150 -> 0 | E19: =IF(D19>0, "vegetative", "No Planting") -> No Planting | F19: =COUNTA('Rimas HVCDP'!I149) -> 0 | G19: ='Rimas HVCDP'!I150 -> 0 | H19: =IF(G19=0,"No Production",'Rimas HVCDP'!L150) -> No Production
B20: INDUSTRIAL CROPS
B21: Banana | C21: =COUNTA('Rimas HVCDP'!F152:F162) -> 0 | D21: ='Rimas HVCDP'!F163 -> 0 | E21: =IF(D21>0, "vegetative", "No Planting") -> No Planting | F21: =COUNTA('Rimas HVCDP'!I153:I162) -> 0 | G21: ='Rimas HVCDP'!I163 -> 0 | H21: =IF(G21=0,"No Production",'Rimas HVCDP'!L163) -> No Production
B22: Cacao | C22: =COUNTA('Rimas HVCDP'!F164:F173) -> 0 | D22: ='Rimas HVCDP'!F174 -> 0 | E22: =IF(D22>0, "vegetative", "No Planting") -> No Planting | F22: =COUNTA('Rimas HVCDP'!I164:I173) -> 0 | G22: ='Rimas HVCDP'!I174 -> 0 | H22: =IF(G22=0,"No Production",'Rimas HVCDP'!L174) -> No Production
B23: Coffee | C23: =COUNTA('Rimas HVCDP'!F175:F177) -> 0 | D23: ='Rimas HVCDP'!F178 -> 0 | E23: =IF(D23>0, "vegetative", "No Planting") -> No Planting | F23: =COUNTA('Rimas HVCDP'!I175:I177) -> 0 | G23: ='Rimas HVCDP'!J178 -> 0 | H23: =IF(G23=0,"No Production",'Rimas HVCDP'!L178) -> No Production
B24: FRUIT TREES
B25: Calamansi | C25: =COUNTA('Rimas HVCDP'!F180:F189) -> 0 | D25: ='Rimas HVCDP'!F190 -> 0 | E25: =IF(D25>0, "vegetative", "No Planting") -> No Planting | F25: =COUNTA('Rimas HVCDP'!I180:I189) -> 0 | G25: ='Rimas HVCDP'!I190 -> 0 | H25: =IF(G25=0,"No Production",'Rimas HVCDP'!L190) -> No Production
B26: Avocado | C26: =COUNTA('Rimas HVCDP'!F191:F200) -> 0 | D26: ='Rimas HVCDP'!F201 -> 0 | E26: =IF(D26>0, "vegetative", "No Planting") -> No Planting | F26: =COUNTA('Rimas HVCDP'!I191:I200) -> 0 | G26: ='Rimas HVCDP'!I201 -> 0 | H26: =IF(G26=0,"No Production",'Rimas HVCDP'!L201) -> No Production
B27: Papaya | C27: =COUNTA('Rimas HVCDP'!F202:F211) -> 0 | D27: ='Rimas HVCDP'!F212 -> 0 | E27: =IF(D27>0, "vegetative", "No Planting") -> No Planting | F27: =COUNTA('Rimas HVCDP'!I202:I211) -> 0 | G27: ='Rimas HVCDP'!I212 -> 0 | H27: =IF(G27=0,"No Production",'Rimas HVCDP'!L212) -> No Production
B28: Chico | C28: =COUNTA('Rimas HVCDP'!F213:F222) -> 0 | D28: ='Rimas HVCDP'!F223 -> 0 | E28: =IF(D28>0, "vegetative", "No Planting") -> No Planting | F28: =COUNTA('Rimas HVCDP'!I213:I222) -> 0 | G28: ='Rimas HVCDP'!I223 -> 0 | H28: =IF(G28=0,"No Production",'Rimas HVCDP'!L223) -> No Production
B29: Rambutan | C29: =COUNTA('Rimas HVCDP'!F224:F233) -> 0 | D29: ='Rimas HVCDP'!F234 -> 0 | E29: =IF(D29>0, "vegetative", "No Planting") -> No Planting | F29: =COUNTA('Rimas HVCDP'!I224:I233) -> 0 | G29: ='Rimas HVCDP'!I234 -> 0 | H29: =IF(G29=0,"No Production",'Rimas HVCDP'!L234) -> No Production
B30: Mango | C30: =COUNTA('Rimas HVCDP'!F235:F244) -> 0 | D30: ='Rimas HVCDP'!F245 -> 0 | E30: =IF(D30>0, "vegetative", "No Planting") -> No Planting | F30: =COUNTA('Rimas HVCDP'!I235:I244) -> 0 | G30: ='Rimas HVCDP'!I245 -> 0 | H30: =IF(G30=0,"No Production",'Rimas HVCDP'!L245) -> No Production
B31: Lanzones | C31: =COUNTA('Rimas HVCDP'!F246:F255) -> 0 | D31: ='Rimas HVCDP'!F256 -> 0 | E31: =IF(D31>0, "vegetative", "No Planting") -> No Planting | F31: =COUNTA('Rimas HVCDP'!I246:I255) -> 0 | G31: ='Rimas HVCDP'!I256 -> 0 | H31: =IF(G31=0,"No Production",'Rimas HVCDP'!L256) -> No Production
B32: LEAFY VEGETABLES | E32: =IF(D32>0, "vegetative", "No Planting") -> No Planting
B33: Malunggay | C33: =COUNTA('Rimas HVCDP'!F258:F267) -> 0 | D33: ='Rimas HVCDP'!F268 -> 0 | E33: =IF(D33>0, "vegetative", "No Planting") -> No Planting | F33: =COUNTA('Rimas HVCDP'!I258:I267) -> 0 | G33: ='Rimas HVCDP'!I268 -> 0 | H33: =IF(G33=0,"No Production",'Rimas HVCDP'!L268) -> No Production
B34: Mustasa | C34: =COUNTA('Rimas HVCDP'!F269:F278) -> 0 | D34: ='Rimas HVCDP'!F279 -> 0 | E34: =IF(D34>0, "vegetative", "No Planting") -> No Planting | F34: =COUNTA('Rimas HVCDP'!I269:I278) -> 0 | G34: ='Rimas HVCDP'!I279 -> 0 | H34: =IF(G34=0,"No Production",'Rimas HVCDP'!L279) -> No Production
B35: Pechay | C35: =COUNTA('Rimas HVCDP'!F280:F289) -> 0 | D35: ='Rimas HVCDP'!F290 -> 0 | E35: =IF(D35>0, "vegetative", "No Planting") -> No Planting | F35: =COUNTA('Rimas HVCDP'!I280:I289) -> 0 | G35: ='Rimas HVCDP'!I290 -> 0 | H35: =IF(G35=0,"No Production",'Rimas HVCDP'!L290) -> No Production
B36: ROOTCROPS
B37: Ginger | C37: =COUNTA('Rimas HVCDP'!F292:F301) -> 0 | D37: ='Rimas HVCDP'!F302 -> 0 | E37: =IF(D37>0, "vegetative", "No Planting") -> No Planting | F37: =COUNTA('Rimas HVCDP'!I292:I301) -> 0 | G37: ='Rimas HVCDP'!I302 -> 0 | H37: =IF(G37=0,"No Production",'Rimas HVCDP'!L302) -> No Production
B38: Ubi | C38: =COUNTA('Rimas HVCDP'!F303:F312) -> 0 | D38: ='Rimas HVCDP'!F313 -> 0 | E38: =IF(D38>0, "vegetative", "No Planting") -> No Planting | F38: =COUNTA('Rimas HVCDP'!I303:I312) -> 0 | G38: ='Rimas HVCDP'!I313 -> 0 | H38: =IF(G38=0,"No Production",'Rimas HVCDP'!L313) -> No Production
B39: Peanut | C39: =COUNTA('Rimas HVCDP'!F314:F323) -> 0 | D39: ='Rimas HVCDP'!F324 -> 0 | E39: =IF(D39>0, "vegetative", "No Planting") -> No Planting | F39: =COUNTA('Rimas HVCDP'!I314:I323) -> 0 | G39: ='Rimas HVCDP'!I324 -> 0 | H39: =IF(G39=0,"No Production",'Rimas HVCDP'!L324) -> No Production
B40: Sweet Potato | C40: =COUNTA('Rimas HVCDP'!F325:F334) -> 0 | D40: ='Rimas HVCDP'!F335 -> 0 | E40: =IF(D40>0, "vegetative", "No Planting") -> No Planting | F40: =COUNTA('Rimas HVCDP'!I325:I334) -> 0 | G40: ='Rimas HVCDP'!I335 -> 0 | H40: =IF(G40=0,"No Production",'Rimas HVCDP'!L335) -> No Production
B41: BULB
B42: Garlic | C42: =COUNTA('Rimas HVCDP'!F337:F346) -> 0 | D42: ='Rimas HVCDP'!F347 -> 0 | E42: =IF(D42>0, "vegetative", "No Planting") -> No Planting | F42: =COUNTA('Rimas HVCDP'!I337:I346) -> 0 | G42: ='Rimas HVCDP'!I347 -> 0 | H42: =IF(G42=0,"No Production",'Rimas HVCDP'!L347) -> No Production
B43: Onion | C43: =COUNTA('Rimas HVCDP'!F348:F357) -> 0 | D43: ='Rimas HVCDP'!F358 -> 0 | E43: =IF(D43>0, "vegetative", "No Planting") -> No Planting | F43: =COUNTA('Rimas HVCDP'!I348:I357) -> 0 | G43: ='Rimas HVCDP'!I358 -> 0 | H43: =IF(G43=0,"No Production",'Rimas HVCDP'!L358) -> No Production
B45: Submitted by:
B48: Sherwin M. Rimas
B49: City Agriculturist

Sheet Consolidated Summary
A1: MONTHLY AGRICULTURAL/FISHERY SITUATION REPORT
A2: TANAUAN CITY
A3: District | B3: Commodity | C3: No. of Barangays Covered | D3: This Mo. | E3: Stage of Growth | F3: No. of Barangays Covered | G3: Area Harvested | H3: Estimated Production
A4: III | B4: FRUIT VEGETABLES
B5: Eggplant | C5: ='Piamonte Summary'!C6+'Lucido Summary'!C6+'Requizo Summary'!C6+'Rimas Summary'!C6 -> 0 | D5: ='Consolidation HVCDP'!F6 -> 2.1 | E5: =IF(D5>0, "Vegetative", "No Planting") -> Vegetative | F5: ='Piamonte Summary'!F6+'Lucido Summary'!F6+'Requizo Summary'!F6+'Rimas Summary'!F6 -> 2 | G5: ='Consolidation HVCDP'!I6 -> 0.65 | H5: =IF(G5=0,"No Production",'Consolidation HVCDP'!L6) -> 1.69
B6: Sitao | C6: ='Piamonte Summary'!C7+'Lucido Summary'!C7+'Requizo Summary'!C7+'Rimas Summary'!C7 -> 2 | D6: ='Consolidation HVCDP'!F7 -> 2.3 | E6: =IF(D6>0, "Vegetative", "No Planting") -> Vegetative | F6: ='Piamonte Summary'!F7+'Lucido Summary'!F7+'Requizo Summary'!F7+'Rimas Summary'!F7 -> 0 | G6: ='Consolidation HVCDP'!I7 -> 0 | H6: =IF(G6=0,"No Production",'Consolidation HVCDP'!L7) -> No Production
B7: Squash | C7: ='Piamonte Summary'!C8+'Lucido Summary'!C8+'Requizo Summary'!C8+'Rimas Summary'!C8 -> 0 | D7: ='Consolidation HVCDP'!F8 -> 1.2 | E7: =IF(D7>0, "Vegetative", "No Planting") -> Vegetative | F7: ='Piamonte Summary'!F8+'Lucido Summary'!F8+'Requizo Summary'!F8+'Rimas Summary'!F8 -> 0 | G7: ='Consolidation HVCDP'!I8 -> 0 | H7: =IF(G7=0,"No Production",'Consolidation HVCDP'!L8) -> No Production
B8: Okra | C8: ='Piamonte Summary'!C9+'Lucido Summary'!C9+'Requizo Summary'!C9+'Rimas Summary'!C9 -> 1 | D8: ='Consolidation HVCDP'!F9 -> 0 | E8: =IF(D8>0, "Vegetative", "No Planting") -> No Planting | F8: ='Piamonte Summary'!F9+'Lucido Summary'!F9+'Requizo Summary'!F9+'Rimas Summary'!F9 -> 0 | G8: ='Consolidation HVCDP'!I9 -> 0.5 | H8: =IF(G8=0,"No Production",'Consolidation HVCDP'!L9) -> 0.5
B9: Patola | C9: ='Piamonte Summary'!C10+'Lucido Summary'!C10+'Requizo Summary'!C10+'Rimas Summary'!C10 -> 1 | D9: ='Consolidation HVCDP'!F10 -> 0.5 | E9: =IF(D9>0, "Vegetative", "No Planting") -> Vegetative | F9: ='Piamonte Summary'!F10+'Lucido Summary'!F10+'Requizo Summary'!F10+'Rimas Summary'!F10 -> 0 | G9: ='Consolidation HVCDP'!I10 -> 0 | H9: =IF(G9=0,"No Production",'Consolidation HVCDP'!L10) -> No Production
B10: Sigarilyas | C10: ='Piamonte Summary'!C11+'Lucido Summary'!C11+'Requizo Summary'!C11+'Rimas Summary'!C11 -> 0 | D10: ='Consolidation HVCDP'!F11 -> 0 | E10: =IF(D10>0, "Vegetative", "No Planting") -> No Planting | F10: ='Piamonte Summary'!F11+'Lucido Summary'!F11+'Requizo Summary'!F11+'Rimas Summary'!F11 -> 0 | G10: ='Consolidation HVCDP'!I11 -> 0 | H10: =IF(G10=0,"No Production",'Consolidation HVCDP'!L11) -> No Production
B11: Upo | C11: ='Piamonte Summary'!C12+'Lucido Summary'!C12+'Requizo Summary'!C12+'Rimas Summary'!C12 -> 2 | D11: ='Consolidation HVCDP'!F12 -> 2.2 | E11: =IF(D11>0, "Vegetative", "No Planting") -> Vegetative | F11: ='Piamonte Summary'!F12+'Lucido Summary'!F12+'Requizo Summary'!F12+'Rimas Summary'!F12 -> 2 | G11: ='Consolidation HVCDP'!I12 -> 0.44 | H11: =IF(G11=0,"No Production",'Consolidation HVCDP'!L12) -> 2.2
B12: Ampalaya | C12: ='Piamonte Summary'!C13+'Lucido Summary'!C13+'Requizo Summary'!C13+'Rimas Summary'!C13 -> 2 | D12: ='Consolidation HVCDP'!F13 -> 2.7 | E12: =IF(D12>0, "Vegetative", "No Planting") -> Vegetative | F12: ='Piamonte Summary'!F13+'Lucido Summary'!F13+'Requizo Summary'!F13+'Rimas Summary'!F13 -> 0 | G12: ='Consolidation HVCDP'!I13 -> 0 | H12: =IF(G12=0,"No Production",'Consolidation HVCDP'!L13) -> No Production
B13: Pipino | C13: ='Piamonte Summary'!C14+'Lucido Summary'!C14+'Requizo Summary'!C14+'Rimas Summary'!C14 -> 0 | D13: ='Consolidation HVCDP'!F14 -> 0 | E13: =IF(D13>0, "Vegetative", "No Planting") -> No Planting | F13: ='Piamonte Summary'!F14+'Lucido Summary'!F14+'Requizo Summary'!F14+'Rimas Summary'!F14 -> 0 | G13: ='Consolidation HVCDP'!I14 -> 0 | H13: =IF(G13=0,"No Production",'Consolidation HVCDP'!L14) -> No Production
B14: Sili | C14: ='Piamonte Summary'!C15+'Lucido Summary'!C15+'Requizo Summary'!C15+'Rimas Summary'!C15 -> 0 | D14: ='Consolidation HVCDP'!F15 -> 0 | E14: =IF(D14>0, "Vegetative", "No Planting") -> No Planting | F14: ='Piamonte Summary'!F15+'Lucido Summary'!F15+'Requizo Summary'!F15+'Rimas Summary'!F15 -> 1 | G14: ='Consolidation HVCDP'!I15 -> 0.19 | H14: =IF(G14=0,"No Production",'Consolidation HVCDP'!L15) -> 0.95
B15: Beans | C15: ='Piamonte Summary'!C16+'Lucido Summary'!C16+'Requizo Summary'!C16+'Rimas Summary'!C16 -> 0 | D15: ='Consolidation HVCDP'!F16 -> 0.25 | E15: =IF(D15>0, "Vegetative", "No Planting") -> Vegetative | F15: ='Piamonte Summary'!F16+'Lucido Summary'!F16+'Requizo Summary'!F16+'Rimas Summary'!F16 -> 0 | G15: ='Consolidation HVCDP'!I16 -> 0 | H15: =IF(G15=0,"No Production",'Consolidation HVCDP'!L16) -> No Production
B16: Paayap | C16: ='Piamonte Summary'!C17+'Lucido Summary'!C17+'Requizo Summary'!C17+'Rimas Summary'!C17 -> 2 | D16: ='Consolidation HVCDP'!F17 -> 0.7 | E16: =IF(D16>0, "Vegetative", "No Planting") -> Vegetative | F16: ='Piamonte Summary'!F17+'Lucido Summary'!F17+'Requizo Summary'!F17+'Rimas Summary'!F17 -> 0 | G16: ='Consolidation HVCDP'!I17 -> 0 | H16: =IF(G16=0,"No Production",'Consolidation HVCDP'!L17) -> No Production
B17: Tomato | C17: ='Piamonte Summary'!C18+'Lucido Summary'!C18+'Requizo Summary'!C18+'Rimas Summary'!C18 -> 2 | D17: ='Consolidation HVCDP'!F18 -> 3.4 | E17: =IF(D17>0, "Vegetative", "No Planting") -> Vegetative | F17: ='Piamonte Summary'!F18+'Lucido Summary'!F18+'Requizo Summary'!F18+'Rimas Summary'!F18 -> 1 | G17: ='Consolidation HVCDP'!I18 -> 0.19 | H17: =IF(G17=0,"No Production",'Consolidation HVCDP'!L18) -> 0.95
B18: Patani | C18: ='Lucido Summary'!C19+'Requizo Summary'!C19+'Rimas Summary'!C19 -> 0 | D18: ='Consolidation HVCDP'!F19 -> 0 | E18: =IF(D18>0, "Vegetative", "No Planting") -> No Planting | F18: ='Lucido Summary'!F19+'Requizo Summary'!F19+'Rimas Summary'!F19 -> 0 | G18: ='Consolidation HVCDP'!I19 -> 0 | H18: =IF(G18=0,"No Production",'Consolidation HVCDP'!L19) -> No Production
B19: Mungbean | C19: ='Lucido Summary'!C20 -> 0 | D19: ='Consolidation HVCDP'!F20 -> 0 | E19: =IF(D19>0, "Vegetative", "No Planting") -> No Planting | F19: ='Lucido Summary'!F20 -> 0 | G19: ='Consolidation HVCDP'!I20 -> 0 | H19: =IF(G19=0,"No Production",'Consolidation HVCDP'!L20) -> No Production
B20: INDUSTRIAL CROPS
B21: Banana | C21: ='Piamonte Summary'!C20+'Lucido Summary'!C22+'Requizo Summary'!C21+'Rimas Summary'!C21 -> 0 | D21: ='Consolidation HVCDP'!F22 -> 0 | E21: =IF(D21>0, "Vegetative", "No Planting") -> No Planting | F21: ='Piamonte Summary'!F20+'Lucido Summary'!F22+'Requizo Summary'!F21+'Rimas Summary'!F21 -> 0 | G21: ='Consolidation HVCDP'!I22 -> 0 | H21: =IF(G21=0,"No Production",'Consolidation HVCDP'!L22) -> No Production
B22: Cacao | C22: ='Piamonte Summary'!C21+'Lucido Summary'!C23+'Requizo Summary'!C22+'Rimas Summary'!C22 -> 0 | D22: ='Consolidation HVCDP'!F23 -> 0 | E22: =IF(D22>0, "Vegetative", "No Planting") -> No Planting | F22: ='Piamonte Summary'!F21+'Lucido Summary'!F23+'Requizo Summary'!F22+'Rimas Summary'!F22 -> 0 | G22: ='Consolidation HVCDP'!I23 -> 0 | H22: =IF(G22=0,"No Production",'Consolidation HVCDP'!L23) -> No Production
B23: Coffee | C23: ='Piamonte Summary'!C22+'Lucido Summary'!C24+'Requizo Summary'!C23 -> 0 | D23: ='Consolidation HVCDP'!F24 -> 0 | E23: =IF(D23>0, "Vegetative", "No Planting") -> No Planting | F23: ='Piamonte Summary'!F22+'Lucido Summary'!F24+'Requizo Summary'!F23 -> 0 | G23: ='Consolidation HVCDP'!I24 -> 0 | H23: =IF(G23=0,"No Production",'Consolidation HVCDP'!L24) -> No Production
B24: FRUIT TREES | E24: =IF(D24>0, "Vegetative", "No Planting") -> No Planting | G24: ='Consolidation HVCDP'!I25 -> 0 | H24: =IF(G24=0,"No Production",'Consolidation HVCDP'!L25) -> No Production
B25: Calamansi | C25: ='Piamonte Summary'!C24+'Lucido Summary'!C26+'Requizo Summary'!C25+'Rimas Summary'!C25 -> 0 | D25: ='Consolidation HVCDP'!F26 -> 0 | E25: =IF(D25>0, "Vegetative", "No Planting") -> No Planting | F25: ='Piamonte Summary'!F24+'Lucido Summary'!F26+'Requizo Summary'!F25+'Rimas Summary'!F25 -> 0 | G25: ='Consolidation HVCDP'!I26 -> 0 | H25: =IF(G25=0,"No Production",'Consolidation HVCDP'!L26) -> No Production
B26: Avocado | C26: ='Piamonte Summary'!C25+'Lucido Summary'!C27+'Requizo Summary'!C26+'Requizo Summary'!C26+'Rimas Summary'!C26 -> 0 | D26: ='Consolidation HVCDP'!F27 -> 0 | E26: =IF(D26>0, "Vegetative", "No Planting") -> No Planting | F26: ='Piamonte Summary'!F25+'Lucido Summary'!F27+'Requizo Summary'!F26+'Requizo Summary'!F26+'Rimas Summary'!F26 -> 0 | G26: ='Consolidation HVCDP'!I27 -> 0 | H26: =IF(G26=0,"No Production",'Consolidation HVCDP'!L27) -> No Production
B27: Papaya | C27: ='Piamonte Summary'!C26+'Lucido Summary'!C28+'Requizo Summary'!C27+'Rimas Summary'!C27 -> 0 | D27: ='Consolidation HVCDP'!F28 -> 0 | E27: =IF(D27>0, "Vegetative", "No Planting") -> No Planting | F27: ='Piamonte Summary'!F26+'Lucido Summary'!F28+'Requizo Summary'!F27+'Rimas Summary'!F27 -> 0 | G27: ='Consolidation HVCDP'!I28 -> 0 | H27: =IF(G27=0,"No Production",'Consolidation HVCDP'!L28) -> No Production
B28: Chico | C28: ='Piamonte Summary'!C27+'Lucido Summary'!C29+'Requizo Summary'!C28+'Rimas Summary'!C28 -> 0 | D28: ='Consolidation HVCDP'!F29 -> 0 | E28: =IF(D28>0, "Vegetative", "No Planting") -> No Planting | F28: ='Piamonte Summary'!F27+'Lucido Summary'!F29+'Requizo Summary'!F28+'Rimas Summary'!F28 -> 0 | G28: ='Consolidation HVCDP'!I29 -> 0 | H28: =IF(G28=0,"No Production",'Consolidation HVCDP'!L29) -> No Production
B29: Rambutan | C29: ='Piamonte Summary'!C28+'Lucido Summary'!C30+'Requizo Summary'!C29+'Rimas Summary'!C29 -> 0 | D29: ='Consolidation HVCDP'!F30 -> 0 | E29: =IF(D29>0, "Vegetative", "No Planting") -> No Planting | F29: ='Piamonte Summary'!F28+'Lucido Summary'!F30+'Requizo Summary'!F29+'Rimas Summary'!F29 -> 0 | G29: ='Consolidation HVCDP'!I30 -> 0 | H29: =IF(G29=0,"No Production",'Consolidation HVCDP'!L30) -> No Production
B30: Mango | C30: ='Piamonte Summary'!C29+'Lucido Summary'!C31+'Requizo Summary'!C30+'Requizo Summary'!C30+'Rimas Summary'!C30 -> 0 | D30: ='Consolidation HVCDP'!F31 -> 0 | E30: =IF(D30>0, "Vegetative", "No Planting") -> No Planting | F30: ='Piamonte Summary'!F29+'Lucido Summary'!F31+'Requizo Summary'!F30+'Requizo Summary'!F30+'Rimas Summary'!F30 -> 0 | G30: ='Consolidation HVCDP'!I31 -> 0 | H30: =IF(G30=0,"No Production",'Consolidation HVCDP'!L31) -> No Production
B31: Lanzones | C31: ='Piamonte Summary'!C30+'Lucido Summary'!C32+'Requizo Summary'!C31+'Rimas Summary'!C31 -> 0 | D31: ='Consolidation HVCDP'!F32 -> 0 | E31: =IF(D31>0, "Vegetative", "No Planting") -> No Planting | F31: ='Piamonte Summary'!F30+'Lucido Summary'!F32+'Requizo Summary'!F31+'Rimas Summary'!F31 -> 0 | G31: ='Consolidation HVCDP'!I32 -> 0 | H31: =IF(G31=0,"No Production",'Consolidation HVCDP'!L32) -> No Production
B32: LEAFY VEGETABLES
B33: Malunggay | C33: ='Piamonte Summary'!C32+'Lucido Summary'!C34+'Requizo Summary'!C33+'Rimas Summary'!C37 -> 0 | D33: ='Consolidation HVCDP'!F34 -> 0 | E33: =IF(D33>0, "Vegetative", "No Planting") -> No Planting | F33: ='Piamonte Summary'!F32+'Lucido Summary'!F34+'Requizo Summary'!F33+'Rimas Summary'!F37 -> 0 | G33: ='Consolidation HVCDP'!I34 -> 0 | H33: =IF(G33=0,"No Production",'Consolidation HVCDP'!L34) -> No Production
B34: Mustasa | C34: ='Piamonte Summary'!C33+'Lucido Summary'!C35+'Requizo Summary'!C34+'Rimas Summary'!C34 -> 0 | D34: ='Consolidation HVCDP'!F35 -> 0 | E34: =IF(D34>0, "Vegetative", "No Planting") -> No Planting | F34: ='Piamonte Summary'!F33+'Lucido Summary'!F35+'Requizo Summary'!F34+'Rimas Summary'!F34 -> 0 | G34: ='Consolidation HVCDP'!I35 -> 0 | H34: =IF(G34=0,"No Production",'Consolidation HVCDP'!L35) -> No Production
B35: Pechay | C35: ='Piamonte Summary'!C34+'Lucido Summary'!C36+'Requizo Summary'!C35+'Rimas Summary'!C35 -> 1 | D35: ='Consolidation HVCDP'!F36 -> 0 | E35: =IF(D35>0, "Vegetative", "No Planting") -> No Planting | F35: ='Piamonte Summary'!F34+'Lucido Summary'!F36+'Requizo Summary'!F35+'Rimas Summary'!F35 -> 2 | G35: ='Consolidation HVCDP'!I36 -> 0 | H35: =IF(G35=0,"No Production",'Consolidation HVCDP'!L36) -> No Production
B36: ROOTCROPS
B37: Radish | C37: ='Lucido Summary'!C38 -> 0 | D37: ='Consolidation HVCDP'!E38 -> 0 | E37: =IF(D37>0, "Vegetative", "No Planting") -> No Planting | F37: ='Lucido Summary'!F38 -> 0 | G37: ='Consolidation HVCDP'!I38 -> 0 | H37: =IF(G37=0,"No Production",'Consolidation HVCDP'!L38) -> No Production
B38: Ginger | C38: ='Piamonte Summary'!C36+'Lucido Summary'!C39+'Requizo Summary'!C37+'Rimas Summary'!C37 -> 0 | D38: ='Consolidation HVCDP'!E39 -> 0.5 | E38: =IF(D38>0, "Vegetative", "No Planting") -> Vegetative | F38: ='Piamonte Summary'!F36+'Lucido Summary'!F39+'Requizo Summary'!F37+'Rimas Summary'!F37 -> 0 | G38: ='Consolidation HVCDP'!I39 -> 0 | H38: =IF(G38=0,"No Production",'Consolidation HVCDP'!L39) -> No Production
B39: Ubi | C39: ='Piamonte Summary'!C37+'Lucido Summary'!C40+'Requizo Summary'!C38+'Rimas Summary'!C38 -> 0 | D39: ='Consolidation HVCDP'!E40 -> 0.05 | E39: =IF(D39>0, "Vegetative", "No Planting") -> Vegetative | F39: ='Piamonte Summary'!F37+'Lucido Summary'!F40+'Requizo Summary'!F38+'Rimas Summary'!F38 -> 0 | G39: ='Consolidation HVCDP'!I40 -> 0 | H39: =IF(G39=0,"No Production",'Consolidation HVCDP'!L40) -> No Production
B40: Peanut | C40: ='Piamonte Summary'!C38+'Lucido Summary'!C41+'Requizo Summary'!C39+'Rimas Summary'!C39 -> 0 | D40: ='Consolidation HVCDP'!E41 -> 0.8 | E40: =IF(D40>0, "Vegetative", "No Planting") -> Vegetative | F40: ='Piamonte Summary'!F38+'Lucido Summary'!F41+'Requizo Summary'!F39+'Rimas Summary'!F39 -> 0 | G40: ='Consolidation HVCDP'!I41 -> 0 | H40: =IF(G40=0,"No Production",'Consolidation HVCDP'!L41) -> No Production
B41: Sweet Potato | C41: ='Piamonte Summary'!C39+'Lucido Summary'!C42+'Requizo Summary'!C40+'Rimas Summary'!C40 -> 0 | D41: ='Consolidation HVCDP'!E42 -> 0 | E41: =IF(D41>0, "Vegetative", "No Planting") -> No Planting | F41: ='Piamonte Summary'!F39+'Lucido Summary'!F42+'Requizo Summary'!F40+'Rimas Summary'!F40 -> 0 | G41: ='Consolidation HVCDP'!I42 -> 0 | H41: =IF(G41=0,"No Production",'Consolidation HVCDP'!L42) -> No Production
B42: BULB
B43: Garlic | C43: ='Piamonte Summary'!C41+'Lucido Summary'!C44+'Requizo Summary'!C42+'Rimas Summary'!C42 -> 0 | D43: ='Consolidation HVCDP'!F44 -> 0 | E43: =IF(D43>0, "Vegetative", "No Planting") -> No Planting | F43: ='Piamonte Summary'!F41+'Lucido Summary'!F44+'Requizo Summary'!F42+'Rimas Summary'!F42 -> 0 | G43: ='Consolidation HVCDP'!I44 -> 0 | H43: =IF(G43=0,"No Production",'Consolidation HVCDP'!L44) -> No Production
B44: Onion | C44: ='Piamonte Summary'!C42+'Lucido Summary'!C45+'Requizo Summary'!C43+'Rimas Summary'!C43 -> 0 | D44: ='Consolidation HVCDP'!F45 -> 0 | E44: =IF(D44>0, "Vegetative", "No Planting") -> No Planting | F44: ='Piamonte Summary'!F42+'Lucido Summary'!F45+'Requizo Summary'!F43+'Rimas Summary'!F43 -> 0 | G44: ='Consolidation HVCDP'!I45 -> 0 | H44: =IF(G44=0,"No Production",'Consolidation HVCDP'!L45) -> No Production
B46: Submitted by:
B49: Sherwin M. Rimas
B50: City Agriculturist

Sheet Piamonte PM
A1: PRICES AND MARKET SITUATION
A2: Barangays Covered: Altura Matanda, Altura South, Banadero, Bilog-Bilog, Luyos, Malaking Pulo, Montana, Sala, Santor, Sulpoc
A4: District | B4: Commodity | C4: Unit of Measure | D4: Farm Gate Price | E4: Wholesale Price | F4: Retail price
A5: III | B5: FRUIT VEGETABLES
B6: Eggplant | C6: per 10 kilos | D6: 400 | E6: 600 | F6: 900
B7: Sitao | C7: per 10 kilos | D7: 700 | E7: 900 | F7: 1200
B8: Squash | C8: per kilo | D8: 50 | E8: 80 | F8: 120
B9: Okra | C9: per 10 kilos | D9: 300 | E9: 500 | F9: 800
B10: Patola (kinis) | C10: per plastic 10 tali | D10: 200 | E10: 350 | F10: 600
B11: Sigarilyas | C11: per 10 kilos | D11: 100 | E11: 200 | F11: 400
B12: Upo | C12: per 10 kilos | D12: 200 | E12: 350 | F12: 650
B13: Ampalaya | C13: per 10 kilos | D13: 700 | E13: 1000 | F13: 1400
B14: Pipino (green) | C14: per 10 kilos | D14: 300 | E14: 500 | F14: 700
B15: Sili (labuyo) | C15: per 10 kilos | D15: 5500 | E15: 6000 | F15: 6500
B16: Beans | C16: per 10 kilos | D16: 950 | E16: 1350 | F16: 1700
B17: Paayap | C17: per 10 kilos
B18: Tomato (big) | C18: per box | D18: 2800 | E18: 3500 | F18: 4300
B19: INDUSTRIAL CROPS
B20: Banana (Lakatan) | C20: per kilo | D20: 60 | E20: 80 | F20: 120
B21: FRUIT TREES
B22: Calamansi | C22: per kilo | D22: 250 | E22: 450 | F22: 700
B23: Avocado | C23: per 10 kilos
B24: Papaya | C24: per plastic 10 tali | D24: 100 | E24: 200 | F24: 400
B25: Chico | C25: per 10 kilos | D25: 200 | E25: 500 | F25: 900
B26: Rambutan | C26: per kilo
B27: Mango (hinog) | C27: per box | D27: 2300 | E27: 2800 | F27: 3500
B28: Lanzones | C28: per kilo
B29: LEAFY VEGETABLES
B30: Malunggay | C30: per bundle
B31: Mustasa | C31: per 10 kilos | D31: 100 | E31: 250 | F31: 450
B32: Pechay | C32: per 10 kilos | D32: 100 | E32: 250 | F32: 450
B33: ROOTCROPS
B34: Radish | C34: per 10 kilos | D34: 300 | E34: 500 | F34: 800
B35: Ginger | C35: per 10 kilos | D35: 900 | E35: 1200 | F35: 1500
B36: Ubi | C36: per kilo
B37: Peanut | C37: per kilo
B38: Sweet Potato | C38: per 10 kilos
B39: BULB
B40: Garlic | C40: per 10 kilos | D40: 450 | E40: 670 | F40: 850
B41: Onion (big) | C41: per 10 kilos | D41: 400 | E41: 630 | F41: 800
B42: FERTILIZERS
B43: Ammonium Sulfate (21-0-0) | C43: per sack | F43: 800
B44: Markang Bulaklak(21-0-0) | C44: per sack | F44: 850
B45: Amigo/Complete (14-14-14) | C45: per sack | F45: 1700
B46: Viking Blue (46-0-0) | C46: per sack | F46: 1700
B47: Viking Yellow | C47: per sack | F47: 1700
B48: Muriate of Potash | C48: per sack | F48: 2000
A49: Note: The prices of different commodities indicated above were based on the prices in Tanauan City Trading Post as of November 18, 2024.
B51: Submitted by: | D51: Noted by:
B54: Adrian V. Piamonte | D54: Sherwin M. Rimas
B55: Agricultural Technologist | D55: City Agriculturist

Sheet Lucido PM
A1: PRICES AND MARKET SITUATION
A2: Barangays Covered: Banjo East, Banjo West, Boot, Cale, Darasa, Hidalgo, Maugat, Natatas, Pantay Bata, Suplang
A4: District | B4: Commodity | C4: Unit of Measure | D4: Farm Gate Price | E4: Wholesale Price | F4: Retail price
A5: III | B5: FRUIT VEGETABLES
B6: Eggplant | C6: per 10 kilos | D6: 400 | E6: 600 | F6: 900
B7: Sitao | C7: per 10 kilos | D7: 700 | E7: 900 | F7: 1200
B8: Squash | C8: per kilo | D8: 50 | E8: 80 | F8: 120
B9: Okra | C9: per 10 kilos | D9: 300 | E9: 500 | F9: 800
B10: Patola (kinis) | C10: per plastic 10 tali | D10: 200 | E10: 350 | F10: 600
B11: Sigarilyas | C11: per 10 kilos | D11: 100 | E11: 200 | F11: 400
B12: Upo | C12: per 10 kilos | D12: 200 | E12: 350 | F12: 650
B13: Ampalaya | C13: per 10 kilos | D13: 700 | E13: 1000 | F13: 1400
B14: Pipino (green) | C14: per 10 kilos | D14: 300 | E14: 500 | F14: 700
B15: Sili (labuyo) | C15: per 10 kilos | D15: 5500 | E15: 6000 | F15: 6500
B16: Beans | C16: per 10 kilos | D16: 950 | E16: 1350 | F16: 1700
B17: Paayap | C17: per 10 kilos
B18: Tomato (big) | C18: per box | D18: 2800 | E18: 3500 | F18: 4300
B19: INDUSTRIAL CROPS
B20: Banana (Lakatan) | C20: per kilo | D20: 60 | E20: 80 | F20: 120
B21: FRUIT TREES
B22: Calamansi | C22: per kilo | D22: 250 | E22: 450 | F22: 700
B23: Avocado | C23: per 10 kilos
B24: Papaya | C24: per plastic 10 tali | D24: 100 | E24: 200 | F24: 400
B25: Chico | C25: per 10 kilos | D25: 200 | E25: 500 | F25: 900
B26: Rambutan | C26: per kilo
B27: Mango (hinog) | C27: per box | D27: 2300 | E27: 2800 | F27: 3500
B28: Lanzones | C28: per kilo
B29: LEAFY VEGETABLES
B30: Malunggay | C30: per bundle
B31: Mustasa | C31: per 10 kilos | D31: 100 | E31: 250 | F31: 450
B32: Pechay | C32: per 10 kilos | D32: 100 | E32: 250 | F32: 450
B33: ROOTCROPS
B34: Radish | C34: per 10 kilos | D34: 300 | E34: 500 | F34: 800
B35: Ginger | C35: per 10 kilos | D35: 900 | E35: 1200 | F35: 1500
B36: Ubi | C36: per kilo
B37: Peanut | C37: per kilo
B38: Sweet Potato | C38: per 10 kilos
B39: BULB
B40: Garlic | C40: per 10 kilos | D40: 450 | E40: 670 | F40: 850
B41: Onion (big) | C41: per 10 kilos | D41: 400 | E41: 630 | F41: 800
B42: FERTILIZERS
B43: Ammonium Sulfate (21-0-0) | C43: per sack | F43: 800
B44: Markang Bulaklak(21-0-0) | C44: per sack | F44: 850
B45: Amigo/Complete (14-14-14) | C45: per sack | F45: 1700
B46: Viking Blue (46-0-0) | C46: per sack | F46: 1700
B47: Viking Yellow | C47: per sack | F47: 1700
B48: Muriate of Potash | C48: per sack | F48: 2000
A49: Note: The prices of different commodities indicated above were based on the prices in Tanauan City Trading Post as of December 11, 2024.
B51: Submitted by: | D51: Noted by:
B54: Cynthia N. Lucido | D54: Sherwin M. Rimas
B55: Senior Agriculturist | D55: City Agriculturist

Sheet Requizo PM 
A1: PRICES AND MARKET SITUATION
A2: Barangays Covered: Altura Bata, Ambulong, Gonzales, Janopol Occ, Janopol Oriental, Pantay Matanda, San Jose, Santor, Talaga, Trapiche
A4: District | B4: Commodity | C4: Unit of Measure | D4: Farm Gate Price | E4: Wholesale Price | F4: Retail price
A5: III | B5: FRUIT VEGETABLES
B6: Eggplant | C6: per 10 kilos | D6: 400 | E6: 600 | F6: 800
B7: Sitao | C7: per 10 kilos | D7: 700 | E7: 900 | F7: 1100
B8: Squash | C8: per kilo | D8: 60 | E8: 80 | F8: 95
B9: Okra | C9: per 10 kilos | D9: 400 | E9: 500 | F9: 650
B10: Patola | C10: per 10 tali | D10: 200 | E10: 350 | F10: 450
B11: Sigarilyas | C11: per 10 kilos | D11: 100 | E11: 200 | F11: 350
B12: Upo | C12: per 10 kilos | D12: 200 | E12: 350 | F12: 450
B13: Ampalaya | C13: per 10 kilos | D13: 850 | E13: 1000 | F13: 1200
B14: Pipino | C14: per 10 kilos | D14: 500 | E14: 680 | F14: 850
B15: Sili | C15: per 10 kilos | D15: 4000 | E15: 6000 | F15: 7500
B16: Beans | C16: per 10 kilos | D16: 1000 | E16: 1350 | F16: 1500
B17: Paayap | C17: per 10 kilos | D17: 0 | E17: 0 | F17: 0
B18: Tomato | C18: per box | D18: 2500 | E18: 3500 | F18: 4500
B19: INDUSTRIAL CROPS
B20: Banana | C20: per kilo | D20: 70 | E20: 80 | F20: 95
B21: FRUIT TREES
B22: Calamansi | C22: per 10 kilos | D22: 300 | E22: 450 | F22: 550
B23: Avocado | C23: per 10 kilos | D23: 0 | E23: 0 | F23: 0
B24: Papaya | C24: per 10 kilos | D24: 100 | E24: 200 | F24: 350
B25: Chico | C25: per 10 kilos | D25: 400 | E25: 500 | F25: 700
B26: Rambutan | C26: per 10 kilos | D26: 0 | E26: 0 | F26: 0
B27: Mango | C27: per 10 kilos | D27: 0 | E27: 0 | F27: 0
B28: Lanzones | C28: per kilo | D28: 0 | E28: 0 | F28: 0
B29: LEAFY VEGETABLES
B30: Malunggay | C30: per bundle | D30: 0 | E30: 0 | F30: 0
B31: Mustasa | C31: per 10 kilos | D31: 150 | E31: 250 | F31: 350
B32: Pechay | C32: per 10 kilos | D32: 150 | E32: 250 | F32: 400
B33: ROOTCROPS
B34: Radish | C34: per 10 kilos | D34: 350 | E34: 500 | F34: 600
B35: Ginger | C35: per 10 kilos | D35: 1000 | E35: 1200 | F35: 1350
B36: Ubi | C36: per kilo | D36: 0 | E36: 0 | F36: 0
B37: Peanut | C37: per kilo | D37: 0 | E37: 0 | F37: 0
B38: Sweet Potato | C38: per 10 kilos | D38: 250 | E38: 350 | F38: 500
B39: BULB
B40: Garlic | C40: per 10 kilos | D40: 500 | E40: 670 | F40: 750
B41: Onion | C41: per 6 kilos | D41: 400 | E41: 600 | F41: 700
B42: FERTILIZERS
B43: Ammonium Sulfate (21-0-0) | C43: per sack | D43: 0 | E43: 0 | F43: 900
B44: Markang Bulaklak(21-0-0) | C44: per sack | D44: 0 | E44: 0 | F44: 1050
B45: Amigo/Complete (14-14-14) | C45: per sack | D45: 0 | E45: 0 | F45: 1200
B46: Viking Blue (46-0-0) | C46: per sack | D46: 0 | E46: 0 | F46: 1750
B47: Viking Yellow | C47: per sack | D47: 0 | E47: 0 | F47: 1600
A48: Note: The prices of different commodities indicated above were based on the prices in Tanauan City Trading Post. (December 11, 2024)
B50: Submitted by: | D50: Noted by:
B53: Charo Marie R. Requizo | D53: Sherwin M. Rimas
B54: Agriculturist II | D54: City Agriculturist

Sheet Rimas PM 
A1: PRICES AND MARKET SITUATION
A2: Barangays Covered: Bagbag, Bagumbayan, Balele, Laurel, Mabini, Maria Paz, Pagaspas, Tinurik, Ulango, Wawa
A4: District | B4: Commodity | C4: Unit of Measure | D4: Farm Gate Price | E4: Wholesale Price | F4: Retail price
A5: III | B5: FRUIT VEGETABLES
B6: Eggplant | C6: per 10 kilos
B7: Sitao | C7: per 10 kilos
B8: Squash | C8: per kilo
B9: Okra | C9: per 10 kilos
B10: Patola | C10: per 10 kilos
B11: Sigarilyas | C11: per 10 kilos
B12: Upo | C12: per 10 kilos
B13: Ampalaya | C13: per 10 kilos
B14: Pipino | C14: per 10 kilos
B15: Sili | C15: per 10 kilos
B16: Beans | C16: per 10 kilos
B17: Paayap | C17: per 10 kilos
B18: Tomato | C18: per 20 kilos
B19: INDUSTRIAL CROPS
B20: Banana | C20: per kilo
B21: FRUIT TREES
B22: Calamansi | C22: per 10 kilos
B23: Avocado | C23: per 10 kilos
B24: Papaya | C24: per 10 kilos
B25: Chico | C25: per kilo
B26: Rambutan | C26: per kilo
B27: Mango | C27: per kaing
B28: Lanzones | C28: per kilo
B29: LEAFY VEGETABLES
B30: Malunggay | C30: per bundle
B31: Mustasa | C31: per 12 kilos
B32: Pechay | C32: per 10 kilos
B33: ROOTCROPS
B34: Radish | C34: per 7 kilos
B35: Ginger | C35: per 10 kilos
B36: Ubi | C36: per kilo
B37: Peanut | C37: per kilo
B38: Sweet Potato | C38: per 10 kilos
B39: BULB
B40: Garlic | C40: per 7 kilos
B41: Onion | C41: per 10 kilos
B42: FERTILIZERS
B43: Ammonium Sulfate (21-0-0) | C43: per sack
B44: Markang Bulaklak(21-0-0) | C44: per sack
B45: Amigo/Complete (14-14-14) | C45: per sack
B46: Viking Blue (46-0-0) | C46: per sack
B47: Viking Yellow | C47: per sack
A48: Note: The prices of different commodities indicated above were based on the prices in Tanauan City Trading Post.
B50: Submitted by:
B53: Sherwin M. Rimas
B54: City Agriculturist

Sheet Consolidateds PM 
A2: TANAUAN CITY
A4: District | B4: Commodity | C4: Unit of Measure | D4: Farm Gate Price | E4: Wholesale Price | F4: Retail price
A5: III | B5: FRUIT VEGETABLES
B6: Eggplant | C6: per 10 kilos | D6: =AVERAGE('Piamonte PM'!D6,'Lucido PM'!D6,'Requizo PM '!D6,'Rimas PM '!D6) -> 400 | E6: =AVERAGE('Piamonte PM'!E6,'Lucido PM'!E6,'Requizo PM '!E6,'Rimas PM '!E6) -> 600 | F6: =AVERAGE('Piamonte PM'!F6,'Lucido PM'!F6,'Requizo PM '!F6,'Rimas PM '!F6) -> 866.66667
B7: Sitao | C7: per 10 kilos | D7: =AVERAGE('Piamonte PM'!D7,'Lucido PM'!D7,'Requizo PM '!D7,'Rimas PM '!D7) -> 700 | E7: =AVERAGE('Piamonte PM'!E7,'Lucido PM'!E7,'Requizo PM '!E7,'Rimas PM '!E7) -> 900 | F7: =AVERAGE('Piamonte PM'!F7,'Lucido PM'!F7,'Requizo PM '!F7,'Rimas PM '!F7) -> 1166.6667
B8: Squash | C8: per kilo | D8: =AVERAGE('Piamonte PM'!D8,'Lucido PM'!D8,'Requizo PM '!D8,'Rimas PM '!D8) -> 53.333333 | E8: =AVERAGE('Piamonte PM'!E8,'Lucido PM'!E8,'Requizo PM '!E8,'Rimas PM '!E8) -> 80 | F8: =AVERAGE('Piamonte PM'!F8,'Lucido PM'!F8,'Requizo PM '!F8,'Rimas PM '!F8) -> 111.66667
B9: Okra | C9: per 10 kilos | D9: =AVERAGE('Piamonte PM'!D9,'Lucido PM'!D9,'Requizo PM '!D9,'Rimas PM '!D9) -> 333.33333 | E9: =AVERAGE('Piamonte PM'!E9,'Lucido PM'!E9,'Requizo PM '!E9,'Rimas PM '!E9) -> 500 | F9: =AVERAGE('Piamonte PM'!F9,'Lucido PM'!F9,'Requizo PM '!F9,'Rimas PM '!F9) -> 750
B10: Patola | C10: per 10 kilos | D10: =AVERAGE('Piamonte PM'!D10,'Lucido PM'!D10,'Requizo PM '!D10,'Rimas PM '!D10) -> 200 | E10: =AVERAGE('Piamonte PM'!E10,'Lucido PM'!E10,'Requizo PM '!E10,'Rimas PM '!E10) -> 350 | F10: =AVERAGE('Piamonte PM'!F10,'Lucido PM'!F10,'Requizo PM '!F10,'Rimas PM '!F10) -> 550
B11: Sigarilyas | C11: per 10 kilos | D11: =AVERAGE('Piamonte PM'!D11,'Lucido PM'!D11,'Requizo PM '!D11,'Rimas PM '!D11) -> 100 | E11: =AVERAGE('Piamonte PM'!E11,'Lucido PM'!E11,'Requizo PM '!E11,'Rimas PM '!E11) -> 200 | F11: =AVERAGE('Piamonte PM'!F11,'Lucido PM'!F11,'Requizo PM '!F11,'Rimas PM '!F11) -> 383.33333
B12: Upo | C12: per 10 kilos | D12: =AVERAGE('Piamonte PM'!D12,'Lucido PM'!D12,'Requizo PM '!D12,'Rimas PM '!D12) -> 200 | E12: =AVERAGE('Piamonte PM'!E12,'Lucido PM'!E12,'Requizo PM '!E12,'Rimas PM '!E12) -> 350 | F12: =AVERAGE('Piamonte PM'!F12,'Lucido PM'!F12,'Requizo PM '!F12,'Rimas PM '!F12) -> 583.33333
B13: Ampalaya | C13: per 10 kilos | D13: =AVERAGE('Piamonte PM'!D13,'Lucido PM'!D13,'Requizo PM '!D13,'Rimas PM '!D13) -> 750 | E13: =AVERAGE('Piamonte PM'!E13,'Lucido PM'!E13,'Requizo PM '!E13,'Rimas PM '!E13) -> 1000 | F13: =AVERAGE('Piamonte PM'!F13,'Lucido PM'!F13,'Requizo PM '!F13,'Rimas PM '!F13) -> 1333.3333
B14: Pipino | C14: per 10 kilos | D14: =AVERAGE('Piamonte PM'!D14,'Lucido PM'!D14,'Requizo PM '!D14,'Rimas PM '!D14) -> 366.66667 | E14: =AVERAGE('Piamonte PM'!E14,'Lucido PM'!E14,'Requizo PM '!E14,'Rimas PM '!E14) -> 560 | F14: =AVERAGE('Piamonte PM'!F14,'Lucido PM'!F14,'Requizo PM '!F14,'Rimas PM '!F14) -> 750
B15: Sili | C15: per 10 kilos | D15: =AVERAGE('Piamonte PM'!D15,'Lucido PM'!D15,'Requizo PM '!D15,'Rimas PM '!D15) -> 5000 | E15: =AVERAGE('Piamonte PM'!E15,'Lucido PM'!E15,'Requizo PM '!E15,'Rimas PM '!E15) -> 6000 | F15: =AVERAGE('Piamonte PM'!F15,'Lucido PM'!F15,'Requizo PM '!F15,'Rimas PM '!F15) -> 6833.3333
B16: Beans | C16: per 10 kilos | D16: =AVERAGE('Piamonte PM'!D16,'Lucido PM'!D16,'Requizo PM '!D16,'Rimas PM '!D16) -> 966.66667 | E16: =AVERAGE('Piamonte PM'!E16,'Lucido PM'!E16,'Requizo PM '!E16,'Rimas PM '!E16) -> 1350 | F16: =AVERAGE('Piamonte PM'!F16,'Lucido PM'!F16,'Requizo PM '!F16,'Rimas PM '!F16) -> 1633.3333
B17: Paayap | C17: per 10 kilos | D17: =AVERAGE('Piamonte PM'!D17,'Lucido PM'!D17,'Requizo PM '!D17,'Rimas PM '!D17) -> 0 | E17: =AVERAGE('Piamonte PM'!E17,'Lucido PM'!E17,'Requizo PM '!E17,'Rimas PM '!E17) -> 0 | F17: =AVERAGE('Piamonte PM'!F17,'Lucido PM'!F17,'Requizo PM '!F17,'Rimas PM '!F17) -> 0
B18: Tomato | C18: per 20 kilos | D18: =AVERAGE('Piamonte PM'!D18,'Lucido PM'!D18,'Requizo PM '!D18,'Rimas PM '!D18) -> 2700 | E18: =AVERAGE('Piamonte PM'!E18,'Lucido PM'!E18,'Requizo PM '!E18,'Rimas PM '!E18) -> 3500 | F18: =AVERAGE('Piamonte PM'!F18,'Lucido PM'!F18,'Requizo PM '!F18,'Rimas PM '!F18) -> 4366.6667
B19: INDUSTRIAL CROPS
B20: Banana | C20: per kilo | D20: =AVERAGE('Piamonte PM'!D20,'Lucido PM'!D20,'Requizo PM '!D20,'Rimas PM '!D20) -> 63.333333 | E20: =AVERAGE('Piamonte PM'!E20,'Lucido PM'!E20,'Requizo PM '!E20,'Rimas PM '!E20) -> 80 | F20: =AVERAGE('Piamonte PM'!F20,'Lucido PM'!F20,'Requizo PM '!F20,'Rimas PM '!F20) -> 111.66667
B21: FRUIT TREES
B22: Calamansi | C22: per 10 kilos | D22: =AVERAGE('Piamonte PM'!D22,'Lucido PM'!D22,'Requizo PM '!D22,'Rimas PM '!D22) -> 266.66667 | E22: =AVERAGE('Piamonte PM'!E22,'Lucido PM'!E22,'Requizo PM '!E22,'Rimas PM '!E22) -> 450 | F22: =AVERAGE('Piamonte PM'!F22,'Lucido PM'!F22,'Requizo PM '!F22,'Rimas PM '!F22) -> 650
B23: Avocado | C23: per 10 kilos | D23: =AVERAGE('Piamonte PM'!D23,'Lucido PM'!D23,'Requizo PM '!D23,'Rimas PM '!D23) -> 0 | E23: =AVERAGE('Piamonte PM'!E23,'Lucido PM'!E23,'Requizo PM '!E23,'Rimas PM '!E23) -> 0 | F23: =AVERAGE('Piamonte PM'!F23,'Lucido PM'!F23,'Requizo PM '!F23,'Rimas PM '!F23) -> 0
B24: Papaya | C24: per 10 kilos | D24: =AVERAGE('Piamonte PM'!D24,'Lucido PM'!D24,'Requizo PM '!D24,'Rimas PM '!D24) -> 100 | E24: =AVERAGE('Piamonte PM'!E24,'Lucido PM'!E24,'Requizo PM '!E24,'Rimas PM '!E24) -> 200 | F24: =AVERAGE('Piamonte PM'!F24,'Lucido PM'!F24,'Requizo PM '!F24,'Rimas PM '!F24) -> 383.33333
B25: Chico | C25: per kilo | D25: =AVERAGE('Piamonte PM'!D25,'Lucido PM'!D25,'Requizo PM '!D25,'Rimas PM '!D25) -> 266.66667 | E25: =AVERAGE('Piamonte PM'!E25,'Lucido PM'!E25,'Requizo PM '!E25,'Rimas PM '!E25) -> 500 | F25: =AVERAGE('Piamonte PM'!F25,'Lucido PM'!F25,'Requizo PM '!F25,'Rimas PM '!F25) -> 833.33333
B26: Rambutan | C26: per kilo | D26: =AVERAGE('Piamonte PM'!D26,'Lucido PM'!D26,'Requizo PM '!D26,'Rimas PM '!D26) -> 0 | E26: =AVERAGE('Piamonte PM'!E26,'Lucido PM'!E26,'Requizo PM '!E26,'Rimas PM '!E26) -> 0 | F26: =AVERAGE('Piamonte PM'!F26,'Lucido PM'!F26,'Requizo PM '!F26,'Rimas PM '!F26) -> 0
B27: Mango | C27: per kaing | D27: =AVERAGE('Piamonte PM'!D27,'Lucido PM'!D27,'Requizo PM '!D27,'Rimas PM '!D27) -> 1533.3333 | E27: =AVERAGE('Piamonte PM'!E27,'Lucido PM'!E27,'Requizo PM '!E27,'Rimas PM '!E27) -> 1866.6667 | F27: =AVERAGE('Piamonte PM'!F27,'Lucido PM'!F27,'Requizo PM '!F27,'Rimas PM '!F27) -> 2333.3333
B28: Lanzones | C28: per kilo | D28: =AVERAGE('Piamonte PM'!D28,'Lucido PM'!D28,'Requizo PM '!D28,'Rimas PM '!D28) -> 0 | E28: =AVERAGE('Piamonte PM'!E28,'Lucido PM'!E28,'Requizo PM '!E28,'Rimas PM '!E28) -> 0 | F28: =AVERAGE('Piamonte PM'!F28,'Lucido PM'!F28,'Requizo PM '!F28,'Rimas PM '!F28) -> 0
B29: LEAFY VEGETABLES
B30: Malunggay | C30: per bundle | D30: =AVERAGE('Piamonte PM'!D30,'Lucido PM'!D30,'Requizo PM '!D30,'Rimas PM '!D30) -> 0 | E30: =AVERAGE('Piamonte PM'!E30,'Lucido PM'!E30,'Requizo PM '!E30,'Rimas PM '!E30) -> 0 | F30: =AVERAGE('Piamonte PM'!F30,'Lucido PM'!F30,'Requizo PM '!F30,'Rimas PM '!F30) -> 0
B31: Mustasa | C31: per 12 kilos | D31: =AVERAGE('Piamonte PM'!D31,'Lucido PM'!D31,'Requizo PM '!D31,'Rimas PM '!D31) -> 116.66667 | E31: =AVERAGE('Piamonte PM'!E31,'Lucido PM'!E31,'Requizo PM '!E31,'Rimas PM '!E31) -> 250 | F31: =AVERAGE('Piamonte PM'!F31,'Lucido PM'!F31,'Requizo PM '!F31,'Rimas PM '!F31) -> 416.66667
B32: Pechay | C32: per 10 kilos | D32: =AVERAGE('Piamonte PM'!D32,'Lucido PM'!D32,'Requizo PM '!D32,'Rimas PM '!D32) -> 116.66667 | E32: =AVERAGE('Piamonte PM'!E32,'Lucido PM'!E32,'Requizo PM '!E32,'Rimas PM '!E32) -> 250 | F32: =AVERAGE('Piamonte PM'!F32,'Lucido PM'!F32,'Requizo PM '!F32,'Rimas PM '!F32) -> 433.33333
B33: ROOTCROPS
B34: Radish | C34: per 7 kilos | D34: =AVERAGE('Piamonte PM'!D34,'Lucido PM'!D34,'Requizo PM '!D34,'Rimas PM '!D34) -> 316.66667 | E34: =AVERAGE('Piamonte PM'!E34,'Lucido PM'!E34,'Requizo PM '!E34,'Rimas PM '!E34) -> 500 | F34: =AVERAGE('Piamonte PM'!F34,'Lucido PM'!F34,'Requizo PM '!F34,'Rimas PM '!F34) -> 733.33333
B35: Ginger | C35: per 10 kilos | D35: =AVERAGE('Piamonte PM'!D35,'Lucido PM'!D35,'Requizo PM '!D35,'Rimas PM '!D35) -> 933.33333 | E35: =AVERAGE('Piamonte PM'!E35,'Lucido PM'!E35,'Requizo PM '!E35,'Rimas PM '!E35) -> 1200 | F35: =AVERAGE('Piamonte PM'!F35,'Lucido PM'!F35,'Requizo PM '!F35,'Rimas PM '!F35) -> 1450
B36: Ubi | C36: per kilo | D36: =AVERAGE('Piamonte PM'!D36,'Lucido PM'!D36,'Requizo PM '!D36,'Rimas PM '!D36) -> 0 | E36: =AVERAGE('Piamonte PM'!E36,'Lucido PM'!E36,'Requizo PM '!E36,'Rimas PM '!E36) -> 0 | F36: =AVERAGE('Piamonte PM'!F36,'Lucido PM'!F36,'Requizo PM '!F36,'Rimas PM '!F36) -> 0
B37: Peanut | C37: per kilo | D37: =AVERAGE('Piamonte PM'!D37,'Lucido PM'!D37,'Requizo PM '!D37,'Rimas PM '!D37) -> 0 | E37: =AVERAGE('Piamonte PM'!E37,'Lucido PM'!E37,'Requizo PM '!E37,'Rimas PM '!E37) -> 0 | F37: =AVERAGE('Piamonte PM'!F37,'Lucido PM'!F37,'Requizo PM '!F37,'Rimas PM '!F37) -> 0
B38: Sweet Potato | C38: per 10 kilos | D38: =AVERAGE('Piamonte PM'!D38,'Lucido PM'!D38,'Requizo PM '!D38,'Rimas PM '!D38) -> 250 | E38: =AVERAGE('Piamonte PM'!E38,'Lucido PM'!E38,'Requizo PM '!E38,'Rimas PM '!E38) -> 350 | F38: =AVERAGE('Piamonte PM'!F38,'Lucido PM'!F38,'Requizo PM '!F38,'Rimas PM '!F38) -> 500
B39: BULB
B40: Garlic | C40: per 7 kilos | D40: =AVERAGE('Piamonte PM'!D40,'Lucido PM'!D40,'Requizo PM '!D40,'Rimas PM '!D40) -> 466.66667 | E40: =AVERAGE('Piamonte PM'!E40,'Lucido PM'!E40,'Requizo PM '!E40,'Rimas PM '!E40) -> 670 | F40: =AVERAGE('Piamonte PM'!F40,'Lucido PM'!F40,'Requizo PM '!F40,'Rimas PM '!F40) -> 816.66667
B41: Onion | C41: per 10 kilos | D41: =AVERAGE('Piamonte PM'!D41,'Lucido PM'!D41,'Requizo PM '!D41,'Rimas PM '!D41) -> 400 | E41: =AVERAGE('Piamonte PM'!E41,'Lucido PM'!E41,'Requizo PM '!E41,'Rimas PM '!E41) -> 620 | F41: =AVERAGE('Piamonte PM'!F41,'Lucido PM'!F41,'Requizo PM '!F41,'Rimas PM '!F41) -> 766.66667
B42: FERTILIZERS
B43: Ammonium Sulfate (21-0-0) | C43: per sack | D43: =AVERAGE('Piamonte PM'!D43,'Lucido PM'!D43,'Requizo PM '!D43,'Rimas PM '!D43) -> 0 | E43: =AVERAGE('Piamonte PM'!E43,'Lucido PM'!E43,'Requizo PM '!E43,'Rimas PM '!E43) -> 0 | F43: =AVERAGE('Piamonte PM'!F43,'Lucido PM'!F43,'Requizo PM '!F43,'Rimas PM '!F43) -> 833.33333
B44: Markang Bulaklak(21-0-0) | C44: per sack | D44: =AVERAGE('Piamonte PM'!D44,'Lucido PM'!D44,'Requizo PM '!D44,'Rimas PM '!D44) -> 0 | E44: =AVERAGE('Piamonte PM'!E44,'Lucido PM'!E44,'Requizo PM '!E44,'Rimas PM '!E44) -> 0 | F44: =AVERAGE('Piamonte PM'!F44,'Lucido PM'!F44,'Requizo PM '!F44,'Rimas PM '!F44) -> 916.66667
B45: Amigo/Complete (14-14-14) | C45: per sack | D45: =AVERAGE('Piamonte PM'!D45,'Lucido PM'!D45,'Requizo PM '!D45,'Rimas PM '!D45) -> 0 | E45: =AVERAGE('Piamonte PM'!E45,'Lucido PM'!E45,'Requizo PM '!E45,'Rimas PM '!E45) -> 0 | F45: =AVERAGE('Piamonte PM'!F45,'Lucido PM'!F45,'Requizo PM '!F45,'Rimas PM '!F45) -> 1533.3333
B46: Viking Blue (46-0-0) | C46: per sack | D46: =AVERAGE('Piamonte PM'!D46,'Lucido PM'!D46,'Requizo PM '!D46,'Rimas PM '!D46) -> 0 | E46: =AVERAGE('Piamonte PM'!E46,'Lucido PM'!E46,'Requizo PM '!E46,'Rimas PM '!E46) -> 0 | F46: =AVERAGE('Piamonte PM'!F46,'Lucido PM'!F46,'Requizo PM '!F46,'Rimas PM '!F46) -> 1716.6667
B47: Viking Yellow | C47: per sack | D47: =AVERAGE('Piamonte PM'!D47,'Lucido PM'!D47,'Requizo PM '!D47,'Rimas PM '!D47) -> 0 | E47: =AVERAGE('Piamonte PM'!E47,'Lucido PM'!E47,'Requizo PM '!E47,'Rimas PM '!E47) -> 0 | F47: =AVERAGE('Piamonte PM'!F47,'Lucido PM'!F47,'Requizo PM '!F47,'Rimas PM '!F47) -> 1666.6667
A48: Note: The prices of different commodities indicated above were based on the prices in Tanauan City Trading Post.
B50: Submitted by:
B53: Sherwin M. Rimas
B54: City Agriculturist

Sheet Piamonte Market
A1: DEPARTMENT OF AGRICULTURE
A2: HIGH VALUE CROPS DEVELOPMENT PROGRAM
A4: SUPPLY AND MARKET PROFILE
A6: Province: Batangas
A7: Municipality: Tanauan City
A9: Barangay | B9: Name (Farmer, Enterprise & Association) | C9: Contact No. | D9: Commodity/ Products Available | E9: Variety | F9: Proposed Crop for next cropping season | G9: Variety2 | H9: Area Planted (ha) | I9: Area Harvested (ha) | J9: Month Planted | K9: Month Harvested | L9: Actual Production (MT) | M9: Column3 | N9: Actual Cost of Production (per area planted) Input Cost + Labor Cost | O9: Cost of Production | P9: Farm Gate Price | Q9: Existing Buyer (Contact person and Contact Number) | R9: Destination | S9: Volume Sold (MT) | T9: Mode of Payment | U9: Mode of Delivery | V9: REMARKS
A10: Montaña | B10: Ronald Alvarez De Guzman | D10: Sigarillas | E10: OPV | H10: 0.3 | J10: August | V10: Damaged by Typhoon Kristine
A11: Montaña | B11: Teotimo Enriquez Dimapilis | D11: Sitao | E11: Maxi Green | H11: 0.25 | J11: August | V11: Damaged by Typhoon Kristine
A12: Montaña | B12: Noriel Arcebuche Tenorio | D12: Pechay | E12: Pavito | H12: 0.25 | J12: August | V12: Damaged by Typhoon Kristine
A13: Montaña | B13: Benito Magsino Maloles | D13: Pechay | E13: Pavito | H13: 0.5 | J13: August | V13: Damaged by Typhoon Kristine
A14: Montaña | B14: Benito Magsino Maloles | D14: Sitao | E14: Mariposa | H14: 0.4 | J14: August | V14: Damaged by Typhoon Kristine
A15: Montaña | B15: Mary Joy Hanie Belmes Hernandez | D15: Pechay | E15: Pavito | H15: 0.6 | J15: August | V15: Damaged by Typhoon Kristine
A16: Montaña | B16: Eufemia Dinglasan Esmedilla | D16: Sigarillas | E16: OPV | H16: 1 | J16: August | V16: Damaged by Typhoon Kristine
A17: Montaña | B17: Eufemia Dinglasan Esmedilla | D17: Pechay | E17: Pavito | H17: 2 | J17: August | V17: Damaged by Typhoon Kristine
A18: Montaña | B18: Rhea Holgado Esmedilla | D18: Sigarillas | E18: OPV | H18: 1.5 | J18: August | V18: Damaged by Typhoon Kristine
A19: Montaña | B19: Leona Hernandez Magsino | D19: Pechay | E19: Pavito | H19: 0.4 | J19: August | V19: Damaged by Typhoon Kristine
A20: Montaña | B20: Jose Nombrado Hernandez | D20: Pechay | E20: Pavito | H20: 3 | J20: August | V20: Damaged by Typhoon Kristine
A21: Montaña | B21: Simeon Garcia Hernandez | D21: Pechay | E21: Black Behi | H21: 0.3 | J21: August | V21: Damaged by Typhoon Kristine
... A35: Bilog- Bilog | B35: Teofilo Manaig Barit | D35: Sitao | E35: Makisig | H35: 0.25 | J35: August | V35: Damaged by Typhoon Kristine
A36: Bilog- Bilog | B36: Teofilo Manaig Barit | D36: Eggplant | E36: Calixto | H36: 0.3 | I36: 0.1 | J36: August | K36: December | L36: 0.11 | O36: 8000 | P36: 60 | Q36: Trader within the City | R36: Tanauan City Trading Post | S36: 0.1 | T36: Cash | U36: Pick- up | V36: Partially damaged
A37: Bilog- Bilog | B37: Victoria Tapia Lumbres | D37: Sigarillas | E37: Tagalog | H37: 0.5 | J37: August | V37: Damaged by Typhoon Kristine
A38: Bilog- Bilog | B38: Victoria Tapia Lumbres | D38: Sitao | E38: Makisig | H38: 0.5 | J38: August | V38: Damaged by Typhoon Kristine
A39: Bilog- Bilog | B39: Victoria Tapia Lumbres | D39: Squash | E39: Tagalog | H39: 1 | J39: August | V39: Damaged by Typhoon Kristine
A40: Bilog- Bilog | B40: Melecio Manalo Benamir | D40: Hot Chili | E40: Dyango F! | H40: 0.25 | J40: August | V40: Damaged by Typhoon Kristine
A41: Bilog- Bilog | B41: Cheryl Cunanan Villanueva | D41: Egpplant | E41: Calixto | H41: 0.5 | I41: 0.3 | J41: August | K41: December | L41: 0.33 | O41: 10000 | P41: 60 | Q41: Trader within the City | R41: Tanauan City Trading Post | S41: 0.33 | T41: Cash | U41: Pick- up | V41: Partially damaged
A42: Bilog- Bilog | B42: Leonida Malabanan Mendoza | D42: Sitao | E42: Galante | H42: 0.3 | J42: August | V42: Damaged by Typhoon Kristine
A43: Bilog- Bilog | B43: Eufrocino Malabao Plaza | D43: Squash | E43: OPV | H43: 0.5 | J43: August | V43: Damaged by Typhoon Kristine
A44: Bilog- Bilog | B44: Guillerma Malabanan Molina | D44: Sigarillas | E44: OPV | H44: 0.5 | J44: August | V44: Damaged by Typhoon Kristine
A45: Bilog- Bilog | B45: Guillerma Malabanan Molina | D45: Sitao | E45: Makisig | H45: 0.5 | J45: August | V45: Damaged by Typhoon Kristine
A46: Sulpoc | B46: Teresita Padilla Ruiz | D46: Pechay | E46: Pavito | H46: 0.9 | J46: August | V46: Damaged by Typhoon Kristine
A47: Sulpoc | B47: Techie Tiña Maranan | D47: Tomato | E47: Tagalog | H47: 0.32 | J47: August | V47: Damaged by Typhoon Kristine
A48: Sulpoc | B48: Melita Manaig Matundan | D48: Beans | E48: OPV | H48: 0.3 | J48: August | V48: Damaged by Typhoon Kristine
A49: Sulpoc | B49: Melita Manaig Matundan | D49: Sigarillas | E49: OPV | H49: 0.4 | J49: August | V49: Damaged by Typhoon Kristine
A50: Sulpoc | B50: Jacobo Maranan Ramilo | D50: Pechay | E50: Pavito | H50: 0.9 | J50: August | V50: Damaged by Typhoon Kristine
A51: Sulpoc | B51: Luz Padilla Molinar | D51: Okra | E51: Smooth Green | H51: 0.7 | I51: 0.5 | J51: August | K51: December | L51: 0.5 | O51: 10000 | P51: 50 | Q51: Trader within the City | R51: Tanauan City Trading Post | S51: 0.5 | T51: Cash | U51: Pick- up | V51: Partially damaged
A52: Sulpoc | B52: Troadio De Ocampo Redondo | D52: Sigarillas | E52: Native | H52: 0.3 | J52: August | V52: Damaged by Typhoon Kristine
A53: Sulpoc | B53: Ryan Enriquez Libelo | D53: Sigarillas | E53: Native | H53: 1 | J53: August | V53: Damaged by Typhoon Kristine
A54: Sulpoc | B54: Ryan Enriquez Libelo | D54: Beans | E54: Jasmine | H54: 1 | J54: August | V54: Damaged by Typhoon Kristine
A55: Sulpoc | B55: Ronald Ocampo Mercado | D55: Pechay | E55: Pavito | H55: 0.8 | J55: August | V55: Damaged by Typhoon Kristine
V56: Damaged by Typhoon Kristine

Sheet Lucido Market
A1: DEPARTMENT OF AGRICULTURE
A2: HIGH VALUE CROPS DEVELOPMENT PROGRAM
A4: SUPPLY AND MARKET PROFILE
A6: Province: Batangas
A7: Municipality: Tanauan City
A9: Barangay | B9: Name (Farmer, Enterprise & Association) | C9: Contact No. | D9: Commodity/ Products Available | E9: Variety | F9: Proposed Crop for next cropping season | G9: Variety2 | H9: Area Planted (ha) | I9: Area Harvested (ha) | J9: Month Planted | K9: Month Harvested | L9: Actual Production (MT) | M9: Column3 | N9: Actual Cost of Production (per area planted) Input Cost + Labor Cost | O9: Cost of Production | P9: Farm Gate Price (kg) | Q9: Existing Buyer (Contact person and Contact Number) | R9: Destination | S9: Volume Sold (MT) | T9: Mode of Payment | U9: Mode of Delivery | V9: REMARKS
L10: This Week | M10: To date
A11: Maugat | B11: CASIMERO CARANDANG GONZALES | D11: Upo | E11: TAGALOG | F11: Sigarilyas | G11: OPV | H11: 0.3 | I11: 0.24 | J11: July | K11: December | L11: 1.2 | M11: 1.2 | N11: 5000 | O11: 15000 | P11: 20 | Q11: Trader within the City | R11: Tanauan City Trading Post | S11: 1.2 | T11: Cash | U11: Picked-up by buyer
A12: Natatas | B12: MELECIO PLATON PECHO | D12: UPO | E12: MAYUMI | F12: Sigarilyas | G12: OPV | H12: 0.25 | I12: 0.2 | J12: July | K12: January | L12: 1 | M12: 1 | N12: 4500 | O12: 15000 | P12: 20 | Q12: Trader within the City | R12: Tanauan City Trading Post | S12: 1 | T12: Cash | U12: Picked-up by buyer
A13: Maugat | B13: DANNY ARIOLA ALVAREZ | D13: EGGPLANT | E13: CALIXTO | F13: Okra | G13: kra Smooth Green | H13: 0.5 | I13: 0.25 | J13: August | K13: February | L13: 1.25 | M13: 1.25 | N13: 35000 | O13: 70000 | P13: 40 | Q13: Trader within the City | R13: Tanauan City Trading Post | S13: 1.25 | T13: Cash | U13: Picked-up by buyer
A14: Maugat | B14: FLORENCIO DELGADO REYES | D14: HOT CHILI/PANIGANG | E14: LABUYO | F14: Eggplant | G14: Fortuner | H14: 0.25 | I14: 0.19 | J14: August | K14: March | L14: 0.95 | M14: 0.95 | N14: 20000 | O14: 80000 | P14: 80 | Q14: Trader within the City | R14: Tanauan City Trading Post | S14: 0.95 | T14: Cash | U14: Picked-up by buyer
A15: Maugat | B15: FLORENCIO DELGADO REYES | D15: TOMATO | E15: DIAMANTE | F15: Hot Chili | G15: Django | H15: 0.25 | I15: 0.19 | J15: August | K15: April | L15: 0.95 | M15: 0.95 | N15: 25000 | O15: 100000 | P15: 50 | Q15: Trader within the City | R15: Tanauan City Trading Post | S15: 0.95 | T15: Cash | U15: Picked-up by buyer
A16: Cale | B16: Teodora Olivar | D16: Bataw | E16: Native | F16: Okra | G16: Smooth Green | H16: 0.3 | I16: 0.24 | J16: September | K16: May | L16: 1.2 | M16: 1.2 | N16: 3500 | O16: 10000 | P16: 20 | Q16: Trader within the City | R16: Tanauan City Trading Post | S16: 1.2 | T16: Cash | U16: Picked-up by buyer
A17: Suplang | B17: Reynante Ramilo | D17: Beans | E17: Sagana | F17: Tomato | G17: Diamante | H17: 0.4 | I17: 0.32 | J17: September | K17: June | L17: 1.6 | M17: 1.6 | N17: 8000 | O17: 20000 | P17: 90 | Q17: Trader within the City | R17: Tanauan City Trading Post | S17: 1.6 | T17: Cash | U17: Picked-up by buyer

Sheet Requizo Market
A1: DEPARTMENT OF AGRICULTURE
A2: HIGH VALUE CROPS DEVELOPMENT PROGRAM
A4: SUPPLY AND MARKET PROFILE
A6: Province: Batangas
A7: Municipality: Tanauan City
A9: Barangay | B9: Name (Farmer, Enterprise & Association) | C9: Contact No. | D9: Commodity/ Products Available | E9: Variety | F9: Proposed Crop for next cropping season | G9: Variety2 | H9: Area Planted (ha) | I9: Area Harvested (ha) | J9: Month Planted | K9: Month Harvested | L9: Actual Production (MT) | M9: Column3 | N9: Actual Cost of Production (per area planted) Input Cost + Labor Cost | O9: Cost of Production | P9: Farm Gate Price | Q9: Existing Buyer (Contact person and Contact Number) | R9: Destination | S9: Volume Sold (MT) | T9: Mode of Payment | U9: Mode of Delivery | V9: REMARKS
L10: This Week | M10: To date
A11: Trapiche | B11: Leston Gerald Molinyawe Maglantay | D11: Pechay | E11: Pavito | F11: Mustasa | G11: - | H11: 1 | I11: 1 | J11: 10/22/2024 | K11: 45627 | L11: 9 | M11: 9 | N11: 0 | O11: 15000 | P11: 25 | Q11: Trader | R11: Trading Post | S11: 9 | T11: Cash | U11: Pick- up | V11: HARVESTED

Sheet Rimas Market
A1: DEPARTMENT OF AGRICULTURE
A2: HIGH VALUE CROPS DEVELOPMENT PROGRAM
A4: SUPPLY AND MARKET PROFILE
A6: Province: Batangas
A7: Municipality: Tanauan City
A9: Barangay | B9: Name (Farmer, Enterprise & Association) | C9: Contact No. | D9: Commodity/ Products Available | E9: Variety | F9: Proposed Crop for next cropping season | G9: Variety2 | H9: Area Planted (ha) | I9: Area Harvested (ha) | J9: Month Planted | K9: Month Harvested | L9: Actual Production (MT) | M9: Column3 | N9: Actual Cost of Production (per area planted) Input Cost + Labor Cost | O9: Cost of Production | P9: Farm Gate Price | Q9: Existing Buyer (Contact person and Contact Number) | R9: Destination | S9: Volume Sold (MT) | T9: Mode of Payment | U9: Mode of Delivery | V9: REMARKS
